Workbook
Name QA: BaseData!$A$2:$A$29

Sheet Instructions
B2: Prerequisite
B3: 1 | C3: You will need JIRA username and Token to use the tool. JIRA Username is your maxxton email address that you use for login to JIRA. Token needs to be created from https://support.atlassian.com/atlassian-account/docs/manage-api-tokens-for-your-atlassian-account/ Token creation is one time activity... Store your token as you can not retrieve it again from above link(only option will be to recreate it)
B4: 2 | C4: You will be asked to give permission from your Google Account when you run this tool for first time; and it's safe to do so ! ;)
B7: Schedule test case for execution
B8: 1 | C8: Go to worksheet of your module.
B9: 2 | C9: For the test case you want to schedule for execution, Update column H with value 'Y' indicating that you want to schedule it. You should set execution priority in column I and Execution By (assignee) in column J
B10: 3 | C10: From 'QA Project' menu, select 'Schedule Test Execution' option
B11: 4 | C11: You will be asked to provide JIRA username and Token.
B12: 5 | C12: You will also need to provide Release Information and Due Date for test result tickets.
B13: 6 | C13: Next give confirmation for scheduling selected test cases.
B14: 7 | C14: Column K and L should be populated with information about Test Result ticket and scheduling information.
B15: 8 | C15: You should also receive an email with details of newly created tickets.
B17: Creat new test case
B18: 1 | C18: Go to worksheet of your module.
B19: 2 | C19: Add value 'NEW' in column A of next empty row. Provide Summary, Priority, Component and Epic Link and Estimate(use JIRA format for estimate - eg 30m, 2h).
B20: 3 | C20: From 'QA Project' menu, select 'Create Test Case' option
B21: 4 | C21: You will be asked to provide JIRA username and Token.
B22: 5 | C22: Next give confirmation for uploading new test cases.
B23: 6 | C23: Column A should be populated with new test case key.
B24: 7 | C24: You should also receive an email with details of newly created tickets.

Sheet Summary
E1: Newyse | F1: CMS | G1: MXTS | H1: MCMS
F2: *v222* | G2: *2023_Week_27* | H2: *149*
C4: Team | D4: Total Test Cases | E4: Scheduled? | G4: Team | H4: Total Test Cases | I4: Scheduled?
C5: Newyse | D5: =Newyse!G2 -> 0 | E5: =countif(Newyse!L:L,$E$2) -> 0 | G5: Newyse | H5: =D5 -> 0 | I5: =E5 -> 0
C6: CMS | D6: =CMS!G2 -> 22 | E6: =countif(CMS!L:L,$F$2) -> 0 | G6: CMS | H6: =D6 -> 22 | I6: =E6 -> 0
C7: MCMS | D7: =MCMS!G2 -> 86 | E7: =countif(MCMS!L:L,$H$2) -> 0 | G7: MCMS | H7: =D7 -> 86 | I7: =E7 -> 0
C8: Rates | D8: =Rates!G2 -> 10 | E8: =countif(Rates!L:L,$G$2) -> 0 | G8: MXTS | H8: =sum(D8:D16) -> 199 | I8: =sum(E8:E16) -> 0
C9: Finance | D9: =Finance!G2 -> 11 | E9: =countif(Finance!L:L,$G$2) -> 0
C10: Operations | D10: =Operations!G2 -> 27 | E10: =countif(Operations!L:L,$G$2) -> 0
C11: Channel | D11: =Channel!G2 -> 17 | E11: =countif(Channel!L:L,$G$2) -> 0
C12: Revenue | D12: =Revenue!G2 -> 9 | E12: =countif(Revenue!L:L,$G$2) -> 0
C13: Reservations | D13: =Reservations!G2 -> 35 | E13: =countif(Reservations!L:L,$G$2) -> 0
C14: API | D14: =API!G2 -> 43 | E14: =countif(API!L:L,$G$2) -> 0
C15: CCM | D15: =CCM!G2 -> 22 | E15: =countif(CCM!L:L,$G$2) -> 0
C16: Content | D16: =Content!G2 -> 25 | E16: =countif(Content!L:L,$G$2) -> 0

Sheet Newyse
N1: Components | O1: Epic
F2: Total Test Cases | G2: =countifs(A:A,"<>NEW",A:A,"<>")-1 -> 0 | N2: CMS-Castle BM | O2: QA-1 | P2: Newyse Regression Test Cases
F3: Schedule? Y | G3: =countif(H:H,"=Y") -> 0 | N3: CMS-Castle MyEnv | O3: QA-24 | P3: CMS Regression Test Cases
F4: New Test Cases | G4: =COUNTIF(A:A,"=NEW") -> 0 | N4: CMS-Contempo BM | O4: QA-25 | P4: CMS Live Test Cases
N5: CMS-Contempo MyEnv | O5: QA-26 | P5: CMS Sanity Test Cases
A6: Key | B6: Summary | C6: Priority | D6: Component | E6: Epic Link | F6: Test Case Assignee | G6: Estimate | H6: Schedule ? | I6: Execution Priority | J6: Execution By | K6: Test Result Ticket | L6: Comments | N6: CMS-Deepcreek BM | O6: QA-54 | P6: Newyse Live Test Cases
N7: CMS-Deepcreek MyEnv | O7: QA-55 | P7: Newyse Sanity Test Cases
N8: CMS-Hogenboom BM | O8: QA-71 | P8: MXTS Sanity Test Cases
N9: CMS-Hogenboom MyEnv | O9: QA-72 | P9: MXTS Regression Test Cases
N10: CMS-Krim BM
N11: CMS-Krim MyEnv
N12: CMS-PerfectExp BM
N13: CMS-PerfectExp MyEnv
N14: CMS-Roompot BM
N15: CMS-Roompot MyEnv
N16: CMS-Siblu BM
N17: CMS-Siblu MyEnv
N18: MXTS-BackOffice Manager
N19: MXTS-Content Manager
N20: MXTS-Implementation Manager
N21: MXTS-Owner Manager
... N26: CMS-EuroparcsNL MyEnv

Sheet CMS
N1: Components | O1: Epic
F2: Total Test Cases | G2: =countifs(A:A,"<>NEW",A:A,"<>")-1 -> 22 | N2: CMS-Castle BM | O2: QA-1 | P2: Newyse Regression Test Cases
F3: Schedule? Y | G3: =countif(H:H,"=Y") -> 6 | N3: CMS-Castle MyEnv | O3: QA-24 | P3: CMS Regression Test Cases
F4: New Test Cases | G4: =COUNTIF(A:A,"=NEW") -> 0 | N4: CMS-Contempo BM | O4: QA-25 | P4: CMS Live Test Cases
N5: CMS-Contempo MyEnv | O5: QA-26 | P5: CMS Sanity Test Cases
A6: Key | B6: Summary | C6: Priority | D6: Component | E6: Epic Link | F6: Test Case Assignee | G6: Estimate | H6: Schedule ? | I6: Execution Priority | J6: Execution By | K6: Test Result Ticket | L6: Comments | N6: CMS-Deepcreek BM | O6: QA-54 | P6: Newyse Live Test Cases
A7: QA-73 | B7: RT_Castle Booking Module | C7: P3 | D7: CMS-Castle BM | E7: QA-24 | F7: Prajwal Atkare | G7: 180m | H7: N | I7: P3 | J7: Jyoti Koli | K7: =HYPERLINK("https://maxxton.atlassian.net/browse/QA-21812","QA-21812") -> QA-21812 | L7: Created on 2025-01-03 for release CMSv262 | N7: CMS-Deepcreek MyEnv | O7: QA-55 | P7: Newyse Sanity Test Cases
A8: QA-102 | B8: RT_Hogenboom Booking Module | C8: P3 | D8: CMS-Hogenboom BM | E8: QA-24 | F8: Jyoti Koli | G8: 180m | H8: N | I8: P3 | J8: Jyoti Koli | K8: =HYPERLINK("https://maxxton.atlassian.net/browse/QA-15771","QA-15771") -> QA-15771 | L8: Created on 2023-12-08 for release CMSv234 | N8: CMS-Hogenboom BM | O8: QA-71 | P8: MXTS Sanity Test Cases
A9: QA-103 | B9: RT_Roompot Booking Module | C9: P3 | D9: CMS-Roompot BM | E9: QA-24 | F9: Jyoti Koli | G9: 180m | H9: N | I9: P3 | J9: Jyoti Koli | K9: =HYPERLINK("https://maxxton.atlassian.net/browse/QA-22266","QA-22266") -> QA-22266 | L9: Created on 2025-01-31 for release CMSv64 | N9: CMS-Hogenboom MyEnv | O9: QA-72 | P9: MXTS Regression Test Cases
A10: QA-79 | B10: RT_Castle My Environment | C10: P3 | D10: CMS-Castle MyEnv | E10: QA-24 | F10: Sujata Pimpale | G10: 60m | H10: N | I10: P3 | J10: Jyoti Koli | K10: =HYPERLINK("https://maxxton.atlassian.net/browse/QA-22267","QA-22267") -> QA-22267 | L10: Created on 2025-01-31 for release CMSv64 | N10: CMS-Krim BM
A11: QA-82 | B11: RT_Hogenboom My Environment | C11: P3 | D11: CMS-Hogenboom MyEnv | E11: QA-24 | F11: Prajwal Atkare | G11: 60m | H11: N | I11: P3 | J11: Jyoti Koli | K11: =HYPERLINK("https://maxxton.atlassian.net/browse/QA-11981","QA-11981") -> QA-11981 | L11: Created on 2023-02-03 for release CMSv212 | N11: CMS-Krim MyEnv
A12: QA-83 | B12: RT_Krim My Environment | C12: P3 | D12: CMS-Krim MyEnv | E12: QA-24 | F12: Prajwal Atkare | G12: 60m | H12: N | I12: P3 | J12: Sujata Pimpale | K12: =HYPERLINK("https://maxxton.atlassian.net/browse/QA-22268","QA-22268") -> QA-22268 | L12: Created on 2025-01-31 for release CMSv64 | N12: CMS-PerfectExp BM
A13: QA-84 | B13: RT_Roompot My Environment | C13: P3 | D13: CMS-Roompot MyEnv | E13: QA-24 | F13: Jyoti Koli | G13: 60m | H13: N | I13: P3 | J13: Jyoti Koli | K13: =HYPERLINK("https://maxxton.atlassian.net/browse/QA-22269","QA-22269") -> QA-22269 | L13: Created on 2025-01-31 for release CMSv64 | N13: CMS-PerfectExp MyEnv
A14: QA-85 | B14: RT_Siblu My Environment | C14: P3 | D14: CMS-Siblu MyEnv | E14: QA-24 | F14: Prajwal Atkare | G14: 60m | H14: N | I14: P3 | J14: Sujata Pimpale | K14: =HYPERLINK("https://maxxton.atlassian.net/browse/QA-22270","QA-22270") -> QA-22270 | L14: Created on 2025-01-31 for release CMSv64 | N14: CMS-Roompot BM
A15: QA-3539 | B15: RT_CMS Webservices - TC1 | C15: P3 | D15: CMS-WebServices | E15: QA-24 | F15: Sujata Pimpale | H15: N | I15: P3 | J15: Jyoti Koli | K15: =HYPERLINK("https://maxxton.atlassian.net/browse/QA-22045","QA-22045") -> QA-22045 | L15: Created on 2025-01-17 for release CMSv263 | N15: CMS-Roompot MyEnv
A16: QA-1565 | B16: RT_Roompot Mobile Bookings Module | C16: P3 | D16: CMS-Roompot BM | E16: QA-24 | F16: Jyoti Koli | G16: 180m | H16: N | I16: P3 | J16: Jyoti Koli | K16: =HYPERLINK("https://maxxton.atlassian.net/browse/QA-22271","QA-22271") -> QA-22271 | L16: Created on 2025-01-31 for release CMSv64 | N16: CMS-Siblu BM
A17: QA-6801 | B17: RT_RCN My Environment | C17: P3 | D17: CMS-RCN MyEnv | E17: QA-24 | F17: Sujata Pimpale | G17: 90m | H17: N | I17: P3 | J17: Prajwal Atkare | K17: =HYPERLINK("https://maxxton.atlassian.net/browse/QA-21210","QA-21210") -> QA-21210 | L17: Created on 2024-11-25 for release CMSv259 | N17: CMS-Siblu MyEnv | Q17: =vlookup(J17,BaseData!A:B,2) -> 625a7ab04f1d57006a26d692
A18: QA-6802 | B18: RT_EuroparcsNL My Environment | C18: P3 | D18: CMS-EuroparcsNL MyEnv | E18: QA-24 | F18: Sujata Pimpale | G18: 90m | H18: N | I18: P3 | J18: Prajwal Atkare | K18: =HYPERLINK("https://maxxton.atlassian.net/browse/QA-21680","QA-21680") -> QA-21680 | L18: Created on 2024-12-20 for release CMSv261 | N18: MXTS-BackOffice Manager
A19: QA-86 | B19: LT_Castle Booking Module | C19: P2 | D19: CMS-Castle BM | E19: QA-25 | F19: Prajwal Atkare | G19: 20m | H19: N | I19: P2 | J19: Jyoti Koli | K19: =HYPERLINK("https://maxxton.atlassian.net/browse/QA-21841","QA-21841") -> QA-21841 | L19: Created on 2025-01-07 for release CMSv262 | N19: MXTS-Content Manager
A20: QA-89 | B20: LT_Hogenboom Booking Module | C20: P2 | D20: CMS-Hogenboom BM | E20: QA-25 | F20: Sujata Pimpale | G20: 20m | H20: N | I20: P2 | J20: Prajwal Atkare | K20: =HYPERLINK("https://maxxton.atlassian.net/browse/QA-19766","QA-19766") -> QA-19766 | L20: Created on 2024-09-03 for release CMSv253 | N20: MXTS-Implementation Manager
A21: QA-91 | B21: LT_Roompot Booking Module | C21: P2 | D21: CMS-Roompot BM | E21: QA-25 | F21: Jyoti Koli | G21: 20m | H21: Y | I21: P2 | J21: Jyoti Koli | K21: =HYPERLINK("https://maxxton.atlassian.net/browse/QA-22288","QA-22288") -> QA-22288 | L21: Created on 2025-02-04 for release CMSv264 | N21: MXTS-Owner Manager
A22: QA-93 | B22: LT_Castle My Environment | C22: P2 | D22: CMS-Castle MyEnv | E22: QA-25 | F22: Prajwal Atkare | G22: 20m | H22: Y | I22: P2 | J22: Jyoti Koli | K22: =HYPERLINK("https://maxxton.atlassian.net/browse/QA-22289","QA-22289") -> QA-22289 | L22: Created on 2025-02-04 for release CMSv264 | N22: MXTS-Rate Manager
A23: QA-96 | B23: LT_Hogenboom My Environment | C23: P2 | D23: CMS-Hogenboom MyEnv | E23: QA-25 | F23: Sujata Pimpale | G23: 20m | H23: N | I23: P2 | J23: Prajwal Atkare | K23: =HYPERLINK("https://maxxton.atlassian.net/browse/QA-19769","QA-19769") -> QA-19769 | L23: Created on 2024-09-03 for release CMSv253 | N23: MXTS-Reservation Manager
A24: QA-97 | B24: LT_Krim My Environment | C24: P2 | D24: CMS-Krim MyEnv | E24: QA-25 | F24: Prajwal Atkare | G24: 20m | H24: Y | I24: P2 | J24: Jyoti Koli | K24: =HYPERLINK("https://maxxton.atlassian.net/browse/QA-22290","QA-22290") -> QA-22290 | L24: Created on 2025-02-04 for release CMSv264 | N24: MXTS-PaymentService
A25: QA-98 | B25: LT_Roompot My Environment | C25: P2 | D25: CMS-Roompot MyEnv | E25: QA-25 | F25: Jyoti Koli | G25: 20m | H25: Y | I25: P2 | J25: Jyoti Koli | K25: =HYPERLINK("https://maxxton.atlassian.net/browse/QA-22291","QA-22291") -> QA-22291 | L25: Created on 2025-02-04 for release CMSv264 | N25: CMS-RCN MyEnv
A26: QA-99 | B26: LT_Siblu My Environment | C26: P2 | D26: CMS-Siblu MyEnv | E26: QA-25 | F26: Prajwal Atkare | G26: 20m | H26: Y | I26: P2 | J26: Jyoti Koli | K26: =HYPERLINK("https://maxxton.atlassian.net/browse/QA-22292","QA-22292") -> QA-22292 | L26: Created on 2025-02-04 for release CMSv264 | N26: CMS-EuroparcsNL MyEnv
A27: QA-1613 | B27: LT_Roompot Mobile Bookings module | C27: P2 | D27: CMS-Roompot BM | E27: QA-25 | F27: Jyoti Koli | G27: 20m | H27: Y | I27: P2 | J27: Jyoti Koli | K27: =HYPERLINK("https://maxxton.atlassian.net/browse/QA-22293","QA-22293") -> QA-22293 | L27: Created on 2025-02-04 for release CMSv264
A28: QA-6803 | B28: LT_EuroparcsNL My Environment | C28: P2 | D28: CMS-EuroparcsNL MyEnv | E28: QA-25 | F28: Sujata Pimpale | G28: 20m | H28: N | I28: P2 | J28: Prajwal Atkare | K28: =HYPERLINK("https://maxxton.atlassian.net/browse/QA-21689","QA-21689") -> QA-21689 | L28: Created on 2024-12-24 for release CMSv261

Sheet API
O1: Components | P1: Epic
F2: Total Test Cases | G2: =countifs(A:A,"<>NEW",A:A,"<>")-1 -> 43 | O2: API_Manager | P2: QA-1 | Q2: Newyse Regression Test Cases
F3: Schedule? Y | G3: =countif(H:H,"=Y") -> 17 | O3: API_PropertyDetails | P3: QA-24 | Q3: CMS Regression Test Cases
F4: New Test Cases | G4: =COUNTIF(A:A,"=NEW") -> 0 | O4: API_Customer Related | P4: QA-25 | Q4: CMS Live Test Cases
O5: API_BatchEventDelta | P5: QA-26 | Q5: CMS Sanity Test Cases
A6: Key | B6: Summary | C6: Priority | D6: Component | E6: Epic Link | F6: Test Case Assignee | G6: Estimate | H6: Schedule ? | I6: Execution Priority | J6: Execution By | K6: Test Result Ticket | L6: Comments | M6: Original Estimates | N6: Remaining Estimates | O6: API_Owner Related | P6: QA-54 | Q6: Newyse Live Test Cases
A7: QA-1429 | B7: RT_API_Property_Details_Resort_P1 | C7: P1 | D7: TPI_Resorts | E7: QA-1223 | G7: 30m | H7: Y | I7: P1 | J7: Anup Sinha | K7: =HYPERLINK("https://maxxton.atlassian.net/browse/QA-24859","QA-24859") -> QA-24859 | L7: Created on 2025-06-27 for release 2025_Week_27 | M7: 2 | O7: API_SearchAndBook | P7: QA-55 | Q7: Newyse Sanity Test Cases
A8: QA-1431 | B8: RT_API_Property_Details_Units_P1 | C8: P1 | D8: TPI_Units | E8: QA-1223 | G8: 2h | H8: Y | I8: P1 | J8: Dhiraj Bobade | K8: =HYPERLINK("https://maxxton.atlassian.net/browse/QA-24860","QA-24860") -> QA-24860 | L8: Created on 2025-06-27 for release 2025_Week_27 | M8: 2 | O8: API_Master Data | P8: QA-71 | Q8: MXTS Sanity Test Cases
A9: QA-1432 | B9: RT_API_Property_Details_Accommodationtypes_P1 | C9: P1 | D9: TPI_AccommodationTpes | E9: QA-1223 | G9: 2h | H9: Y | I9: P1 | J9: Dhiraj Bobade | K9: =HYPERLINK("https://maxxton.atlassian.net/browse/QA-24861","QA-24861") -> QA-24861 | L9: Created on 2025-06-27 for release 2025_Week_27 | M9: 2 | P9: QA-72 | Q9: MXTS Regression Test Cases
A10: QA-1433 | B10: RT_API_Property_Details_Accommodationtypes_P2 | C10: P2 | D10: TPI_AccommodationTpes | E10: QA-1223 | G10: 4h | H10: N | I10: P2 | J10: Anup Sinha | K10: =HYPERLINK("https://maxxton.atlassian.net/browse/QA-22977","QA-22977") -> QA-22977 | L10: Created on 2025-03-12 for release
A11: QA-1250 | B11: RT_API_Property_Details_Units_P2 | C11: P2 | D11: TPI_Units | E11: QA-1223 | G11: 4h | H11: N | I11: P2 | J11: Anup Sinha | K11: =HYPERLINK("https://maxxton.atlassian.net/browse/QA-22978","QA-22978") -> QA-22978 | L11: Created on 2025-03-12 for release
A12: QA-1430 | B12: RT_API_Property_Details_Resort_P2 | C12: P2 | D12: TPI_Resorts | E12: QA-1223 | G12: 4h | H12: N | I12: P2 | J12: Anup Sinha | K12: =HYPERLINK("https://maxxton.atlassian.net/browse/QA-22979","QA-22979") -> QA-22979 | L12: Created on 2025-03-12 for release
A13: QA-1473 | B13: RT_API_Property_Details_Offers_P1 | C13: P1 | D13: TPI_Offers | E13: QA-1223 | G13: 4h | H13: Y | I13: P1 | J13: Dhiraj Bobade | K13: =HYPERLINK("https://maxxton.atlassian.net/browse/QA-24862","QA-24862") -> QA-24862 | L13: Created on 2025-06-27 for release 2025_Week_27 | M13: 1
A14: QA-1475 | B14: RT_API_Property_Details_AddOn_P1 | C14: P1 | D14: TPI_AddOn | E14: QA-1223 | G14: 1h | H14: Y | I14: P1 | J14: Dhiraj Bobade | K14: =HYPERLINK("https://maxxton.atlassian.net/browse/QA-24863","QA-24863") -> QA-24863 | L14: Created on 2025-06-27 for release 2025_Week_27 | M14: 1
A15: QA-1501 | B15: RT_API_Property_Details_Amenity_P1 | C15: P1 | D15: TPI_Amenity | E15: QA-1223 | G15: 1h | H15: Y | I15: P1 | J15: Anup Sinha | K15: =HYPERLINK("https://maxxton.atlassian.net/browse/QA-24864","QA-24864") -> QA-24864 | L15: Created on 2025-06-27 for release 2025_Week_27 | M15: 30m
A16: QA-1534 | B16: API_Customer_P1 | C16: P1 | D16: TPI_Customer | E16: QA-1223 | G16: 4h | H16: Y | I16: P1 | J16: Aparna Shinde | K16: =HYPERLINK("https://maxxton.atlassian.net/browse/QA-24865","QA-24865") -> QA-24865 | L16: Created on 2025-06-27 for release 2025_Week_27 | M16: 1
A17: QA-1512 | B17: API_Batches/Delta/Events _Event_P1 | C17: P1 | D17: TPI_Events | E17: QA-1223 | G17: 2h | H17: N | I17: P1 | J17: Aparna Shinde | K17: =HYPERLINK("https://maxxton.atlassian.net/browse/QA-22740","QA-22740") -> QA-22740 | L17: Created on 2025-03-07 for release 2025_Week_11 | M17: 30m
A18: QA-1513 | B18: API_Owner_P1 | C18: P1 | D18: TPI_owners | E18: QA-1223 | G18: 4h | H18: Y | I18: P1 | J18: Anup Sinha | K18: =HYPERLINK("https://maxxton.atlassian.net/browse/QA-24866","QA-24866") -> QA-24866 | L18: Created on 2025-06-27 for release 2025_Week_27 | M18: 2
A19: QA-1514 | B19: API_Owner_P2 | C19: P2 | D19: TPI_owners | E19: QA-1223 | G19: 5h | H19: N | I19: P2 | J19: Aparna Shinde | K19: =HYPERLINK("https://maxxton.atlassian.net/browse/QA-22980","QA-22980") -> QA-22980 | L19: Created on 2025-03-12 for release
A20: QA-2737 | B20: API_Accommodation_Search | C20: P1 | D20: TPI_SearchAndBook | E20: QA-1223 | G20: 1h | H20: Y | I20: P1 | J20: Aparna Shinde | K20: =HYPERLINK("https://maxxton.atlassian.net/browse/QA-24867","QA-24867") -> QA-24867 | L20: Created on 2025-06-27 for release 2025_Week_27 | M20: 30m
A21: QA-2738 | B21: API_Accommodation_Range_Search | C21: P1 | D21: TPI_SearchAndBook | E21: QA-1223 | G21: 1h | H21: Y | I21: P1 | J21: Anup Sinha | K21: =HYPERLINK("https://maxxton.atlassian.net/browse/QA-24868","QA-24868") -> QA-24868 | L21: Created on 2025-06-27 for release 2025_Week_27 | M21: 30m
A22: QA-1508 | B22: API_Reservations_P1_Reservation_proposal | C22: P1 | D22: TPI_Reservations/TPI_ReservationProposal | E22: QA-1223 | G22: 2h | H22: Y | I22: P1 | J22: Aparna Shinde | K22: =HYPERLINK("https://maxxton.atlassian.net/browse/QA-24869","QA-24869") -> QA-24869 | L22: Created on 2025-06-27 for release 2025_Week_27 | M22: 1h 30m
A23: QA-1531 | B23: API_Reservations_P1_Reservations | C23: P1 | D23: TPI_Reservations | E23: QA-1223 | G23: 2h | H23: Y | I23: P1 | J23: Aparna Shinde | K23: =HYPERLINK("https://maxxton.atlassian.net/browse/QA-24870","QA-24870") -> QA-24870 | L23: Created on 2025-06-27 for release 2025_Week_27 | M23: 1h 30m
A24: QA-1532 | B24: API_Reservations_P1_Others | C24: P1 | D24: TPI_Reservations | E24: QA-1223 | G24: 4h | H24: Y | I24: P1 | J24: Anup Sinha | K24: =HYPERLINK("https://maxxton.atlassian.net/browse/QA-24871","QA-24871") -> QA-24871 | L24: Created on 2025-06-27 for release 2025_Week_27 | M24: 3h
A25: QA-1506 | B25: API_Master Data_P1 | C25: P1 | D25: TPI_MasterData | E25: QA-1223 | G25: 2h | H25: Y | I25: P1 | J25: Aparna Shinde | K25: =HYPERLINK("https://maxxton.atlassian.net/browse/QA-24872","QA-24872") -> QA-24872 | L25: Created on 2025-06-27 for release 2025_Week_27 | M25: 45m
A26: QA-9613 | B26: To view recent requests of an API user | C26: P3 | D26: TPI_IntegrationManager | E26: QA-9605 | G26: 2h | H26: N | I26: P3 | J26: Aparna Shinde | K26: =HYPERLINK("https://maxxton.atlassian.net/browse/QA-17792","QA-17792") -> QA-17792 | L26: Created on 2024-05-02 for release 2024_Week_19 | M26: 15m
A27: QA-9606 | B27: API user Creation | C27: P3 | D27: TPI_IntegrationManager | E27: QA-9605 | G27: 30m | H27: N | I27: P3 | J27: Aparna Shinde | K27: =HYPERLINK("https://maxxton.atlassian.net/browse/QA-17793","QA-17793") -> QA-17793 | L27: Created on 2024-05-02 for release 2024_Week_19 | M27: 1h
A28: QA-9607 | B28: To view and add new credentials for an API user | C28: P3 | D28: TPI_IntegrationManager | E28: QA-9605 | G28: 30m | H28: N | I28: P3 | J28: Aparna Shinde | K28: =HYPERLINK("https://maxxton.atlassian.net/browse/QA-17794","QA-17794") -> QA-17794 | L28: Created on 2024-05-02 for release 2024_Week_19 | M28: 30m
A29: QA-9608 | B29: To view and update Linked Locations for an API user | C29: P3 | D29: TPI_IntegrationManager | E29: QA-9605 | G29: 30m | H29: N | I29: P3 | J29: Aparna Shinde | K29: =HYPERLINK("https://maxxton.atlassian.net/browse/QA-17795","QA-17795") -> QA-17795 | L29: Created on 2024-05-02 for release 2024_Week_19 | M29: 30m
A30: QA-9609 | B30: Updating Permissions for an API user | C30: P3 | D30: TPI_IntegrationManager | E30: QA-9605 | G30: 30m | H30: N | I30: P3 | J30: Aparna Shinde | K30: =HYPERLINK("https://maxxton.atlassian.net/browse/QA-17796","QA-17796") -> QA-17796 | L30: Created on 2024-05-02 for release 2024_Week_19 | M30: 30m
A31: QA-9610 | B31: Calculating API usage costs | C31: P3 | D31: TPI_IntegrationManager | E31: QA-9605 | G31: 30m | H31: N | I31: P3 | J31: Aparna Shinde | K31: =HYPERLINK("https://maxxton.atlassian.net/browse/QA-17797","QA-17797") -> QA-17797 | L31: Created on 2024-05-02 for release 2024_Week_19 | M31: 20m
A32: QA-9611 | B32: To view and add new admin organizations for an API user | C32: P3 | D32: TPI_IntegrationManager | E32: QA-9605 | G32: 30m | H32: N | I32: P3 | J32: Aparna Shinde | K32: =HYPERLINK("https://maxxton.atlassian.net/browse/QA-17798","QA-17798") -> QA-17798 | L32: Created on 2024-05-02 for release 2024_Week_19 | M32: 30m
A33: QA-9612 | B33: Searching an API user and viewing API documentation | C33: P3 | D33: TPI_IntegrationManager | E33: QA-9605 | G33: 30m | H33: N | I33: P3 | J33: Aparna Shinde | K33: =HYPERLINK("https://maxxton.atlassian.net/browse/QA-17799","QA-17799") -> QA-17799 | L33: Created on 2024-05-02 for release 2024_Week_19 | M33: 15m | O33: Anup Sinha | P33: =COUNTIF(J7:J41, "*Anup Sinha*") -> 13
A34: QA-1505 | B34: API_Representations_P1 | C34: P1 | D34: TPI_Representations | E34: QA-1223 | G34: 2h | H34: N | I34: P1 | J34: Anup Sinha | K34: =HYPERLINK("https://maxxton.atlassian.net/browse/QA-22981","QA-22981") -> QA-22981 | L34: Created on 2025-03-12 for release | O34: Rohan Bhegade | P34: =COUNTIF(J7:J41, "*Rohan Bhegade*") -> 0
A35: QA-1503 | B35: API_UnitReservability/Reservability_P1 | C35: P1 | D35: TPI_Reservability | E35: QA-1223 | G35: 2h | H35: N | I35: P1 | J35: Anup Sinha | K35: =HYPERLINK("https://maxxton.atlassian.net/browse/QA-22982","QA-22982") -> QA-22982 | L35: Created on 2025-03-12 for release | O35: Aparna Shinde | P35: =COUNTIF(J1:J41, "Aparna Shinde") -> 16
A36: =HYPERLINK("https://maxxton.atlassian.net/browse/QA-10650","QA-10650") -> QA-10650 | B36: API_Housekeepings | C36: P1 | D36: TPI_Housekeeping | E36: QA-1223 | G36: 30m | H36: Y | I36: P1 | J36: Anup Sinha | K36: =HYPERLINK("https://maxxton.atlassian.net/browse/QA-24873","QA-24873") -> QA-24873 | L36: Created on 2025-06-27 for release 2025_Week_27 | M36: 1
A37: =HYPERLINK("https://maxxton.atlassian.net/browse/QA-11287","QA-11287") -> QA-11287 | B37: API_Infotexts_P1 | C37: P1 | D37: TPI_Infotexts | E37: QA-1223 | G37: 1h | H37: Y | I37: P1 | J37: Dhiraj Bobade | K37: =HYPERLINK("https://maxxton.atlassian.net/browse/QA-24874","QA-24874") -> QA-24874 | L37: Created on 2025-06-27 for release 2025_Week_27 | M37: 1
A38: =HYPERLINK("https://maxxton.atlassian.net/browse/QA-14981","QA-14981") -> QA-14981 | B38: API_Employee_P1 | C38: P1 | D38: TPI_Employee | E38: QA-1223 | G38: 60m | H38: N | I38: P1 | J38: Aparna Shinde | K38: =HYPERLINK("https://maxxton.atlassian.net/browse/QA-22985","QA-22985") -> QA-22985 | L38: Created on 2025-03-12 for release | M38: 1
A39: =HYPERLINK("https://maxxton.atlassian.net/browse/QA-15098","QA-15098") -> QA-15098 | B39: API_Operations_P1 | C39: P1 | D39: TPI_Operations | E39: QA-1223 | G39: 1h | H39: Y | I39: P1 | J39: Dhiraj Bobade | K39: =HYPERLINK("https://maxxton.atlassian.net/browse/QA-24875","QA-24875") -> QA-24875 | L39: Created on 2025-06-27 for release 2025_Week_27 | M39: 1
A40: QA-15099 | B40: API_Packages_P2 | C40: P3 | D40: TPI_Packages | E40: QA-1223 | G40: 30m | H40: N | I40: P3 | J40: Anup Sinha | K40: =HYPERLINK("https://maxxton.atlassian.net/browse/QA-22987","QA-22987") -> QA-22987 | L40: Created on 2025-03-12 for release | M40: 1
A41: =HYPERLINK("https://maxxton.atlassian.net/browse/QA-15100","QA-15100") -> QA-15100 | B41: API_PointOfinterests_P2 | C41: P3 | D41: TPI_PointOfIntrestes | E41: QA-1223 | G41: 30m | H41: N | I41: P3 | J41: Anup Sinha | K41: =HYPERLINK("https://maxxton.atlassian.net/browse/QA-22988","QA-22988") -> QA-22988 | L41: Created on 2025-03-12 for release | M41: 1
A42: =HYPERLINK("https://maxxton.atlassian.net/browse/QA-22963","QA-22963") -> QA-22963 | B42: API_AdminOrganisation_P2 | C42: P2 | D42: TPI_PointOfIntrestes | E42: QA-1223 | F42: Aparna Shinde | G42: 45m | H42: N | I42: P2 | J42: Dhiraj Bobade | K42: =HYPERLINK("https://maxxton.atlassian.net/browse/QA-22989","QA-22989") -> QA-22989 | L42: Created on 2025-03-12 for release | M42: 1
A43: =HYPERLINK("https://maxxton.atlassian.net/browse/QA-22964","QA-22964") -> QA-22964 | B43: API_DistributionChannel_P2 | C43: P2 | D43: TPI_PointOfIntrestes | E43: QA-1223 | F43: Aparna Shinde | G43: 60m | H43: N | I43: P2 | J43: Dhiraj Bobade | K43: =HYPERLINK("https://maxxton.atlassian.net/browse/QA-22990","QA-22990") -> QA-22990 | L43: Created on 2025-03-12 for release | M43: 1
A44: =HYPERLINK("https://maxxton.atlassian.net/browse/QA-22970","QA-22970") -> QA-22970 | B44: API_Allotment | C44: P2 | D44: TPI_PointOfIntrestes | E44: QA-1223 | F44: Aparna Shinde | G44: 60m | H44: N | I44: P2 | J44: Dhiraj Bobade | K44: =HYPERLINK("https://maxxton.atlassian.net/browse/QA-24103","QA-24103") -> QA-24103 | L44: Created on 2025-05-15 for release 2025_Week_21 | M44: 1
A45: =HYPERLINK("https://maxxton.atlassian.net/browse/QA-22972","QA-22972") -> QA-22972 | B45: API_CashClerance | C45: P2 | D45: TPI_PointOfIntrestes | E45: QA-1223 | F45: Aparna Shinde | G45: 60m | H45: N | I45: P2 | J45: Anup Sinha | K45: =HYPERLINK("https://maxxton.atlassian.net/browse/QA-22992","QA-22992") -> QA-22992 | L45: Created on 2025-03-12 for release | M45: 1
A46: =HYPERLINK("https://maxxton.atlassian.net/browse/QA-22973","QA-22973") -> QA-22973 | B46: API_Contracts | C46: P2 | D46: TPI_PointOfIntrestes | E46: QA-1223 | F46: Aparna Shinde | G46: 60m | H46: N | I46: P2 | J46: Anup Sinha | K46: =HYPERLINK("https://maxxton.atlassian.net/browse/QA-22993","QA-22993") -> QA-22993 | L46: Created on 2025-03-12 for release | M46: 1
A47: =HYPERLINK("https://maxxton.atlassian.net/browse/QA-22974","QA-22974") -> QA-22974 | B47: API_Facilities,Groups&Icals | C47: P2 | D47: TPI_PointOfIntrestes | E47: QA-1223 | F47: Aparna Shinde | G47: 60m | H47: N | I47: P2 | J47: Aparna Shinde | K47: =HYPERLINK("https://maxxton.atlassian.net/browse/QA-24104","QA-24104") -> QA-24104 | L47: Created on 2025-05-15 for release 2025_Week_21 | M47: 1
A48: =HYPERLINK("https://maxxton.atlassian.net/browse/QA-22975","QA-22975") -> QA-22975 | B48: API_Ledgers | C48: P2 | D48: TPI_PointOfIntrestes | E48: QA-1223 | F48: Aparna Shinde | G48: 60m | H48: N | I48: P2 | J48: Dhiraj Bobade | K48: =HYPERLINK("https://maxxton.atlassian.net/browse/QA-22995","QA-22995") -> QA-22995 | L48: Created on 2025-03-12 for release | M48: 1
A49: =HYPERLINK("https://maxxton.atlassian.net/browse/QA-22976","QA-22976") -> QA-22976 | B49: API_Rentability | C49: P2 | D49: TPI_PointOfIntrestes | E49: QA-1223 | F49: Aparna Shinde | G49: 60m | H49: N | I49: P2 | J49: Anup Sinha | K49: =HYPERLINK("https://maxxton.atlassian.net/browse/QA-22996","QA-22996") -> QA-22996 | L49: Created on 2025-03-12 for release | M49: 1
M50: 33h 45m

Sheet Revenue
O1: Components | P1: Epic
F2: Total Test Cases | G2: =countifs(A:A,"<>NEW",A:A,"<>")-1 -> 9 | O2: RevM_Autopilot | P2: QA-9421 | Q2: Revenue Manager Regression Test Cases
F3: Schedule? Y | G3: =countif(H:H,"=Y") -> 5 | O3: RevM_Budgets
F4: New Test Cases | G4: =COUNTIF(A:A,"=NEW") -> 0 | O4: RevM_Trends_page
F5: ciTSS7f3VPYW8Af3i2ZO923A | O5: RevM_Notification
A6: Key | B6: Summary | C6: Priority | D6: Component | E6: Epic Link | F6: Test Case Assignee | G6: Estimate | H6: Schedule ? | I6: Execution Priority | J6: Execution By | K6: Test Result Ticket | L6: Comments | M6: Original Estimates | N6: Remaining Estimates | O6: RevM_Monitors
A7: QA-9457 | B7: RT_Autopilot | C7: P3 | D7: RevM_Autopilot | E7: QA-9421 | F7: Mahesh Pawar | G7: 2h | H7: N | I7: P3 | J7: Mahesh Pawar | K7: =HYPERLINK("https://maxxton.atlassian.net/browse/QA-27256","QA-27256") -> QA-27256 | L7: Created on 2025-11-28 for release 2025_Week_49 | M7: 2h | N7: 30m | O7: RevM_Insight
A8: QA-9458 | B8: RT_Budget | C8: P3 | D8: RevM_Budgets | E8: QA-9421 | F8: Mahesh Pawar | G8: 90m | H8: N | I8: P3 | J8: Mahesh Pawar | K8: =HYPERLINK("https://maxxton.atlassian.net/browse/QA-27257","QA-27257") -> QA-27257 | L8: Created on 2025-11-28 for release 2025_Week_49 | M8: 1h 30m | N8: 30m | O8: RevM_Collection
A9: QA-9459 | B9: RT_Collection | C9: P3 | D9: RevM_Collection | E9: QA-9421 | F9: Mahesh Pawar | G9: 3h | H9: Y | I9: P3 | J9: Mahesh Pawar | K9: =HYPERLINK("https://maxxton.atlassian.net/browse/QA-28695","QA-28695") -> QA-28695 | L9: Created on 2026-03-06 for release 2026_Week_11 | M9: 3h | N9: 20m | O9: RevM_Dashboard
A10: QA-9460 | B10: RT_Yearly_insights | C10: P3 | D10: RevM_Yearly_insights | E10: QA-9421 | F10: Mahesh Pawar | G10: 1h 30m | H10: Y | I10: P3 | J10: Mahesh Pawar | K10: =HYPERLINK("https://maxxton.atlassian.net/browse/QA-28696","QA-28696") -> QA-28696 | L10: Created on 2026-03-06 for release 2026_Week_11 | M10: 1h 30m | N10: 30m | O10: RevM_Optimized_Rates
A11: =HYPERLINK("https://maxxton.atlassian.net/browse/QA-9463","QA-9463") -> QA-9463 | B11: RT_Insights | C11: P3 | D11: RevM_Insight | E11: QA-9421 | F11: Mahesh Pawar | G11: 210m | H11: Y | I11: P3 | J11: Mahesh Pawar | K11: =HYPERLINK("https://maxxton.atlassian.net/browse/QA-28697","QA-28697") -> QA-28697 | L11: Created on 2026-03-06 for release 2026_Week_11 | M11: 3h 30m | N11: 1h 30m
A12: =HYPERLINK("https://maxxton.atlassian.net/browse/QA-9465","QA-9465") -> QA-9465 | B12: RT_Notifications | C12: P3 | D12: RevM_Notification | E12: QA-9421 | F12: Narendra Deshmane | G12: 3h | H12: N | I12: P3 | J12: Narendra Deshmane | K12: =HYPERLINK("https://maxxton.atlassian.net/browse/QA-27261","QA-27261") -> QA-27261 | L12: Created on 2025-11-28 for release 2025_Week_49 | M12: 3h | N12: 1h 20m
A13: =HYPERLINK("https://maxxton.atlassian.net/browse/QA-9466","QA-9466") -> QA-9466 | B13: RT_Trends_page | C13: P3 | D13: RevM_Trends_page | E13: QA-9421 | F13: Narendra Deshmane | G13: 90m | H13: N | I13: P3 | J13: Narendra Deshmane | K13: =HYPERLINK("https://maxxton.atlassian.net/browse/QA-27262","QA-27262") -> QA-27262 | L13: Created on 2025-11-28 for release 2025_Week_49 | M13: 1h 30m | N13: 45m
A14: =HYPERLINK("https://maxxton.atlassian.net/browse/QA-9864","QA-9864") -> QA-9864 | B14: RT_Rate_updates | C14: P3 | D14: RevM_Optimized_Rates | E14: QA-9421 | F14: Narendra Deshmane | G14: 3h | H14: Y | I14: P3 | J14: Narendra Deshmane | K14: =HYPERLINK("https://maxxton.atlassian.net/browse/QA-28698","QA-28698") -> QA-28698 | L14: Created on 2026-03-06 for release 2026_Week_11 | M14: 3h | N14: 45m
A15: =HYPERLINK("https://maxxton.atlassian.net/browse/QA-15665","QA-15665") -> QA-15665 | B15: RT_Rate_Generator | C15: P3 | D15: RevM_Rate_Generator | E15: QA-9421 | F15: Narendra Deshmane | G15: 3h | H15: Y | I15: P3 | J15: Narendra Deshmane | K15: =HYPERLINK("https://maxxton.atlassian.net/browse/QA-28699","QA-28699") -> QA-28699 | L15: Created on 2026-03-06 for release 2026_Week_11 | M15: 3h | N15: 1h 15m
L16: Total hrs | M16: 22h | N16: 7h 41m

Sheet MCMS
F2: Total Test Cases | G2: =countifs(A:A,"<>NEW",A:A,"<>")-1 -> 86
F3: Schedule? Y | G3: =countif(H:H,"=Y") -> 27
F4: New Test Cases | G4: =COUNTIF(A:A,"=NEW") -> 0
A6: Key | B6: Summary | C6: Priority | D6: Component | E6: Epic Link | F6: Test Case Assignee | G6: Estimate | H6: Schedule ? | I6: Execution Priority | J6: Execution By
A7: QA-6877 | B7: LT_MCMS FMC BM | C7: P2 | D7: MCMS_Booking Module | E7: QA-2184 | G7: 1h 30m | H7: Y | I7: P2 | J7: Chandra Mohanty | K7: =HYPERLINK("https://maxxton.atlassian.net/browse/QA-29033","QA-29033") -> QA-29033 | L7: Created on 2026-04-01 for release Sprint_221
A8: QA-6879 | B8: LT_MCMS KRM BM | C8: P2 | D8: MCMS_Booking Module | E8: QA-2184 | G8: 1h 30m | H8: Y | I8: P2 | J8: Chandra Mohanty | K8: =HYPERLINK("https://maxxton.atlassian.net/browse/QA-29034","QA-29034") -> QA-29034 | L8: Created on 2026-04-01 for release Sprint_221
A9: QA-6880 | B9: LT_MCMS WEE BM | C9: P2 | D9: MCMS_Booking Module | E9: QA-2184 | G9: 1h 30m | H9: Y | I9: P2 | J9: Sujata Pimpale | K9: =HYPERLINK("https://maxxton.atlassian.net/browse/QA-29035","QA-29035") -> QA-29035 | L9: Created on 2026-04-01 for release Sprint_221
A10: QA-6881 | B10: LT_MCMS CSH BM | C10: P2 | D10: MCMS_Booking Module | E10: QA-2184 | G10: 1h 30m | H10: Y | I10: P2 | J10: Amruta Jadhav | K10: =HYPERLINK("https://maxxton.atlassian.net/browse/QA-29036","QA-29036") -> QA-29036 | L10: Created on 2026-04-01 for release Sprint_221
A11: QA-6882 | B11: LT_MCMS SA BM | C11: P2 | D11: MCMS_Booking Module | E11: QA-2184 | G11: 1h 30m | H11: Y | I11: P2 | J11: Amruta Jadhav | K11: =HYPERLINK("https://maxxton.atlassian.net/browse/QA-29037","QA-29037") -> QA-29037 | L11: Created on 2026-04-01 for release Sprint_221
A12: QA-6883 | B12: LT_MCMS ONS BM | C12: P2 | D12: MCMS_Booking Module | E12: QA-2184 | G12: 1h 30m | H12: Y | I12: P2 | J12: Amruta Jadhav | K12: =HYPERLINK("https://maxxton.atlassian.net/browse/QA-29038","QA-29038") -> QA-29038 | L12: Created on 2026-04-01 for release Sprint_221
A13: QA-8382 | B13: LT_MCMS LSH BM | C13: P2 | D13: MCMS_Booking Module | E13: QA-2184 | G13: 1h 30m | H13: Y | I13: P2 | J13: Sujata Pimpale | K13: =HYPERLINK("https://maxxton.atlassian.net/browse/QA-29039","QA-29039") -> QA-29039 | L13: Created on 2026-04-01 for release Sprint_221
A14: =HYPERLINK("https://maxxton.atlassian.net/browse/QA-17365","QA-17365") -> QA-17365 | B14: LT_MCMS COF BM | C14: P2 | D14: MCMS_Booking Module | E14: QA-2184 | F14: Sujata Pimpale | G14: 1h 30m | H14: Y | I14: P2 | J14: Amruta Jadhav | K14: =HYPERLINK("https://maxxton.atlassian.net/browse/QA-29040","QA-29040") -> QA-29040 | L14: Created on 2026-04-01 for release Sprint_221
A15: QA-6886 | B15: LT_MCMS NRT BM | C15: P2 | D15: MCMS_Booking Module | E15: QA-2184 | G15: 1h 30m | H15: Y | I15: P2 | J15: Amruta Jadhav | K15: =HYPERLINK("https://maxxton.atlassian.net/browse/QA-29041","QA-29041") -> QA-29041 | L15: Created on 2026-04-01 for release Sprint_221
A16: =HYPERLINK("https://maxxton.atlassian.net/browse/QA-22306","QA-22306") -> QA-22306 | B16: LT_MCMS SAN BM | C16: P3 | D16: MCMS_Booking Module | E16: QA-2184 | F16: Sujata Pimpale | G16: 1h 30m | H16: Y | I16: P3 | J16: Amruta Jadhav | K16: =HYPERLINK("https://maxxton.atlassian.net/browse/QA-29042","QA-29042") -> QA-29042 | L16: Created on 2026-04-01 for release Sprint_221
A17: QA-6878 | B17: LT_MCMS RVP QURIOS BM | C17: P3 | D17: MCMS_Booking Module | E17: QA-2184 | G17: 60m | H17: N | I17: P3
A18: QA-6884 | B18: LT_MCMS VDT BM | C18: P3 | D18: MCMS_Booking Module | E18: QA-2184 | G18: 1h 30m | H18: N | I18: P3 | J18: Chandra Mohanty | K18: =HYPERLINK("https://maxxton.atlassian.net/browse/QA-27854","QA-27854") -> QA-27854
A19: QA-6885 | B19: LT_MCMS ALP BM | C19: P3 | D19: MCMS_Booking Module | E19: QA-2184 | G19: 1h 30m | H19: N | I19: P3 | J19: Chandra Mohanty | K19: =HYPERLINK("https://maxxton.atlassian.net/browse/QA-27855","QA-27855") -> QA-27855
A20: QA-6983 | B20: RT_WM_Categories | C20: P3 | D20: MCMS_WM_Categories | E20: QA-2184 | G20: 60m | H20: N | I20: P3 | J20: Amruta Jadhav | K20: =HYPERLINK("https://maxxton.atlassian.net/browse/QA-26108","QA-26108") -> QA-26108
A21: QA-6984 | B21: RT_WM_CRP | C21: P3 | D21: MCMS_WM_CustomResultPanels | E21: QA-2184 | G21: 60m | H21: N | I21: P3 | J21: Chandra Mohanty | K21: =HYPERLINK("https://maxxton.atlassian.net/browse/QA-26109","QA-26109") -> QA-26109
A22: QA-6985 | B22: RT_WM_Datalayers | C22: P3 | D22: MCMS_WM_Datalayers | E22: QA-2184 | G22: 60m | H22: N | I22: P3 | J22: Amruta Jadhav
A23: QA-6986 | B23: RT_WM_Dynamic Sitemaps | C23: P3 | D23: MCMS_WM_DynamicSitemaps | E23: QA-2184 | G23: 60m | H23: N | I23: P3 | J23: Amruta Jadhav
A24: QA-6987 | B24: RT_WM_Flows | C24: P3 | D24: MCMS_WM_Flows | E24: QA-2184 | G24: 60m | H24: N | I24: P3 | J24: Amruta Jadhav
A25: QA-6988 | B25: RT_WM_Forms | C25: P3 | D25: MCMS_WM_Forms | E25: QA-2184 | G25: 60m | H25: N | I25: P3 | J25: Amruta Jadhav | K25: =HYPERLINK("https://maxxton.atlassian.net/browse/QA-28277","QA-28277") -> QA-28277
A26: QA-6989 | B26: RT_WM_Free Search | C26: P3 | D26: MCMS_WM_FreeSearch | E26: QA-2184 | G26: 60m | H26: N | I26: P3 | J26: Amruta Jadhav
A27: QA-6990 | B27: RT_WM_Locale | C27: P3 | D27: MCMS_WM_Languages | E27: QA-2184 | G27: 60m | H27: N | I27: P3 | J27: Amruta Jadhav | K27: =HYPERLINK("https://maxxton.atlassian.net/browse/QA-26110","QA-26110") -> QA-26110
A28: QA-6991 | B28: RT_WM_Translations | C28: P3 | D28: MCMS_WM_Languages | E28: QA-2184 | G28: 60m | H28: N | I28: P3 | J28: Amruta Jadhav
A29: QA-6992 | B29: RT_WM_Menus | C29: P3 | D29: MCMS_WM_Menus | E29: QA-2184 | G29: 60m | H29: N | I29: P3 | J29: Amruta Jadhav | K29: =HYPERLINK("https://maxxton.atlassian.net/browse/QA-27582","QA-27582") -> QA-27582
A30: QA-6993 | B30: RT_WM_CMS Settings | C30: P3 | D30: MCMS_WM_OverallSettings | E30: QA-2184 | G30: 60m | H30: N | I30: P3 | J30: Amruta Jadhav | K30: =HYPERLINK("https://maxxton.atlassian.net/browse/QA-25388","QA-25388") -> QA-25388
A31: QA-6994 | B31: RT_WM_Pages | C31: P3 | D31: MCMS_WM_Pages | E31: QA-2184 | G31: 60m | H31: N | I31: P3 | J31: Amruta Jadhav | K31: =HYPERLINK("https://maxxton.atlassian.net/browse/QA-28278","QA-28278") -> QA-28278
A32: QA-6995 | B32: RT_WM_Posts | C32: P3 | D32: MCMS_WM_Posts | E32: QA-2184 | G32: 60m | H32: N | I32: P3 | J32: Amruta Jadhav | K32: =HYPERLINK("https://maxxton.atlassian.net/browse/QA-28279","QA-28279") -> QA-28279
A33: QA-6996 | B33: RT_WM_Sites | C33: P3 | D33: MCMS_WM_Sites | E33: QA-2184 | G33: 60m | H33: N | I33: P3 | J33: Amruta Jadhav | K33: =HYPERLINK("https://maxxton.atlassian.net/browse/QA-27585","QA-27585") -> QA-27585
A34: QA-6997 | B34: RT_WM_Templates | C34: P3 | D34: MCMS_WM_Templates | E34: QA-2184 | G34: 60m | H34: N | I34: P3 | J34: Amruta Jadhav | K34: =HYPERLINK("https://maxxton.atlassian.net/browse/QA-28280","QA-28280") -> QA-28280
A35: QA-6998 | B35: RT_WM_Web Contents | C35: P3 | D35: MCMS_WM_WebContents | E35: QA-2184 | G35: 60m | H35: N | I35: P3 | J35: Amruta Jadhav | K35: =HYPERLINK("https://maxxton.atlassian.net/browse/QA-28281","QA-28281") -> QA-28281
A36: QA-6999 | B36: RT_WM_Price Widget | C36: P3 | D36: MCMS_WM_Widgets | E36: QA-2184 | G36: 60m | H36: N | I36: P3 | J36: Amruta Jadhav | K36: =HYPERLINK("https://maxxton.atlassian.net/browse/QA-26114","QA-26114") -> QA-26114
A37: QA-7000 | B37: RT_WM_Containers Widget | C37: P3 | D37: MCMS_WM_Widgets | E37: QA-2184 | G37: 60m | H37: N | I37: P3 | J37: Amruta Jadhav | K37: =HYPERLINK("https://maxxton.atlassian.net/browse/QA-26115","QA-26115") -> QA-26115
A38: QA-7001 | B38: RT_WM_Button Widget | C38: P3 | D38: MCMS_WM_Widgets | E38: QA-2184 | G38: 60m | H38: N | I38: P3 | J38: Amruta Jadhav | K38: =HYPERLINK("https://maxxton.atlassian.net/browse/QA-27588","QA-27588") -> QA-27588
A39: QA-7002 | B39: RT_WM_Map Widget | C39: P3 | D39: MCMS_WM_Widgets | E39: QA-2184 | G39: 60m | H39: N | I39: P3 | J39: Amruta Jadhav | K39: =HYPERLINK("https://maxxton.atlassian.net/browse/QA-28282","QA-28282") -> QA-28282
A40: QA-7003 | B40: RT_WM_Gallery Widget | C40: P3 | D40: MCMS_WM_Widgets | E40: QA-2184 | G40: 60m | H40: N | I40: P3 | J40: Amruta Jadhav | K40: =HYPERLINK("https://maxxton.atlassian.net/browse/QA-28283","QA-28283") -> QA-28283
A41: QA-7004 | B41: RT_WM_Dynamic Container Widget | C41: P3 | D41: MCMS_WM_Widgets | E41: QA-2184 | G41: 60m | H41: N | I41: P3 | J41: Amruta Jadhav | K41: =HYPERLINK("https://maxxton.atlassian.net/browse/QA-26116","QA-26116") -> QA-26116
A42: QA-7005 | B42: RT_WM_Search Widget | C42: P3 | D42: MCMS_WM_Widgets | E42: QA-2184 | G42: 60m | H42: N | I42: P3 | J42: Amruta Jadhav
A43: =HYPERLINK("https://maxxton.atlassian.net/browse/QA-10931","QA-10931") -> QA-10931 | B43: RT_MCMS VCS MYENV | C43: P3 | D43: MCMS_Guest Portal | E43: QA-2184 | F43: Chandra Mohanty | G43: 60m | H43: N | I43: P3 | J43: Amruta Jadhav
A44: =HYPERLINK("https://maxxton.atlassian.net/browse/QA-14413","QA-14413") -> QA-14413 | B44: RT_WM_Activity Planner | C44: P3 | D44: MCMS_WM_Widgets | E44: QA-2184 | F44: Chandra Mohanty | G44: 60m | H44: N | I44: P3 | J44: Chandra Mohanty | K44: =HYPERLINK("https://maxxton.atlassian.net/browse/QA-28284","QA-28284") -> QA-28284
A45: =HYPERLINK("https://maxxton.atlassian.net/browse/QA-14414","QA-14414") -> QA-14414 | B45: RT_WM_Breadcrumb | C45: P3 | D45: MCMS_WM_Menus | E45: QA-2184 | F45: Chandra Mohanty | G45: 60m | H45: N | I45: P3 | J45: Amruta Jadhav | K45: =HYPERLINK("https://maxxton.atlassian.net/browse/QA-25871","QA-25871") -> QA-25871
A46: =HYPERLINK("https://maxxton.atlassian.net/browse/QA-14415","QA-14415") -> QA-14415 | B46: RT_WM_Availability Date | C46: P3 | D46: MCMS_WM_Widgets | E46: QA-2184 | F46: Chandra Mohanty | G46: 60m | H46: N | I46: P3 | J46: Amruta Jadhav | K46: =HYPERLINK("https://maxxton.atlassian.net/browse/QA-25872","QA-25872") -> QA-25872
A47: =HYPERLINK("https://maxxton.atlassian.net/browse/QA-16289","QA-16289") -> QA-16289 | B47: RT_MCMS FMC BM1 | C47: P3 | D47: MCMS_Booking Module | E47: QA-2184 | F47: Sujata Pimpale | G47: 1h 30m | H47: N | I47: P3 | J47: Chandra Mohanty | K47: =HYPERLINK("https://maxxton.atlassian.net/browse/QA-29002","QA-29002") -> QA-29002 | L47: Created on 2026-03-27 for release Sprint_221
A48: =HYPERLINK("https://maxxton.atlassian.net/browse/QA-16290","QA-16290") -> QA-16290 | B48: RT_MCMS KRM BM | C48: P3 | D48: MCMS_Booking Module | E48: QA-2184 | F48: Sujata Pimpale | G48: 2h | H48: N | I48: P3 | J48: Chandra Mohanty | K48: =HYPERLINK("https://maxxton.atlassian.net/browse/QA-29003","QA-29003") -> QA-29003 | L48: Created on 2026-03-27 for release Sprint_221
A49: =HYPERLINK("https://maxxton.atlassian.net/browse/QA-16291","QA-16291") -> QA-16291 | B49: RT_MCMS WEE BM | C49: P3 | D49: MCMS_Booking Module | E49: QA-2184 | F49: Sujata Pimpale | G49: 1h 30m | H49: N | I49: P3 | J49: Sujata Pimpale | K49: =HYPERLINK("https://maxxton.atlassian.net/browse/QA-29004","QA-29004") -> QA-29004 | L49: Created on 2026-03-27 for release Sprint_221
A50: =HYPERLINK("https://maxxton.atlassian.net/browse/QA-16292","QA-16292") -> QA-16292 | B50: RT_MCMS CSH BM | C50: P3 | D50: MCMS_Booking Module | E50: QA-2184 | F50: Sujata Pimpale | G50: 1h 30m | H50: N | I50: P3 | J50: Amruta Jadhav | K50: =HYPERLINK("https://maxxton.atlassian.net/browse/QA-29005","QA-29005") -> QA-29005 | L50: Created on 2026-03-27 for release Sprint_221
A51: =HYPERLINK("https://maxxton.atlassian.net/browse/QA-16293","QA-16293") -> QA-16293 | B51: RT_MCMS COF BM | C51: P3 | D51: MCMS_Booking Module | E51: QA-2184 | F51: Sujata Pimpale | G51: 1h 30m | H51: N | I51: P3 | J51: Amruta Jadhav | K51: =HYPERLINK("https://maxxton.atlassian.net/browse/QA-29006","QA-29006") -> QA-29006 | L51: Created on 2026-03-27 for release Sprint_221
A52: =HYPERLINK("https://maxxton.atlassian.net/browse/QA-16294","QA-16294") -> QA-16294 | B52: RT_MCMS ONS BM | C52: P3 | D52: MCMS_Booking Module | E52: QA-2184 | F52: Sujata Pimpale | G52: 1h 30m | H52: N | I52: P3 | J52: Amruta Jadhav | K52: =HYPERLINK("https://maxxton.atlassian.net/browse/QA-29007","QA-29007") -> QA-29007 | L52: Created on 2026-03-27 for release Sprint_221
A53: =HYPERLINK("https://maxxton.atlassian.net/browse/QA-16295","QA-16295") -> QA-16295 | B53: RT_MCMS LSH BM | C53: P3 | D53: MCMS_Booking Module | E53: QA-2184 | F53: Sujata Pimpale | G53: 2h | H53: N | I53: P3 | J53: Sujata Pimpale | K53: =HYPERLINK("https://maxxton.atlassian.net/browse/QA-29008","QA-29008") -> QA-29008 | L53: Created on 2026-03-27 for release Sprint_221
A54: =HYPERLINK("https://maxxton.atlassian.net/browse/QA-16296","QA-16296") -> QA-16296 | B54: RT_MCMS NRT BM | C54: P3 | D54: MCMS_Booking Module | E54: QA-2184 | F54: Sujata Pimpale | G54: 1h 30m | H54: N | I54: P3 | J54: Amruta Jadhav | K54: =HYPERLINK("https://maxxton.atlassian.net/browse/QA-29009","QA-29009") -> QA-29009 | L54: Created on 2026-03-27 for release Sprint_221
A55: =HYPERLINK("https://maxxton.atlassian.net/browse/QA-16297","QA-16297") -> QA-16297 | B55: RT_MCMS FMC MY ENV | C55: P3 | D55: MCMS_Guest Portal | E55: QA-2184 | F55: Sujata Pimpale | G55: 1h | H55: N | I55: P3 | J55: Chandra Mohanty | K55: =HYPERLINK("https://maxxton.atlassian.net/browse/QA-29010","QA-29010") -> QA-29010 | L55: Created on 2026-03-27 for release Sprint_221
A56: =HYPERLINK("https://maxxton.atlassian.net/browse/QA-16298","QA-16298") -> QA-16298 | B56: RT_MCMS KRM MY ENV | C56: P3 | D56: MCMS_Guest Portal | E56: QA-2184 | F56: Sujata Pimpale | G56: 1h | H56: N | I56: P3 | J56: Chandra Mohanty | K56: =HYPERLINK("https://maxxton.atlassian.net/browse/QA-29011","QA-29011") -> QA-29011 | L56: Created on 2026-03-27 for release Sprint_221
A57: =HYPERLINK("https://maxxton.atlassian.net/browse/QA-18644","QA-18644") -> QA-18644 | B57: RT_MCMS WEE MY ENV | C57: P3 | D57: MCMS_Guest Portal | E57: QA-2184 | F57: Sujata Pimpale | G57: 2h | H57: N | I57: P3 | J57: Sujata Pimpale | K57: =HYPERLINK("https://maxxton.atlassian.net/browse/QA-29012","QA-29012") -> QA-29012 | L57: Created on 2026-03-27 for release Sprint_221
A58: =HYPERLINK("https://maxxton.atlassian.net/browse/QA-21824","QA-21824") -> QA-21824 | B58: RT_MCMS AHS BM | C58: P3 | D58: MCMS_Booking Module | E58: QA-2184 | F58: Sujata Pimpale | G58: 1h 30m | H58: N | I58: P3 | J58: Amruta Jadhav | K58: =HYPERLINK("https://maxxton.atlassian.net/browse/QA-29013","QA-29013") -> QA-29013 | L58: Created on 2026-03-27 for release Sprint_221
A59: =HYPERLINK("https://maxxton.atlassian.net/browse/QA-21825","QA-21825") -> QA-21825 | B59: RT_MCMS RCN MY ENV | C59: P3 | D59: MCMS_Guest Portal | E59: QA-2184 | F59: Sujata Pimpale | G59: 2h | H59: N | I59: P3 | J59: Chandra Mohanty | K59: =HYPERLINK("https://maxxton.atlassian.net/browse/QA-29014","QA-29014") -> QA-29014 | L59: Created on 2026-03-27 for release Sprint_221
A60: =HYPERLINK("https://maxxton.atlassian.net/browse/QA-21826","QA-21826") -> QA-21826 | B60: RT_MCMS LIB MY ENV | C60: P3 | D60: MCMS_Guest Portal | E60: QA-2184 | F60: Sujata Pimpale | G60: 1h 30m | H60: N | I60: P3 | J60: Sujata Pimpale | K60: =HYPERLINK("https://maxxton.atlassian.net/browse/QA-29015","QA-29015") -> QA-29015 | L60: Created on 2026-03-27 for release Sprint_221
A61: =HYPERLINK("https://maxxton.atlassian.net/browse/QA-22502","QA-22502") -> QA-22502 | B61: RT_MCMS SAN BM | C61: P3 | D61: MCMS_Booking Module | E61: QA-2184 | F61: Sujata Pimpale | G61: 1h 30m | H61: N | I61: P3 | J61: Amruta Jadhav | K61: =HYPERLINK("https://maxxton.atlassian.net/browse/QA-29016","QA-29016") -> QA-29016 | L61: Created on 2026-03-27 for release Sprint_221
A62: =HYPERLINK("https://maxxton.atlassian.net/browse/QA-23007","QA-23007") -> QA-23007 | B62: RT_MCMS EST MY ENV | C62: P3 | D62: MCMS_Booking Module | E62: QA-2184 | F62: Sujata Pimpale | G62: 2h | H62: N | I62: P3 | J62: Sujata Pimpale | K62: =HYPERLINK("https://maxxton.atlassian.net/browse/QA-29017","QA-29017") -> QA-29017 | L62: Created on 2026-03-27 for release Sprint_221
A63: =HYPERLINK("https://maxxton.atlassian.net/browse/QA-23008","QA-23008") -> QA-23008 | B63: RT_MCMS FoV MY ENV | C63: P3 | D63: MCMS_Booking Module | E63: QA-2184 | F63: Sujata Pimpale | G63: 2h | H63: N | I63: P3 | J63: Chandra Mohanty | K63: =HYPERLINK("https://maxxton.atlassian.net/browse/QA-29018","QA-29018") -> QA-29018 | L63: Created on 2026-03-27 for release Sprint_221
A64: =HYPERLINK("https://maxxton.atlassian.net/browse/QA-23010","QA-23010") -> QA-23010 | B64: RT_MCMS EST BM | C64: P3 | D64: MCMS_Booking Module | E64: QA-2184 | F64: Sujata Pimpale | G64: 2h | H64: N | I64: P3 | J64: Sujata Pimpale | K64: =HYPERLINK("https://maxxton.atlassian.net/browse/QA-29019","QA-29019") -> QA-29019 | L64: Created on 2026-03-27 for release Sprint_221
A65: =HYPERLINK("https://maxxton.atlassian.net/browse/QA-23029","QA-23029") -> QA-23029 | B65: RT_MCMS RVP Owner Portal | C65: P3 | D65: MCMS_Booking Module | E65: QA-2184 | F65: Sujata Pimpale | G65: 1h 30m | H65: N | I65: P3 | J65: Chandra Mohanty | K65: =HYPERLINK("https://maxxton.atlassian.net/browse/QA-29020","QA-29020") -> QA-29020 | L65: Created on 2026-03-27 for release Sprint_221
A66: =HYPERLINK("https://maxxton.atlassian.net/browse/QA-24221","QA-24221") -> QA-24221 | B66: RT_MCMS Embed BM | C66: P3 | D66: MCMS_Booking Module | E66: QA-2184 | F66: Chandra Mohanty | G66: 1h | H66: N | I66: P3 | J66: Amruta Jadhav | K66: =HYPERLINK("https://maxxton.atlassian.net/browse/QA-29021","QA-29021") -> QA-29021 | L66: Created on 2026-03-27 for release Sprint_221
A67: =HYPERLINK("https://maxxton.atlassian.net/browse/QA-24225","QA-24225") -> QA-24225 | B67: RT_MCMS NRT MY ENV | C67: P3 | D67: MCMS_Guest Portal | E67: QA-2184 | F67: Amruta Jadhav | G67: 2h | H67: N | I67: P3 | J67: Amruta Jadhav | K67: =HYPERLINK("https://maxxton.atlassian.net/browse/QA-29022","QA-29022") -> QA-29022 | L67: Created on 2026-03-27 for release Sprint_221
A68: =HYPERLINK("https://maxxton.atlassian.net/browse/QA-25426","QA-25426") -> QA-25426 | B68: RT_MCMS CSH MY ENV | C68: P3 | D68: MCMS_Guest Portal | E68: QA-2184 | F68: Chandra Mohanty | G68: 1h 30m | H68: N | I68: P3 | J68: Amruta Jadhav | K68: =HYPERLINK("https://maxxton.atlassian.net/browse/QA-29023","QA-29023") -> QA-29023 | L68: Created on 2026-03-27 for release Sprint_221
A69: =HYPERLINK("https://maxxton.atlassian.net/browse/QA-25905","QA-25905") -> QA-25905 | B69: RT_MCMS MOL MY ENV | C69: P3 | D69: MCMS_Guest Portal | E69: QA-2184 | F69: Sujata Pimpale | G69: 1h | H69: N | I69: P3 | J69: Sujata Pimpale | K69: =HYPERLINK("https://maxxton.atlassian.net/browse/QA-29024","QA-29024") -> QA-29024 | L69: Created on 2026-03-27 for release Sprint_221
A70: =HYPERLINK("https://maxxton.atlassian.net/browse/QA-25906","QA-25906") -> QA-25906 | B70: RT_MCMS AHS MY ENV | C70: P3 | D70: MCMS_Guest Portal | E70: QA-2184 | F70: Sujata Pimpale | G70: 1h | H70: N | I70: P3 | J70: Sujata Pimpale | K70: =HYPERLINK("https://maxxton.atlassian.net/browse/QA-29025","QA-29025") -> QA-29025 | L70: Created on 2026-03-27 for release Sprint_221
A71: =HYPERLINK("https://maxxton.atlassian.net/browse/QA-27369","QA-27369") -> QA-27369 | B71: RT_MCMS EUP MY ENV | C71: P3 | D71: MCMS_Guest Portal | E71: QA-2184 | F71: Chandra Mohanty | G71: 1h | H71: N | I71: P3 | J71: Chandra Mohanty | K71: =HYPERLINK("https://maxxton.atlassian.net/browse/QA-29026","QA-29026") -> QA-29026 | L71: Created on 2026-03-27 for release Sprint_221
A72: =HYPERLINK("https://maxxton.atlassian.net/browse/QA-27370","QA-27370") -> QA-27370 | B72: RT_MCMS EUP BM | C72: P3 | D72: MCMS_Booking Module | E72: QA-2184 | F72: Chandra Mohanty | G72: 1h 30m | H72: N | I72: P3 | J72: Chandra Mohanty | K72: =HYPERLINK("https://maxxton.atlassian.net/browse/QA-29027","QA-29027") -> QA-29027 | L72: Created on 2026-03-27 for release Sprint_221
A73: =HYPERLINK("https://maxxton.atlassian.net/browse/QA-28048","QA-28048") -> QA-28048 | B73: RT_MCMS LSH MY ENV | C73: P3 | D73: MCMS_Guest Portal | E73: QA-2184 | F73: Sujata Pimpale | G73: 1h | H73: N | I73: P3 | J73: Sujata Pimpale | K73: =HYPERLINK("https://maxxton.atlassian.net/browse/QA-29028","QA-29028") -> QA-29028 | L73: Created on 2026-03-27 for release Sprint_221
A74: =HYPERLINK("https://maxxton.atlassian.net/browse/QA-28049","QA-28049") -> QA-28049 | B74: RT_MCMS ONS MY ENV | C74: P3 | D74: MCMS_Guest Portal | E74: QA-2184 | F74: Sujata Pimpale | G74: 1h 30m | H74: N | I74: P3 | J74: Sujata Pimpale | K74: =HYPERLINK("https://maxxton.atlassian.net/browse/QA-29029","QA-29029") -> QA-29029 | L74: Created on 2026-03-27 for release Sprint_221
A75: =HYPERLINK("https://maxxton.atlassian.net/browse/QA-28050","QA-28050") -> QA-28050 | B75: RT_BHP BM | C75: P3 | D75: MCMS_Booking Module | E75: QA-2184 | F75: Sujata Pimpale | G75: 1h 30m | H75: N | I75: P3 | J75: Sujata Pimpale | K75: =HYPERLINK("https://maxxton.atlassian.net/browse/QA-29030","QA-29030") -> QA-29030 | L75: Created on 2026-03-27 for release Sprint_221
A76: =HYPERLINK("https://maxxton.atlassian.net/browse/QA-25198","QA-25198") -> QA-25198 | B76: LT_MCMS FOV MY ENV | C76: P2 | D76: MCMS_Guest Portal | E76: QA-2184 | F76: Chandra Mohanty | G76: 1h | H76: Y | I76: P2 | J76: Amruta Jadhav | K76: =HYPERLINK("https://maxxton.atlassian.net/browse/QA-29043","QA-29043") -> QA-29043 | L76: Created on 2026-04-01 for release Sprint_221
A77: =HYPERLINK("https://maxxton.atlassian.net/browse/QA-25199","QA-25199") -> QA-25199 | B77: LT_MCMS FMC MY ENV | C77: P2 | D77: MCMS_Guest Portal | E77: QA-2184 | F77: Chandra Mohanty | G77: 1h | H77: Y | I77: P2 | J77: Chandra Mohanty | K77: =HYPERLINK("https://maxxton.atlassian.net/browse/QA-29044","QA-29044") -> QA-29044 | L77: Created on 2026-04-01 for release Sprint_221
A78: =HYPERLINK("https://maxxton.atlassian.net/browse/QA-25200","QA-25200") -> QA-25200 | B78: LT_MCMS RCN MY ENV | C78: P2 | D78: MCMS_Guest Portal | E78: QA-2184 | F78: Chandra Mohanty | G78: 1h | H78: Y | I78: P2 | J78: Chandra Mohanty | K78: =HYPERLINK("https://maxxton.atlassian.net/browse/QA-29045","QA-29045") -> QA-29045 | L78: Created on 2026-04-01 for release Sprint_221
A79: =HYPERLINK("https://maxxton.atlassian.net/browse/QA-25201","QA-25201") -> QA-25201 | B79: LT_MCMS RVP OWNER PORTAL | C79: P2 | D79: MCMS_Guest Portal | E79: QA-2184 | F79: Chandra Mohanty | G79: 1h | H79: Y | I79: P2 | J79: Chandra Mohanty | K79: =HYPERLINK("https://maxxton.atlassian.net/browse/QA-29046","QA-29046") -> QA-29046 | L79: Created on 2026-04-01 for release Sprint_221
A80: =HYPERLINK("https://maxxton.atlassian.net/browse/QA-25202","QA-25202") -> QA-25202 | B80: LT_MCMS EST BM | C80: P2 | D80: MCMS_Booking Module | E80: QA-2184 | F80: Sujata Pimpale | G80: 1h | H80: Y | I80: P2 | J80: Sujata Pimpale | K80: =HYPERLINK("https://maxxton.atlassian.net/browse/QA-29047","QA-29047") -> QA-29047 | L80: Created on 2026-04-01 for release Sprint_221
A81: =HYPERLINK("https://maxxton.atlassian.net/browse/QA-25203","QA-25203") -> QA-25203 | B81: LT_MCMS WEE MY ENV | C81: P2 | D81: MCMS_Guest Portal | E81: QA-2184 | F81: Sujata Pimpale | G81: 1h | H81: Y | I81: P2 | J81: Sujata Pimpale | K81: =HYPERLINK("https://maxxton.atlassian.net/browse/QA-29048","QA-29048") -> QA-29048 | L81: Created on 2026-04-01 for release Sprint_221
A82: =HYPERLINK("https://maxxton.atlassian.net/browse/QA-25204","QA-25204") -> QA-25204 | B82: LT_MCMS LIB MY ENV | C82: P2 | D82: MCMS_Guest Portal | E82: QA-2184 | F82: Sujata Pimpale | G82: 1h | H82: Y | I82: P2 | J82: Sujata Pimpale | K82: =HYPERLINK("https://maxxton.atlassian.net/browse/QA-29049","QA-29049") -> QA-29049 | L82: Created on 2026-04-01 for release Sprint_221
A83: =HYPERLINK("https://maxxton.atlassian.net/browse/QA-25205","QA-25205") -> QA-25205 | B83: LT_MCMS KRM MY ENV | C83: P2 | D83: MCMS_Guest Portal | E83: QA-2184 | F83: Sujata Pimpale | G83: 1h | H83: Y | I83: P2 | J83: Chandra Mohanty | K83: =HYPERLINK("https://maxxton.atlassian.net/browse/QA-29050","QA-29050") -> QA-29050 | L83: Created on 2026-04-01 for release Sprint_221
A84: =HYPERLINK("https://maxxton.atlassian.net/browse/QA-25206","QA-25206") -> QA-25206 | B84: LT_MCMS NRT MY ENV | C84: P2 | D84: MCMS_Guest Portal | E84: QA-2184 | F84: Sujata Pimpale | G84: 1h 30m | H84: Y | I84: P2 | J84: Amruta Jadhav | K84: =HYPERLINK("https://maxxton.atlassian.net/browse/QA-29051","QA-29051") -> QA-29051 | L84: Created on 2026-04-01 for release Sprint_221
A85: =HYPERLINK("https://maxxton.atlassian.net/browse/QA-25207","QA-25207") -> QA-25207 | B85: LT_MCMS EST MY ENV | C85: P2 | D85: MCMS_Guest Portal | E85: QA-2185 | F85: Sujata Pimpale | G85: 1h | H85: Y | I85: P2 | J85: Sujata Pimpale | K85: =HYPERLINK("https://maxxton.atlassian.net/browse/QA-29052","QA-29052") -> QA-29052 | L85: Created on 2026-04-01 for release Sprint_221
A86: =HYPERLINK("https://maxxton.atlassian.net/browse/QA-25208","QA-25208") -> QA-25208 | B86: LT_MCMS CSH MY ENV | C86: P2 | D86: MCMS_Guest Portal | E86: QA-2184 | F86: Sujata Pimpale | G86: 1h | H86: Y | I86: P2 | J86: Amruta Jadhav | K86: =HYPERLINK("https://maxxton.atlassian.net/browse/QA-29053","QA-29053") -> QA-29053 | L86: Created on 2026-04-01 for release Sprint_221
A87: =HYPERLINK("https://maxxton.atlassian.net/browse/QA-25907","QA-25907") -> QA-25907 | B87: LT_MCMS MOL MY ENV | C87: P3 | D87: MCMS_Guest Portal | E87: QA-2184 | F87: Sujata Pimpale | G87: 1h | H87: Y | I87: P3 | J87: Amruta Jadhav | K87: =HYPERLINK("https://maxxton.atlassian.net/browse/QA-29054","QA-29054") -> QA-29054 | L87: Created on 2026-04-01 for release Sprint_221
A88: =HYPERLINK("https://maxxton.atlassian.net/browse/QA-25908","QA-25908") -> QA-25908 | B88: LT_MCMS AHS MY ENV | C88: P3 | D88: MCMS_Guest Portal | E88: QA-2184 | F88: Sujata Pimpale | G88: 1h | H88: Y | I88: P3 | J88: Amruta Jadhav | K88: =HYPERLINK("https://maxxton.atlassian.net/browse/QA-29055","QA-29055") -> QA-29055 | L88: Created on 2026-04-01 for release Sprint_221
A89: =HYPERLINK("https://maxxton.atlassian.net/browse/QA-27374","QA-27374") -> QA-27374 | B89: LT_MCMS EUP MY ENV | C89: P2 | D89: MCMS_Guest Portal | E89: QA-2184 | F89: Chandra Mohanty | G89: 1h | H89: Y | I89: P2 | J89: Chandra Mohanty | K89: =HYPERLINK("https://maxxton.atlassian.net/browse/QA-29056","QA-29056") -> QA-29056 | L89: Created on 2026-04-01 for release Sprint_221
A90: =HYPERLINK("https://maxxton.atlassian.net/browse/QA-27375","QA-27375") -> QA-27375 | B90: LT_MCMS EUP BM | C90: P2 | D90: MCMS_Booking Module | E90: QA-2184 | F90: Chandra Mohanty | G90: 1h 30m | H90: Y | I90: P2 | J90: Chandra Mohanty | K90: =HYPERLINK("https://maxxton.atlassian.net/browse/QA-29057","QA-29057") -> QA-29057 | L90: Created on 2026-04-01 for release Sprint_221
A91: =HYPERLINK("https://maxxton.atlassian.net/browse/QA-28800","QA-28800") -> QA-28800 | B91: LT_MCMS LSH MY ENV | C91: P2 | D91: MCMS_Guest Portal | E91: QA-2184 | F91: Chandra Mohanty | G91: 1h | H91: Y | I91: P2 | J91: Chandra Mohanty | K91: =HYPERLINK("https://maxxton.atlassian.net/browse/QA-29058","QA-29058") -> QA-29058 | L91: Created on 2026-04-01 for release Sprint_221
A92: =HYPERLINK("https://maxxton.atlassian.net/browse/QA-28801","QA-28801") -> QA-28801 | B92: LT_MCMS ONS MY ENV | C92: P2 | D92: MCMS_Guest Portal | E92: QA-2184 | F92: Chandra Mohanty | G92: 1h | H92: Y | I92: P2 | J92: Chandra Mohanty | K92: =HYPERLINK("https://maxxton.atlassian.net/browse/QA-29059","QA-29059") -> QA-29059 | L92: Created on 2026-04-01 for release Sprint_221

Sheet Finance
O1: Components | P1: Epic
F2: Total Test Cases | G2: =countifs(A:A,"<>NEW",A:A,"<>")-1 -> 11 | O2: CMS-Castle BM | P2: QA-1 | Q2: Newyse Regression Test Cases
F3: Schedule? Y | G3: =countif(H:H,"=Y") -> 11 | O3: CMS-Castle MyEnv | P3: QA-24 | Q3: CMS Regression Test Cases
F4: New Test Cases | G4: =COUNTIF(A:A,"=NEW") -> 0 | O4: CMS-Contempo BM | P4: QA-25 | Q4: CMS Live Test Cases
O5: CMS-Contempo MyEnv | P5: QA-26 | Q5: CMS Sanity Test Cases
A6: Key | B6: Summary | C6: Priority | D6: Component | E6: Epic Link | F6: Test Case Assignee | G6: Estimate | H6: Schedule ? | I6: Execution Priority | J6: Execution By | K6: Test Result Ticket | L6: Comments | M6: Original Estimates | N6: Remaining Estimates | O6: CMS-Deepcreek BM | P6: QA-54 | Q6: Newyse Live Test Cases
A7: QA-3465 | B7: RT_Owner Manager Owner | C7: P3 | D7: OwnerMngr_Owner | E7: QA-1795 | F7: Ritesh Kumar | G7: 4h | H7: Y | I7: P3 | J7: Ritesh Kumar | K7: =HYPERLINK("https://maxxton.atlassian.net/browse/QA-28973","QA-28973") -> QA-28973 | L7: Created on 2026-03-23 for release 2026_Week_13 | M7: 4h | N7: 1h | O7: CMS-Deepcreek MyEnv | P7: QA-55 | Q7: Newyse Sanity Test Cases
A8: QA-3466 | B8: RT_Owner Manager PreSettlement | C8: P3 | D8: OwnerMngr_PreSettlement | E8: QA-1795 | F8: Ritesh Kumar | G8: 4h | H8: Y | I8: P3 | J8: Ritesh Kumar | K8: =HYPERLINK("https://maxxton.atlassian.net/browse/QA-28974","QA-28974") -> QA-28974 | L8: Created on 2026-03-23 for release 2026_Week_13 | M8: 4h | N8: 2h 30m | O8: CMS-Hogenboom BM | P8: QA-71 | Q8: MXTS Sanity Test Cases
A9: QA-3467 | B9: RT_Owner Manager Settlement | C9: P3 | D9: OwnerMngr_Settlement | E9: QA-1795 | F9: Ritesh Kumar | G9: 4h 30m | H9: Y | I9: P3 | J9: Ritesh Kumar | K9: =HYPERLINK("https://maxxton.atlassian.net/browse/QA-28975","QA-28975") -> QA-28975 | L9: Created on 2026-03-23 for release 2026_Week_13 | M9: 4h 30m | N9: 4h 30m | O9: CMS-Hogenboom MyEnv | P9: QA-72 | Q9: MXTS Regression Test Cases
A10: QA-3468 | B10: RT_Owner Manager PostSettlement | C10: P3 | D10: OwnerMngr_PostSettlement | E10: QA-1795 | F10: Ritesh Kumar | G10: 2h | H10: Y | I10: P3 | J10: Ritesh Kumar | K10: =HYPERLINK("https://maxxton.atlassian.net/browse/QA-28976","QA-28976") -> QA-28976 | L10: Created on 2026-03-23 for release 2026_Week_13 | M10: 2h | N10: 2h | O10: CMS-Krim BM
A11: QA-4208 | B11: RT_FnMngr_FM_Configuration | C11: P3 | D11: FnMngr_Ledgers | E11: QA-4207 | F11: Ashwini Kedare | G11: 4h | H11: Y | I11: P3 | J11: Nikhil Gurav | K11: =HYPERLINK("https://maxxton.atlassian.net/browse/QA-28977","QA-28977") -> QA-28977 | L11: Created on 2026-03-23 for release 2026_Week_13 | M11: 4h | N11: 1h 30m | O11: CMS-Krim MyEnv
A12: QA-4209 | B12: RT_FnMngr_Payments_Statements/ Unassigned_Payments | C12: P3 | D12: FnMngr_Revenue_Distri_Rules | E12: QA-4207 | F12: Ashwini Kedare | G12: 4h | H12: Y | I12: P3 | J12: Nikhil Gurav | K12: =HYPERLINK("https://maxxton.atlassian.net/browse/QA-28978","QA-28978") -> QA-28978 | L12: Created on 2026-03-23 for release 2026_Week_13 | M12: 4h | N12: 2h | O12: CMS-PerfectExp BM
A13: QA-4210 | B13: RT_FnMngr_Revenue_Distribution_Process RD/ RD Scheduler/ RD Rules | C13: P3 | D13: FnMngr_Revenue_Distri_Processing | E13: QA-4207 | F13: Nikhil Gurav | G13: 4h | H13: Y | I13: P3 | J13: Nikhil Gurav | K13: =HYPERLINK("https://maxxton.atlassian.net/browse/QA-28979","QA-28979") -> QA-28979 | L13: Created on 2026-03-23 for release 2026_Week_13 | M13: 4h | N13: 2h | O13: CMS-PerfectExp MyEnv
A14: QA-4211 | B14: RT_FnMngr_Financial_Reports_JR/FTR & Financial_Archive | C14: P3 | D14: FnMngr_Trans_Archiver | E14: QA-4207 | F14: Nikhil Gurav | G14: 4h | H14: Y | I14: P3 | J14: Nikhil Gurav | K14: =HYPERLINK("https://maxxton.atlassian.net/browse/QA-28980","QA-28980") -> QA-28980 | L14: Created on 2026-03-23 for release 2026_Week_13 | M14: 4h | N14: 4h | O14: CMS-Roompot BM
A15: QA-23620 | B15: RT_FnMngr_Agent_Settlement | C15: P3 | D15: FnMngr_Trans_Archiver | E15: QA-4207 | F15: Ashwini Kedare | G15: 2h | H15: Y | I15: P3 | J15: Nikhil Gurav | K15: =HYPERLINK("https://maxxton.atlassian.net/browse/QA-28981","QA-28981") -> QA-28981 | L15: Created on 2026-03-23 for release 2026_Week_13 | M15: 2h | N15: 0h | O15: CMS-Roompot MyEnv
A16: =HYPERLINK("https://maxxton.atlassian.net/browse/QA-23955","QA-23955") -> QA-23955 | B16: RT_NF525_Sii Invoices | C16: P3 | D16: FnMngr_Trans_Archiver | E16: QA-4207 | F16: Ritesh Kumar | G16: 4h | H16: Y | I16: P3 | J16: Ritesh Kumar | K16: =HYPERLINK("https://maxxton.atlassian.net/browse/QA-28982","QA-28982") -> QA-28982 | L16: Created on 2026-03-23 for release 2026_Week_13 | M16: 4h | N16: 4h | O16: CMS-Siblu BM
A17: =HYPERLINK("https://maxxton.atlassian.net/browse/QA-23956","QA-23956") -> QA-23956 | B17: RT_NF525_Sii_Jeng | C17: P3 | D17: FnMngr_Trans_Archiver | E17: QA-4207 | F17: Nikhil Gurav | G17: 4h | H17: Y | I17: P3 | J17: Nikhil Gurav | K17: =HYPERLINK("https://maxxton.atlassian.net/browse/QA-28983","QA-28983") -> QA-28983 | L17: Created on 2026-03-23 for release 2026_Week_13 | M17: 4h | N17: 4h | O17: CMS-Siblu MyEnv
O18: MXTS-BackOffice Manager
O19: MXTS-Content Manager
O20: MXTS-Implementation Manager
O21: MXTS-Owner Manager
O22: MXTS-Rate Manager
O23: MXTS-Reservation Manager
O24: MXTS-PaymentService
O25: CMS-RCN MyEnv
O26: CMS-EuroparcsNL MyEnv

Sheet Operations
P1: Components | Q1: Epic
F2: Total Test Cases | G2: =countifs(A:A,"<>NEW",A:A,"<>")-1 -> 27 | P2: CMS-Castle BM | Q2: QA-1 | R2: Newyse Regression Test Cases
F3: Schedule? Y | G3: =countif(H:H,"=Y") -> 17 | P3: CMS-Castle MyEnv | Q3: QA-24 | R3: CMS Regression Test Cases
F4: New Test Cases | G4: =COUNTIF(A:A,"=NEW") -> 0 | P4: CMS-Contempo BM | Q4: QA-25 | R4: CMS Live Test Cases
P5: CMS-Contempo MyEnv | Q5: QA-26 | R5: CMS Sanity Test Cases
A6: Key | B6: Summary | C6: Priority | D6: Component | E6: Epic Link | F6: Test Case Assignee | G6: Estimate | H6: Schedule ? | I6: Execution Priority | J6: Execution By | K6: Test Result Ticket | L6: Comments | M6: Remark | N6: Original Estimates | O6: Remaining Estimates | P6: CMS-Deepcreek BM | Q6: QA-54 | R6: Newyse Live Test Cases
A7: QA-3939 | B7: RT_Planning Creation | C7: P3 | D7: OpnMngr_HK_Dashboard | E7: QA-3936 | F7: Narendra Deshmane | G7: 120m | H7: Y | I7: P3 | J7: Narendra Deshmane | K7: =HYPERLINK("https://maxxton.atlassian.net/browse/QA-29094","QA-29094") -> QA-29094 | L7: Created on 2026-04-03 for release 2026_Week_15 | N7: 120m | O7: 40m | P7: CMS-Deepcreek MyEnv | Q7: QA-55 | R7: Newyse Sanity Test Cases
A8: QA-3940 | B8: RT_HK Dashboard Summary page | C8: P3 | D8: OpnMngr_HK_Dashboard | E8: QA-3936 | F8: Narendra Deshmane | G8: 60m | H8: Y | I8: P3 | J8: Narendra Deshmane | K8: =HYPERLINK("https://maxxton.atlassian.net/browse/QA-29095","QA-29095") -> QA-29095 | L8: Created on 2026-04-03 for release 2026_Week_15 | N8: 60m | O8: 10m | P8: CMS-Hogenboom BM | Q8: QA-71 | R8: MXTS Sanity Test Cases
A9: QA-3941 | B9: RT_Employee Detail Page | C9: P3 | D9: OpnMngr_HK_Dashboard | E9: QA-3936 | F9: Narendra Deshmane | G9: 60m | H9: Y | I9: P3 | J9: Narendra Deshmane | K9: =HYPERLINK("https://maxxton.atlassian.net/browse/QA-29096","QA-29096") -> QA-29096 | L9: Created on 2026-04-03 for release 2026_Week_15 | N9: 60m | O9: 20m | P9: CMS-Hogenboom MyEnv | Q9: QA-72 | R9: MXTS Regression Test Cases
A10: QA-3942 | B10: RT_Planning Dashboard Page | C10: P3 | D10: OpnMngr_HK_PlanningDashboard | E10: QA-3936 | F10: Narendra Deshmane | G10: 60m | H10: Y | I10: P3 | J10: Narendra Deshmane | K10: =HYPERLINK("https://maxxton.atlassian.net/browse/QA-29097","QA-29097") -> QA-29097 | L10: Created on 2026-04-03 for release 2026_Week_15 | N10: 60m | O10: 20m | P10: CMS-Krim BM
A11: QA-3943 | B11: RT_Assign Employee Page | C11: P3 | D11: OpnMngr_HK_PlanningDashboard | E11: QA-3936 | F11: Narendra Deshmane | G11: 60m | H11: Y | I11: P3 | J11: Narendra Deshmane | K11: =HYPERLINK("https://maxxton.atlassian.net/browse/QA-29098","QA-29098") -> QA-29098 | L11: Created on 2026-04-03 for release 2026_Week_15 | N11: 60m | O11: 10m | P11: CMS-Krim MyEnv
A12: QA-3944 | B12: RT_Task Configuation | C12: P3 | D12: OpnMngr_HK_Config | E12: QA-3936 | F12: Narendra Deshmane | G12: 60m | H12: Y | I12: P3 | J12: Narendra Deshmane | K12: =HYPERLINK("https://maxxton.atlassian.net/browse/QA-29099","QA-29099") -> QA-29099 | L12: Created on 2026-04-03 for release 2026_Week_15 | N12: 60m | O12: 15m | P12: CMS-PerfectExp BM
A13: QA-3945 | B13: RT_Sector Configuration | C13: P3 | D13: OpnMngr_HK_Config | E13: QA-3936 | F13: Narendra Deshmane | G13: 60m | H13: N | I13: P3 | J13: Narendra Deshmane | K13: =HYPERLINK("https://maxxton.atlassian.net/browse/QA-22621","QA-22621") -> QA-22621 | L13: Created on 2025-02-20 for release 2025_Week_09 | M13: Merged in QA-3944 | N13: 60m | O13: 10m | P13: CMS-PerfectExp MyEnv
A14: QA-3946 | B14: RT_Maint Dashboard Summary Page | C14: P3 | D14: OpnMngr_Maint_Dashboard | E14: QA-3937 | F14: Narendra Deshmane | G14: 60m | H14: N | I14: P3 | J14: Narendra Deshmane | K14: =HYPERLINK("https://maxxton.atlassian.net/browse/QA-22622","QA-22622") -> QA-22622 | L14: Created on 2025-02-20 for release 2025_Week_09 | M14: Merged in QA-3947 | N14: 60m | O14: 10m | P14: CMS-Roompot BM
A15: QA-3947 | B15: RT_Work Order Daily Operation | C15: P3 | D15: OpnMngr_Maint_Dashboard | E15: QA-3937 | F15: Narendra Deshmane | G15: 90m | H15: Y | I15: P3 | J15: Narendra Deshmane | K15: =HYPERLINK("https://maxxton.atlassian.net/browse/QA-29100","QA-29100") -> QA-29100 | L15: Created on 2026-04-03 for release 2026_Week_15 | N15: 60m | O15: 10m | P15: CMS-Roompot MyEnv
A16: QA-3948 | B16: RT_Work Order Creat/edit | C16: P3 | D16: OpnMngr_Maint_WorkOrderList | E16: QA-3937 | F16: Narendra Deshmane | G16: 60m | H16: Y | I16: P3 | J16: Narendra Deshmane | K16: =HYPERLINK("https://maxxton.atlassian.net/browse/QA-29101","QA-29101") -> QA-29101 | L16: Created on 2026-04-03 for release 2026_Week_15 | N16: 60m | O16: 10m | P16: CMS-Siblu BM
A17: QA-3949 | B17: RT_Work Order Invoicing | C17: P3 | D17: OpnMngr_Maint_WorkOrderList | E17: QA-3937 | F17: Narendra Deshmane | G17: 60m | H17: N | I17: P3 | J17: Narendra Deshmane | K17: =HYPERLINK("https://maxxton.atlassian.net/browse/QA-22625","QA-22625") -> QA-22625 | L17: Created on 2025-02-20 for release 2025_Week_09 | M17: Merged in QA-3948 | N17: 60m | O17: 20m | P17: CMS-Siblu MyEnv
A18: QA-3950 | B18: RT_WO Categories Configuration | C18: P3 | D18: OpnMngr_Maint_Config | E18: QA-3937 | F18: Narendra Deshmane | G18: 60m | H18: Y | I18: P3 | J18: Narendra Deshmane | K18: =HYPERLINK("https://maxxton.atlassian.net/browse/QA-29102","QA-29102") -> QA-29102 | L18: Created on 2026-04-03 for release 2026_Week_15 | N18: 60m | O18: 5m | P18: MXTS-BackOffice Manager
A19: QA-3951 | B19: RT_App HK Dashboard | C19: P3 | D19: OpnMngr_App_HK | E19: QA-3938 | F19: Narendra Deshmane | G19: 60m | H19: N | I19: P3 | J19: Narendra Deshmane | K19: =HYPERLINK("https://maxxton.atlassian.net/browse/QA-22627","QA-22627") -> QA-22627 | L19: Created on 2025-02-20 for release 2025_Week_09 | M19: Merged in QA-3952 | N19: 60m | O19: 60m | P19: MXTS-Content Manager
A20: QA-3952 | B20: RT_App Task Detail Screen | C20: P3 | D20: OpnMngr_App_HK | E20: QA-3938 | F20: Narendra Deshmane | G20: 60m | H20: Y | I20: P3 | J20: Narendra Deshmane | K20: =HYPERLINK("https://maxxton.atlassian.net/browse/QA-29103","QA-29103") -> QA-29103 | L20: Created on 2026-04-03 for release 2026_Week_15 | N20: 60m | O20: 60m | P20: MXTS-Implementation Manager
A21: QA-3953 | B21: RT_App Maint Dashboard | C21: P3 | D21: OpnMngr_App_Maint | E21: QA-3938 | F21: Narendra Deshmane | G21: 60m | H21: N | I21: P3 | J21: Narendra Deshmane | K21: =HYPERLINK("https://maxxton.atlassian.net/browse/QA-22629","QA-22629") -> QA-22629 | L21: Created on 2025-02-20 for release 2025_Week_09 | M21: Merged in QA-3954 | N21: 60m | O21: 60m | P21: MXTS-Owner Manager
A22: QA-3954 | B22: RT_App Work Order Detail Screen | C22: P3 | D22: OpnMngr_App_Maint | E22: QA-3938 | F22: Narendra Deshmane | G22: 60m | H22: Y | I22: P3 | J22: Narendra Deshmane | K22: =HYPERLINK("https://maxxton.atlassian.net/browse/QA-29104","QA-29104") -> QA-29104 | L22: Created on 2026-04-03 for release 2026_Week_15 | N22: 60m | O22: 60m | P22: MXTS-Rate Manager
A23: QA-7395 | B23: RT_Periodical Tasks | C23: P3 | D23: OpnMngr_Perio_task | E23: QA-3937 | F23: Narendra Deshmane | G23: 60m | H23: Y | I23: P3 | J23: Narendra Deshmane | K23: =HYPERLINK("https://maxxton.atlassian.net/browse/QA-29105","QA-29105") -> QA-29105 | L23: Created on 2026-04-03 for release 2026_Week_15 | N23: 60m | O23: 20m | P23: MXTS-Reservation Manager
A24: QA-7615 | B24: RT_Inspection | C24: P3 | D24: OpnMngr_Maint_Inspection | E24: QA-3937 | F24: Narendra Deshmane | G24: 90m | H24: Y | I24: P3 | J24: Narendra Deshmane | K24: =HYPERLINK("https://maxxton.atlassian.net/browse/QA-29106","QA-29106") -> QA-29106 | L24: Created on 2026-04-03 for release 2026_Week_15 | N24: 90m | O24: 20m | P24: MXTS-PaymentService
A25: QA-10282 | B25: RT_WO Item Configuration | C25: P3 | D25: OpnMngr_Maint_Config | E25: QA-3937 | F25: Narendra Deshmane | G25: 60m | H25: N | I25: P3 | J25: Narendra Deshmane | K25: =HYPERLINK("https://maxxton.atlassian.net/browse/QA-22633","QA-22633") -> QA-22633 | L25: Created on 2025-02-20 for release 2025_Week_09 | M25: Merged in QA-3950 | N25: 60m | O25: 5m | P25: CMS-RCN MyEnv
A26: QA-10283 | B26: RT_WO Area Configuration | C26: P3 | D26: OpnMngr_Maint_Config | E26: QA-3937 | F26: Narendra Deshmane | G26: 60m | H26: N | I26: P3 | J26: Narendra Deshmane | K26: =HYPERLINK("https://maxxton.atlassian.net/browse/QA-22634","QA-22634") -> QA-22634 | L26: Created on 2025-02-20 for release 2025_Week_09 | M26: Merged in QA-3950 | N26: 60m | O26: 5m | P26: CMS-EuroparcsNL MyEnv
A27: QA-10284 | B27: RT_WO Materials Configuration | C27: P3 | D27: OpnMngr_Maint_Config | E27: QA-3937 | F27: Narendra Deshmane | G27: 60m | H27: Y | I27: P3 | J27: Narendra Deshmane | K27: =HYPERLINK("https://maxxton.atlassian.net/browse/QA-29107","QA-29107") -> QA-29107 | L27: Created on 2026-04-03 for release 2026_Week_15 | N27: 60m | O27: 5m
A28: QA-10285 | B28: RT_Periodical Task Configuration | C28: P3 | D28: OpnMngr_Maint_Config | E28: QA-3937 | F28: Narendra Deshmane | G28: 60m | H28: Y | I28: P3 | J28: Narendra Deshmane | K28: =HYPERLINK("https://maxxton.atlassian.net/browse/QA-29108","QA-29108") -> QA-29108 | L28: Created on 2026-04-03 for release 2026_Week_15 | N28: 60m | O28: 20m
A29: QA-16460 | B29: RT_App Periodical Task | C29: P3 | D29: OpnMngr_App_Maint | E29: QA-3938 | F29: Narendra Deshmane | G29: 60m | H29: Y | I29: P3 | J29: Narendra Deshmane | K29: =HYPERLINK("https://maxxton.atlassian.net/browse/QA-29109","QA-29109") -> QA-29109 | L29: Created on 2026-04-03 for release 2026_Week_15 | N29: 60m | O29: 60m
A30: QA-16461 | B30: RT_App Meter Reading | C30: P3 | D30: OpnMngr_App_Maint | E30: QA-3938 | F30: Narendra Deshmane | G30: 60m | H30: N | I30: P3 | J30: Narendra Deshmane | K30: =HYPERLINK("https://maxxton.atlassian.net/browse/QA-22638","QA-22638") -> QA-22638 | L30: Created on 2025-02-20 for release 2025_Week_09 | M30: Merged in QA-16460 | N30: 60m | O30: 60m
A31: QA-16462 | B31: RT_App Barrier Control and Inspection | C31: P3 | D31: OpnMngr_App_Maint | E31: QA-3938 | F31: Narendra Deshmane | G31: 60m | H31: N | I31: P3 | J31: Narendra Deshmane | K31: =HYPERLINK("https://maxxton.atlassian.net/browse/QA-27233","QA-27233") -> QA-27233 | L31: Created on 2025-11-27 for release 2025_Week_49 | N31: 60m | O31: 60m
A32: QA-19284 | B32: RT_WO Material Supplier Configuration | C32: P3 | D32: OpnMngr_Maint_Config | E32: QA-3937 | F32: Narendra Deshmane | G32: 60m | H32: N | I32: P3 | J32: Narendra Deshmane | K32: =HYPERLINK("https://maxxton.atlassian.net/browse/QA-22639","QA-22639") -> QA-22639 | L32: Created on 2025-02-20 for release 2025_Week_09 | M32: Merged in QA-10284 | N32: 60m | O32: 5m
A33: =HYPERLINK("https://maxxton.atlassian.net/browse/QA-22962","QA-22962") -> QA-22962 | B33: RT_Work schedule module | C33: P3 | D33: OpnMngr_Maint_Config | E33: QA-3937 | F33: Narendra Deshmane | G33: 60m | H33: Y | I33: P3 | J33: Narendra Deshmane | K33: =HYPERLINK("https://maxxton.atlassian.net/browse/QA-29110","QA-29110") -> QA-29110 | L33: Created on 2026-04-03 for release 2026_Week_15 | N33: 90m | O33: 20m

Sheet Rates
O1: Components | P1: Epic
F2: Total Test Cases | G2: =countifs(A:A,"<>NEW",A:A,"<>")-1 -> 10 | O2: CMS-Castle BM | P2: QA-1 | Q2: Newyse Regression Test Cases
F3: Schedule? Y | G3: =countif(H:H,"=Y") -> 6 | O3: CMS-Castle MyEnv | P3: QA-24 | Q3: CMS Regression Test Cases
F4: New Test Cases | G4: =COUNTIF(A:A,"=NEW") -> 0 | O4: CMS-Contempo BM | P4: QA-25 | Q4: CMS Live Test Cases
E5: API token | F5: ciTSS7f3VPYW8Af3i2ZO923A | H5: 2025_Week_17 | O5: CMS-Contempo MyEnv | P5: QA-26 | Q5: CMS Sanity Test Cases
A6: Key | B6: Summary | C6: Priority | D6: Component | E6: Epic Link | F6: Test Case Assignee | G6: Estimate | H6: Schedule ? | I6: Execution Priority | J6: Execution By | K6: Test Result Ticket | L6: Comments | M6: Original Estimates | N6: Remaining Estimates | O6: CMS-Deepcreek BM | P6: QA-54 | Q6: Newyse Live Test Cases
A7: QA-3046 | B7: RT_Rate Screen | C7: P3 | D7: RtMngr_Rates | E7: QA-1782 | F7: Mahesh Pawar | G7: 2h | H7: N | I7: P3 | J7: Mahesh Pawar | K7: =HYPERLINK("https://maxxton.atlassian.net/browse/QA-24171","QA-24171") -> QA-24171 | L7: Created on 2025-05-16 for release 2025_Week_21 | M7: 1h | N7: 30m | O7: CMS-Deepcreek MyEnv | P7: QA-55 | Q7: Newyse Sanity Test Cases
A8: QA-3056 | B8: RT_Accomodation Type | C8: P3 | D8: RtMngr_AccomodationType | E8: QA-1782 | F8: Mahesh Pawar | G8: 2h | H8: Y | I8: P3 | J8: Mahesh Pawar | K8: =HYPERLINK("https://maxxton.atlassian.net/browse/QA-28953","QA-28953") -> QA-28953 | L8: Created on 2026-03-22 for release 2026_Week_13 | M8: 2h | N8: 20m | O8: CMS-PerfectExp MyEnv
A9: QA-3047 | B9: RT_Rate Types | C9: P3 | D9: RtMngr_RateTypes | E9: QA-1782 | F9: Mahesh Pawar | G9: 2h | H9: Y | I9: P3 | J9: Mahesh Pawar | K9: =HYPERLINK("https://maxxton.atlassian.net/browse/QA-28954","QA-28954") -> QA-28954 | L9: Created on 2026-03-22 for release 2026_Week_13 | M9: 2h | N9: 30m | O9: CMS-Krim BM
A10: =HYPERLINK("https://maxxton.atlassian.net/browse/QA-9473","QA-9473") -> QA-9473 | B10: RT_Package | C10: P3 | D10: RtMngr_Offer | E10: QA-1782 | F10: Mahesh Pawar | G10: 2h | H10: N | I10: P3 | J10: Mahesh Pawar | K10: =HYPERLINK("https://maxxton.atlassian.net/browse/QA-27792","QA-27792") -> QA-27792 | L10: Created on 2026-01-12 for release 2026_Week_03 | M10: 3h | N10: 60m | O10: MXTS-BackOffice Manager
A11: =HYPERLINK("https://maxxton.atlassian.net/browse/QA-9476","QA-9476") -> QA-9476 | B11: RT_Offer/Package Import | C11: P3 | D11: RtMngr_Offer | E11: QA-1782 | F11: Mahesh Pawar | G11: 2h | H11: Y | I11: P3 | J11: Mahesh Pawar | K11: =HYPERLINK("https://maxxton.atlassian.net/browse/QA-28955","QA-28955") -> QA-28955 | L11: Created on 2026-03-22 for release 2026_Week_13 | M11: 1h | N11: 60m | O11: MXTS-Content Manager
A12: QA-17104 | B12: RT_Offer | C12: P3 | D12: RtMngr_Offer | E12: QA-1782 | F12: Mahesh Pawar | G12: 2h | H12: Y | I12: P3 | J12: Mahesh Pawar | K12: =HYPERLINK("https://maxxton.atlassian.net/browse/QA-28956","QA-28956") -> QA-28956 | L12: Created on 2026-03-22 for release 2026_Week_13 | M12: 3h | N12: 60m | O12: MXTS-Implementation Manager
A13: QA-3058 | B13: RT_Rentability Set | C13: P3 | D13: RtMngr_RentabilitySet | E13: QA-1782 | F13: Mahesh Pawar | G13: 2h | H13: Y | I13: P3 | J13: Mahesh Pawar | K13: =HYPERLINK("https://maxxton.atlassian.net/browse/QA-28957","QA-28957") -> QA-28957 | L13: Created on 2026-03-22 for release 2026_Week_13 | M13: 2h | N13: 30m | O13: CMS-Roompot MyEnv
A14: QA-3060 | B14: RT_Batch Updates | C14: P3 | D14: RtMngr_Import&BatchUpdates | E14: QA-1782 | F14: Mahesh Pawar | G14: 2h | H14: N | I14: P3 | J14: Mahesh Pawar | K14: =HYPERLINK("https://maxxton.atlassian.net/browse/QA-27795","QA-27795") -> QA-27795 | L14: Created on 2026-01-12 for release 2026_Week_03 | M14: 2h | N14: 30m | O14: CMS-Siblu MyEnv
A15: QA-3059 | B15: RT_Rates Imports | C15: P3 | D15: RtMngr_Import&BatchUpdates | E15: QA-1782 | F15: Mahesh Pawar | G15: 2h | H15: N | I15: P3 | J15: Mahesh Pawar | K15: =HYPERLINK("https://maxxton.atlassian.net/browse/QA-24759","QA-24759") -> QA-24759 | L15: Created on 2025-06-27 for release 2025_Week_27 | M15: 1h | N15: 60m | O15: CMS-Siblu BM
A16: QA-19070 | B16: RT_Vouchers | C16: P3 | D16: RtMngr_Voucher | E16: QA-1782 | F16: Mahesh Pawar | G16: 2h | H16: Y | I16: P3 | J16: Mahesh Pawar | K16: =HYPERLINK("https://maxxton.atlassian.net/browse/QA-28958","QA-28958") -> QA-28958 | L16: Created on 2026-03-22 for release 2026_Week_13 | M16: 1h | N16: 30m | O16: CMS-Siblu BM
L17: Total Hrs | M17: 18h | N17: 7h

Sheet ThirdPartyAPI(New)
F2: Total Test Cases | G2: =countifs(A:A,"<>NEW",A:A,"<>")-1 -> 42 | O2: Components | P2: Epic
F3: Schedule? Y | G3: =countif(H:H,"=Y") -> 14
F4: New Test Cases | G4: =COUNTIF(A:A,"=NEW") -> 0
O5: API_BatchEventDelta | P5: QA-26 | Q5: CMS Sanity Test Cases
A6: Key | B6: Summary | C6: Priority | D6: Component | E6: Epic Link | F6: Test Case Assignee | G6: Estimate | H6: Schedule ? | I6: Execution Priority | J6: Execution By | K6: Test Result Ticket | L6: Comments | M6: Original Estimates | N6: Remaining Estimates | O6: API_Owner Related | P6: QA-54 | Q6: Newyse Live Test Cases
A7: QA-1432 | B7: RT_API_Property_Details_Accommodationtypes_P1 | C7: P1 | D7: TPI_AccommodationTpes | E7: QA-1223 | F7: Anup Sinha | G7: 2h | H7: Y | I7: P1 | J7: Anup Sinha | K7: =HYPERLINK("https://maxxton.atlassian.net/browse/QA-28959","QA-28959") -> QA-28959 | L7: Created on 2026-03-23 for release 2026_Week_13 | M7: 2 | P7: QA-72 | Q7: MXTS Regression Test Cases
A8: QA-1501 | B8: RT_API_Property_Details_Amenity_P1 | C8: P1 | D8: TPI_Amenity | E8: QA-1223 | F8: Aparna Shinde | G8: 1h | H8: Y | I8: P1 | J8: Aparna Shinde | K8: =HYPERLINK("https://maxxton.atlassian.net/browse/QA-28960","QA-28960") -> QA-28960 | L8: Created on 2026-03-23 for release 2026_Week_13 | M8: 30m
A9: QA-1475 | B9: RT_API_Property_Details_AddOn_P1 | C9: P1 | D9: TPI_AddOn | E9: QA-1223 | F9: Anup Sinha | G9: 1h | H9: Y | I9: P1 | J9: Aparna Shinde | K9: =HYPERLINK("https://maxxton.atlassian.net/browse/QA-28961","QA-28961") -> QA-28961 | L9: Created on 2026-03-23 for release 2026_Week_13 | M9: 1
A10: QA-1506 | B10: API_Master Data_P1 | C10: P1 | D10: TPI_MasterData | E10: QA-1223 | F10: Aparna Shinde | G10: 2h | H10: Y | I10: P1 | J10: Aparna Shinde | K10: =HYPERLINK("https://maxxton.atlassian.net/browse/QA-28962","QA-28962") -> QA-28962 | L10: Created on 2026-03-23 for release 2026_Week_13 | M10: 45m
A11: QA-1534 | B11: API_Customer_P1 | C11: P1 | D11: TPI_Customer | E11: QA-1223 | F11: Aparna Shinde | G11: 4h | H11: Y | I11: P1 | J11: Anup Sinha | K11: =HYPERLINK("https://maxxton.atlassian.net/browse/QA-28963","QA-28963") -> QA-28963 | L11: Created on 2026-03-23 for release 2026_Week_13 | M11: 1
A12: QA-1512 | B12: API_Batches/Delta/Events _Event_P1 | C12: P1 | D12: TPI_Events | E12: QA-1223 | F12: Aparna Shinde | G12: 2h | H12: Y | I12: P1 | J12: Aparna Shinde | K12: =HYPERLINK("https://maxxton.atlassian.net/browse/QA-28964","QA-28964") -> QA-28964 | L12: Created on 2026-03-23 for release 2026_Week_13 | M12: 30m
A13: =HYPERLINK("https://maxxton.atlassian.net/browse/QA-10650","QA-10650") -> QA-10650 | B13: API_Housekeepings_P1 | C13: P1 | D13: TPI_Housekeeping | E13: QA-1223 | F13: Aparna Shinde | G13: 30m | H13: N | I13: P1 | J13: Aparna Shinde | K13: =HYPERLINK("https://maxxton.atlassian.net/browse/QA-24306","QA-24306") -> QA-24306 | L13: Created on 2025-05-29 for release 2025_Week_23 | M13: 1
A14: =HYPERLINK("https://maxxton.atlassian.net/browse/QA-11287","QA-11287") -> QA-11287 | B14: API_Infotexts_P1 | C14: P1 | D14: TPI_Infotexts | E14: QA-1223 | F14: Anup Sinha | G14: 1h | H14: Y | I14: P1 | J14: Anup Sinha | K14: =HYPERLINK("https://maxxton.atlassian.net/browse/QA-28965","QA-28965") -> QA-28965 | L14: Created on 2026-03-23 for release 2026_Week_13 | M14: 1
A15: =HYPERLINK("https://maxxton.atlassian.net/browse/QA-15098","QA-15098") -> QA-15098 | B15: API_Operations_P1 | C15: P1 | D15: TPI_Operations | E15: QA-1223 | F15: Anup Sinha | G15: 1h | H15: N | I15: P1 | J15: Anup Sinha | K15: =HYPERLINK("https://maxxton.atlassian.net/browse/QA-24308","QA-24308") -> QA-24308 | L15: Created on 2025-05-29 for release 2025_Week_23 | M15: 1
A16: QA-1429 | B16: RT_API_Property_Details_Resort_P1 | C16: P1 | D16: TPI_Resorts | E16: QA-1223 | F16: Anup Sinha | G16: 30m | H16: Y | I16: P1 | J16: Anup Sinha | K16: =HYPERLINK("https://maxxton.atlassian.net/browse/QA-28966","QA-28966") -> QA-28966 | L16: Created on 2026-03-23 for release 2026_Week_13 | M16: 2 | O16: API_SearchAndBook | P16: QA-55 | Q16: Newyse Sanity Test Cases
A17: QA-1431 | B17: RT_API_Property_Details_Units_P1 | C17: P1 | D17: TPI_Units | E17: QA-1223 | F17: Anup Sinha | G17: 2h | H17: Y | I17: P1 | J17: Anup Sinha | K17: =HYPERLINK("https://maxxton.atlassian.net/browse/QA-28967","QA-28967") -> QA-28967 | L17: Created on 2026-03-23 for release 2026_Week_13 | M17: 2 | O17: API_Master Data | P17: QA-71 | Q17: MXTS Sanity Test Cases
A18: QA-1473 | B18: RT_API_Property_Details_Offers_P1 | C18: P1 | D18: TPI_Offers | E18: QA-1223 | F18: Anup Sinha | G18: 4h | H18: Y | I18: P1 | J18: Anup Sinha | K18: =HYPERLINK("https://maxxton.atlassian.net/browse/QA-28968","QA-28968") -> QA-28968 | L18: Created on 2026-03-23 for release 2026_Week_13 | M18: 1
A19: QA-1513 | B19: API_Owner_P1 | C19: P1 | D19: TPI_owners | E19: QA-1223 | F19: Anup Sinha | G19: 4h | H19: Y | I19: P1 | J19: Anup Sinha | K19: =HYPERLINK("https://maxxton.atlassian.net/browse/QA-28969","QA-28969") -> QA-28969 | L19: Created on 2026-03-23 for release 2026_Week_13 | M19: 2
A20: QA-1508 | B20: API_Reservations_P1_Reservation_proposal | C20: P1 | D20: TPI_Reservations/TPI_ReservationProposal | E20: QA-1223 | F20: Aparna Shinde | G20: 2h | H20: Y | I20: P1 | J20: Aparna Shinde | K20: =HYPERLINK("https://maxxton.atlassian.net/browse/QA-28970","QA-28970") -> QA-28970 | L20: Created on 2026-03-23 for release 2026_Week_13 | M20: 1h 30m
A21: QA-1531 | B21: API_Reservations_P1_Reservations | C21: P1 | D21: TPI_Reservations | E21: QA-1223 | F21: Aparna Shinde | G21: 2h | H21: Y | I21: P1 | J21: Aparna Shinde | K21: =HYPERLINK("https://maxxton.atlassian.net/browse/QA-28971","QA-28971") -> QA-28971 | L21: Created on 2026-03-23 for release 2026_Week_13 | M21: 1h 30m
A22: QA-1532 | B22: API_Reservations_P1_Others | C22: P1 | D22: TPI_Reservations | E22: QA-1223 | F22: Anup Sinha | G22: 4h | H22: Y | I22: P1 | J22: Anup Sinha | K22: =HYPERLINK("https://maxxton.atlassian.net/browse/QA-28972","QA-28972") -> QA-28972 | L22: Created on 2026-03-23 for release 2026_Week_13 | M22: 3h
A23: QA-9613 | B23: To view recent requests of an API user | C23: P2 | D23: TPI_IntegrationManager | E23: QA-9605 | G23: 2h | H23: N | I23: P3 | K23: =HYPERLINK("https://maxxton.atlassian.net/browse/QA-17792","QA-17792") -> QA-17792 | L23: Created on 2024-05-02 for release 2024_Week_19 | M23: 15m
A24: QA-9606 | B24: API user Creation | C24: P2 | D24: TPI_IntegrationManager | E24: QA-9605 | G24: 30m | H24: N | I24: P3 | K24: =HYPERLINK("https://maxxton.atlassian.net/browse/QA-17793","QA-17793") -> QA-17793 | L24: Created on 2024-05-02 for release 2024_Week_19 | M24: 1h
A25: QA-9607 | B25: To view and add new credentials for an API user | C25: P2 | D25: TPI_IntegrationManager | E25: QA-9605 | G25: 30m | H25: N | I25: P3 | K25: =HYPERLINK("https://maxxton.atlassian.net/browse/QA-17794","QA-17794") -> QA-17794 | L25: Created on 2024-05-02 for release 2024_Week_19 | M25: 30m
A26: QA-9608 | B26: To view and update Linked Locations for an API user | C26: P2 | D26: TPI_IntegrationManager | E26: QA-9605 | G26: 30m | H26: N | I26: P3 | K26: =HYPERLINK("https://maxxton.atlassian.net/browse/QA-17795","QA-17795") -> QA-17795 | L26: Created on 2024-05-02 for release 2024_Week_19 | M26: 30m
A27: QA-9609 | B27: Updating Permissions for an API user | C27: P2 | D27: TPI_IntegrationManager | E27: QA-9605 | G27: 30m | H27: N | I27: P3 | K27: =HYPERLINK("https://maxxton.atlassian.net/browse/QA-17796","QA-17796") -> QA-17796 | L27: Created on 2024-05-02 for release 2024_Week_19 | M27: 30m
A28: QA-9610 | B28: Calculating API usage costs | C28: P2 | D28: TPI_IntegrationManager | E28: QA-9605 | G28: 30m | H28: N | I28: P3 | K28: =HYPERLINK("https://maxxton.atlassian.net/browse/QA-17797","QA-17797") -> QA-17797 | L28: Created on 2024-05-02 for release 2024_Week_19 | M28: 20m
A29: QA-9611 | B29: To view and add new admin organizations for an API user | C29: P2 | D29: TPI_IntegrationManager | E29: QA-9605 | G29: 30m | H29: N | I29: P3 | K29: =HYPERLINK("https://maxxton.atlassian.net/browse/QA-17798","QA-17798") -> QA-17798 | L29: Created on 2024-05-02 for release 2024_Week_19 | M29: 30m
A30: QA-9612 | B30: Searching an API user and viewing API documentation | C30: P2 | D30: TPI_IntegrationManager | E30: QA-9605 | G30: 30m | H30: N | I30: P3 | K30: =HYPERLINK("https://maxxton.atlassian.net/browse/QA-17799","QA-17799") -> QA-17799 | L30: Created on 2024-05-02 for release 2024_Week_19 | M30: 15m | O30: Anup Sinha | P30: =COUNTIF(J16:J39, "*Anup Sinha*") -> 5
A31: QA-1433 | B31: RT_API_Property_Details_Accommodationtypes_P2 | C31: P2 | D31: TPI_AccommodationTpes | E31: QA-1223 | G31: 4h | H31: N | I31: P2 | K31: =HYPERLINK("https://maxxton.atlassian.net/browse/QA-22977","QA-22977") -> QA-22977 | L31: Created on 2025-03-12 for release
A32: QA-1430 | B32: RT_API_Property_Details_Resort_P2 | C32: P2 | D32: TPI_Resorts | E32: QA-1223 | G32: 4h | H32: N | I32: P2 | K32: =HYPERLINK("https://maxxton.atlassian.net/browse/QA-22979","QA-22979") -> QA-22979 | L32: Created on 2025-03-12 for release
A33: QA-1250 | B33: RT_API_Property_Details_Units_P2 | C33: P2 | D33: TPI_Units | E33: QA-1223 | G33: 4h | H33: N | I33: P2 | K33: =HYPERLINK("https://maxxton.atlassian.net/browse/QA-22978","QA-22978") -> QA-22978 | L33: Created on 2025-03-12 for release
A34: QA-1514 | B34: API_Owner_P2 | C34: P2 | D34: TPI_owners | E34: QA-1223 | G34: 5h | H34: N | I34: P2 | K34: =HYPERLINK("https://maxxton.atlassian.net/browse/QA-22980","QA-22980") -> QA-22980 | L34: Created on 2025-03-12 for release
A35: QA-1505 | B35: API_Representations_P2 | C35: P2 | D35: TPI_Representations | E35: QA-1223 | G35: 2h | H35: N | I35: P1 | K35: =HYPERLINK("https://maxxton.atlassian.net/browse/QA-22981","QA-22981") -> QA-22981 | L35: Created on 2025-03-12 for release | O35: Rohan Bhegade | P35: =COUNTIF(J16:J39, "*Rohan Bhegade*") -> 0
A36: QA-1503 | B36: API_UnitReservability/Reservability_P2 | C36: P2 | D36: TPI_Reservability | E36: QA-1223 | G36: 2h | H36: N | I36: P1 | K36: =HYPERLINK("https://maxxton.atlassian.net/browse/QA-22982","QA-22982") -> QA-22982 | L36: Created on 2025-03-12 for release | O36: Aparna Shinde | P36: =COUNTIF(J2:J39, "Aparna Shinde") -> 7
A37: =HYPERLINK("https://maxxton.atlassian.net/browse/QA-14981","QA-14981") -> QA-14981 | B37: API_Employee_P2 | C37: P2 | D37: TPI_Employee | E37: QA-1223 | G37: 60m | H37: N | I37: P1 | K37: =HYPERLINK("https://maxxton.atlassian.net/browse/QA-22985","QA-22985") -> QA-22985 | L37: Created on 2025-03-12 for release | M37: 1
A38: QA-15099 | B38: API_Packages_P2 | C38: P2 | D38: TPI_Packages | E38: QA-1223 | G38: 30m | H38: N | I38: P3 | K38: =HYPERLINK("https://maxxton.atlassian.net/browse/QA-22987","QA-22987") -> QA-22987 | L38: Created on 2025-03-12 for release | M38: 1
A39: =HYPERLINK("https://maxxton.atlassian.net/browse/QA-15100","QA-15100") -> QA-15100 | B39: API_PointOfinterests_P2 | C39: P2 | D39: TPI_PointOfIntrestes | E39: QA-1223 | G39: 30m | H39: N | I39: P3 | K39: =HYPERLINK("https://maxxton.atlassian.net/browse/QA-22988","QA-22988") -> QA-22988 | L39: Created on 2025-03-12 for release | M39: 1
A40: =HYPERLINK("https://maxxton.atlassian.net/browse/QA-22963","QA-22963") -> QA-22963 | B40: API_AdminOrganisation_P2 | C40: P2 | D40: TPI_PointOfIntrestes | E40: QA-1223 | G40: 45m | H40: N | I40: P2 | K40: =HYPERLINK("https://maxxton.atlassian.net/browse/QA-22989","QA-22989") -> QA-22989 | L40: Created on 2025-03-12 for release | M40: 1
A41: =HYPERLINK("https://maxxton.atlassian.net/browse/QA-22964","QA-22964") -> QA-22964 | B41: API_DistributionChannel_P2 | C41: P2 | D41: TPI_PointOfIntrestes | E41: QA-1223 | G41: 60m | H41: N | I41: P2 | K41: =HYPERLINK("https://maxxton.atlassian.net/browse/QA-22990","QA-22990") -> QA-22990 | L41: Created on 2025-03-12 for release | M41: 1
A42: =HYPERLINK("https://maxxton.atlassian.net/browse/QA-22970","QA-22970") -> QA-22970 | B42: API_Allotment_P2 | C42: P2 | D42: TPI_PointOfIntrestes | E42: QA-1223 | G42: 60m | H42: N | I42: P2 | K42: =HYPERLINK("https://maxxton.atlassian.net/browse/QA-24103","QA-24103") -> QA-24103 | L42: Created on 2025-05-15 for release 2025_Week_21 | M42: 1
A43: =HYPERLINK("https://maxxton.atlassian.net/browse/QA-22972","QA-22972") -> QA-22972 | B43: API_CashClerance_P2 | C43: P2 | D43: TPI_PointOfIntrestes | E43: QA-1223 | G43: 60m | H43: N | I43: P2 | K43: =HYPERLINK("https://maxxton.atlassian.net/browse/QA-22992","QA-22992") -> QA-22992 | L43: Created on 2025-03-12 for release | M43: 1
A44: =HYPERLINK("https://maxxton.atlassian.net/browse/QA-22973","QA-22973") -> QA-22973 | B44: API_Contracts_P2 | C44: P2 | D44: TPI_PointOfIntrestes | E44: QA-1223 | G44: 60m | H44: N | I44: P2 | K44: =HYPERLINK("https://maxxton.atlassian.net/browse/QA-22993","QA-22993") -> QA-22993 | L44: Created on 2025-03-12 for release | M44: 1
A45: =HYPERLINK("https://maxxton.atlassian.net/browse/QA-22974","QA-22974") -> QA-22974 | B45: API_Facilities,Groups&Icals_P2 | C45: P2 | D45: TPI_PointOfIntrestes | E45: QA-1223 | G45: 60m | H45: N | I45: P2 | K45: =HYPERLINK("https://maxxton.atlassian.net/browse/QA-24104","QA-24104") -> QA-24104 | L45: Created on 2025-05-15 for release 2025_Week_21 | M45: 1
A46: =HYPERLINK("https://maxxton.atlassian.net/browse/QA-22975","QA-22975") -> QA-22975 | B46: API_Ledgers_P2 | C46: P2 | D46: TPI_PointOfIntrestes | E46: QA-1223 | G46: 60m | H46: N | I46: P2 | K46: =HYPERLINK("https://maxxton.atlassian.net/browse/QA-22995","QA-22995") -> QA-22995 | L46: Created on 2025-03-12 for release | M46: 1
A47: =HYPERLINK("https://maxxton.atlassian.net/browse/QA-22976","QA-22976") -> QA-22976 | B47: API_Rentability_P2 | C47: P2 | D47: TPI_PointOfIntrestes | E47: QA-1223 | G47: 60m | H47: N | I47: P2 | K47: =HYPERLINK("https://maxxton.atlassian.net/browse/QA-22996","QA-22996") -> QA-22996 | L47: Created on 2025-03-12 for release | M47: 1
A54: QA-24513 | B54: API_P1_OtherEndpoints | C54: P1 | D54: TPI_SearchAndBook | E54: QA-1223 | F54: Anup Sinha | G54: 1h | H54: N | I54: P1 | J54: Anup Sinha

Sheet Integeration Manager
O1: Components | P1: Epic
F2: Total Test Cases | G2: =countifs(A:A,"<>NEW",A:A,"<>")-1 -> 5 | O2: CMS-Castle BM | P2: QA-1 | Q2: Newyse Regression Test Cases
F3: Schedule? Y | G3: =countif(H:H,"=Y") -> 4 | O3: CMS-Castle MyEnv | P3: QA-24 | Q3: CMS Regression Test Cases
F4: New Test Cases | G4: =COUNTIF(A:A,"=NEW") -> 0 | O4: CMS-Contempo BM | P4: QA-25 | Q4: CMS Live Test Cases
O5: CMS-Contempo MyEnv | P5: QA-26 | Q5: CMS Sanity Test Cases
A6: Key | B6: Summary | C6: Priority | D6: Component | E6: Epic Link | F6: Test Case Assignee | G6: Estimate | H6: Schedule ? | I6: Execution Priority | J6: Execution By | K6: Test Result Ticket | L6: Comments | M6: Original Estimates | N6: Remaining Estimates | O6: CMS-Deepcreek BM | P6: QA-54 | Q6: Newyse Live Test Cases
A7: QA-6230 | B7: RT_ChnlMngr_Reseller_Config | C7: P3 | D7: Connection_Reseller | E7: QA-12945 | F7: Dhiraj Bobade | G7: 4h | H7: Y | I7: P3 | J7: Pragati Mohadure | K7: =HYPERLINK("https://maxxton.atlassian.net/browse/QA-28881","QA-28881") -> QA-28881 | L7: Created on 2026-03-20 for release 2026_Week_13 | M7: 4h | O7: CMS-Deepcreek MyEnv | P7: QA-55 | Q7: Newyse Sanity Test Cases
A8: QA-6231 | B8: RT_ChnlMngr_Reseller_Dashboard | C8: P3 | D8: Connection_Reseller | E8: QA-12945 | F8: Dhiraj Bobade | G8: 5h | H8: Y | I8: P3 | J8: Pragati Mohadure | K8: =HYPERLINK("https://maxxton.atlassian.net/browse/QA-28882","QA-28882") -> QA-28882 | L8: Created on 2026-03-20 for release 2026_Week_13 | M8: 5h | O8: CMS-PerfectExp MyEnv
A9: QA-6232 | B9: RT_ChnlMngr_Supplier_Config | C9: P3 | D9: Connection_Supplier | E9: QA-12945 | F9: Dhiraj Bobade | G9: 5h | H9: Y | I9: P3 | J9: Dhiraj Bobade | K9: =HYPERLINK("https://maxxton.atlassian.net/browse/QA-28883","QA-28883") -> QA-28883 | L9: Created on 2026-03-20 for release 2026_Week_13 | M9: 5h | O9: CMS-Krim BM
A10: QA-6233 | B10: RT_ChnlMngr_Supplier_Dashboard | C10: P3 | D10: Connection_Supplier | E10: QA-12945 | F10: Dhiraj Bobade | G10: 8h | H10: Y | I10: P3 | J10: Dhiraj Bobade | K10: =HYPERLINK("https://maxxton.atlassian.net/browse/QA-28884","QA-28884") -> QA-28884 | L10: Created on 2026-03-20 for release 2026_Week_13 | M10: 8h | O10: MXTS-BackOffice Manager
A11: QA-10453 | B11: RT_ChnlMngr_CMS_Reseller_Flow | C11: P3 | D11: Connection_Reseller | E11: QA-12945 | F11: Pragati Mohadure | H11: N | I11: P3 | J11: Pragati Mohadure | O11: MXTS-Content Manager

Sheet Reservations
Q1: Components | S1: Epic
F2: Total Test Cases | G2: =countifs(A:A,"<>NEW",A:A,"<>")-1 -> 35 | Q2: NM_LandingPage | S2: QA-10184 | T2: Notification Manager Regression Test Cases
F3: Schedule? Y | G3: =countif(H:H,"=Y") -> 34 | Q3: NM_Task
F4: New Test Cases | G4: =COUNTIF(A:A,"=NEW") -> 0 | Q4: NM_Templates
A6: Key | B6: Summary | C6: Priority | D6: Component | E6: Epic Link | F6: Test Case Assignee | G6: Estimate | H6: Schedule ? | I6: Execution Priority | J6: Execution By | K6: Test Result Ticket | L6: Comments | M6: Original Estimates | N6: Manual Estimate Work(this needs to fill in ticket) | O6: WorkDoneBY
A7: QA-7517 | B7: RT-Cash Clearance | C7: P2 | D7: FOM_Cash Clearance | E7: QA-1796 | F7: Shubhangi Dhumal | G7: 45m | H7: Y | I7: P2 | J7: Parag Suryawanshi | K7: =HYPERLINK("https://maxxton.atlassian.net/browse/QA-29060","QA-29060") -> QA-29060 | L7: Created on 2026-04-03 for release 2026_Week_15 | M7: 1h 30m | N7: 1h 30m
A8: QA-7518 | B8: RT_Cash Register Config and Purchase | C8: P2 | D8: FOM_Cash Register | E8: QA-1796 | F8: Parag Suryawanshi | G8: 1h | H8: Y | I8: P2 | J8: Parag Suryawanshi | K8: =HYPERLINK("https://maxxton.atlassian.net/browse/QA-29061","QA-29061") -> QA-29061 | L8: Created on 2026-04-03 for release 2026_Week_15 | M8: 1h 30m | N8: 30m
A9: QA-7519 | B9: RT_Cash Register Report | C9: P2 | D9: FOM_Cash Register | E9: QA-1796 | F9: Parag Suryawanshi | G9: 20m | H9: Y | I9: P2 | J9: Parag Suryawanshi | K9: =HYPERLINK("https://maxxton.atlassian.net/browse/QA-29062","QA-29062") -> QA-29062 | L9: Created on 2026-04-03 for release 2026_Week_15 | M9: 30m | N9: 30m
A10: QA-7520 | B10: RT_CICO UI Tests | C10: P1 | D10: FOM_CICO | E10: QA-1796 | F10: Parag Suryawanshi | G10: 4h | H10: Y | I10: P1 | J10: Parag Suryawanshi | K10: =HYPERLINK("https://maxxton.atlassian.net/browse/QA-29063","QA-29063") -> QA-29063 | L10: Created on 2026-04-03 for release 2026_Week_15 | M10: 4h 30m | N10: 4h 30m
A11: QA-7521 | B11: RT_CICO Update Reservations | C11: P1 | D11: FOM_CICO | E11: QA-1796 | F11: Parag Suryawanshi | G11: 30m | H11: Y | I11: P1 | J11: Parag Suryawanshi | K11: =HYPERLINK("https://maxxton.atlassian.net/browse/QA-29064","QA-29064") -> QA-29064 | L11: Created on 2026-04-03 for release 2026_Week_15 | M11: 30m | N11: 30m | O11: Maxxton-Pooja
A12: QA-7522 | B12: RT_CICO Payment | C12: P1 | D12: FOM_CICO | E12: QA-1796 | F12: Parag Suryawanshi | G12: 1h | H12: Y | I12: P1 | J12: Parag Suryawanshi | K12: =HYPERLINK("https://maxxton.atlassian.net/browse/QA-29065","QA-29065") -> QA-29065 | L12: Created on 2026-04-03 for release 2026_Week_15 | M12: 1h 15m | N12: 1h 15m
A13: QA-7523 | B13: RT_CICO Print | C13: P2 | D13: FOM_CICO | E13: QA-1796 | F13: Parag Suryawanshi | G13: 30m | H13: Y | I13: P2 | J13: Parag Suryawanshi | K13: =HYPERLINK("https://maxxton.atlassian.net/browse/QA-29066","QA-29066") -> QA-29066 | L13: Created on 2026-04-03 for release 2026_Week_15 | M13: 30m | N13: 30m
A14: QA-7524 | B14: RT_FOM Dashboard | C14: P1 | D14: FOM_Dashboard | E14: QA-1796 | F14: Parag Suryawanshi | G14: 2h | H14: Y | I14: P1 | J14: Parag Suryawanshi | K14: =HYPERLINK("https://maxxton.atlassian.net/browse/QA-29067","QA-29067") -> QA-29067 | L14: Created on 2026-04-03 for release 2026_Week_15 | M14: 2h | N14: 2h
A15: QA-7525 | B15: RT_FOM Facilities | C15: P2 | D15: FOM_Facilities | E15: QA-1796 | F15: Parag Suryawanshi | G15: 15m | H15: Y | I15: P2 | J15: Parag Suryawanshi | K15: =HYPERLINK("https://maxxton.atlassian.net/browse/QA-29068","QA-29068") -> QA-29068 | L15: Created on 2026-04-03 for release 2026_Week_15 | M15: 30m | N15: 10m
A16: QA-7526 | B16: RT_FOM Other | C16: P3 | D16: FOM_Other | E16: QA-1796 | F16: Parag Suryawanshi | G16: 10m | H16: Y | I16: P3 | J16: Parag Suryawanshi | K16: =HYPERLINK("https://maxxton.atlassian.net/browse/QA-29069","QA-29069") -> QA-29069 | L16: Created on 2026-04-03 for release 2026_Week_15 | M16: 10m | N16: 10m
A17: QA-7527 | B17: RT_FOM Planning Chart UI and Settings | C17: P1 | D17: FOM_Planning Chart | E17: QA-1796 | F17: Parag Suryawanshi | G17: 3h 30m | H17: Y | I17: P1 | J17: Parag Suryawanshi | K17: =HYPERLINK("https://maxxton.atlassian.net/browse/QA-29070","QA-29070") -> QA-29070 | L17: Created on 2026-04-03 for release 2026_Week_15 | M17: 4h | N17: 4h
A18: QA-7528 | B18: RT_FOM Planning Chart Actions | C18: P2 | D18: FOM_Planning Chart | E18: QA-1796 | F18: Parag Suryawanshi | G18: 30m | H18: Y | I18: P2 | J18: Parag Suryawanshi | K18: =HYPERLINK("https://maxxton.atlassian.net/browse/QA-29071","QA-29071") -> QA-29071 | L18: Created on 2026-04-03 for release 2026_Week_15 | M18: 30m | N18: 30m
A19: QA-7529 | B19: RT_FOM WorkOrders | C19: P2 | D19: FOM_WorkOrders | E19: QA-1796 | F19: Parag Suryawanshi | G19: 30m | H19: Y | I19: P2 | J19: Parag Suryawanshi | K19: =HYPERLINK("https://maxxton.atlassian.net/browse/QA-29072","QA-29072") -> QA-29072 | L19: Created on 2026-04-03 for release 2026_Week_15 | M19: 45m | N19: 10m
A20: QA-9214 | B20: RT_FOM Barrier Dashboard | C20: P1 | D20: FOM_Barrier Dashboard | E20: QA-1796 | F20: Parag Suryawanshi | G20: 45m | H20: Y | I20: P1 | J20: Parag Suryawanshi | K20: =HYPERLINK("https://maxxton.atlassian.net/browse/QA-29073","QA-29073") -> QA-29073 | L20: Created on 2026-04-03 for release 2026_Week_15 | M20: 1h | N20: 1h
A21: QA-9215 | B21: RT_FOM Activity Planner | C21: P1 | D21: FOM_Activity Planner | E21: QA-1796 | F21: Parag Suryawanshi | G21: 2h | H21: Y | I21: P1 | J21: Parag Suryawanshi | K21: =HYPERLINK("https://maxxton.atlassian.net/browse/QA-29074","QA-29074") -> QA-29074 | L21: Created on 2026-04-03 for release 2026_Week_15 | M21: 4h | N21: 1h | O21: Maxxton-Parag
A22: QA-207 | B22: RT_Reservation Manager | C22: P1 | D22: MXTS-Reservation Manager | E22: QA-1797 | F22: Pooja Tudha | G22: 4h | H22: Y | I22: P1 | J22: Pooja Tudha | K22: =HYPERLINK("https://maxxton.atlassian.net/browse/QA-29075","QA-29075") -> QA-29075 | L22: Created on 2026-04-03 for release 2026_Week_15 | M22: 8h | N22: 8h | O22: Manual Effort
A23: =HYPERLINK("https://maxxton.atlassian.net/browse/QA-10185","QA-10185") -> QA-10185 | B23: RT_ Linear Reservation | C23: P1 | D23: MXTS-Reservation Manager | E23: QA-1797 | F23: Tuhina Gupta | G23: 3h | H23: Y | I23: P3 | J23: Tuhina Gupta | K23: =HYPERLINK("https://maxxton.atlassian.net/browse/QA-29076","QA-29076") -> QA-29076 | L23: Created on 2026-04-03 for release 2026_Week_15
A24: =HYPERLINK("https://maxxton.atlassian.net/browse/QA-12630","QA-12630") -> QA-12630 | B24: RT_Room Planner | C24: P3 | D24: MXTS-Reservation Manager | E24: QA-1797 | F24: Tuhina Gupta | G24: 45m | H24: Y | I24: P3 | J24: Tuhina Gupta | K24: =HYPERLINK("https://maxxton.atlassian.net/browse/QA-29077","QA-29077") -> QA-29077 | L24: Created on 2026-04-03 for release 2026_Week_15 | M24: 1h | N24: 45m | O24: Frugal-Done | Q24: Started monitoring automation test cases
A25: =HYPERLINK("https://maxxton.atlassian.net/browse/QA-12631","QA-12631") -> QA-12631 | B25: RT_Infotext | C25: P3 | D25: MXTS-Reservation Manager | E25: QA-1797 | F25: Tuhina Gupta | G25: 3h | H25: Y | I25: P3 | J25: Tuhina Gupta | K25: =HYPERLINK("https://maxxton.atlassian.net/browse/QA-29078","QA-29078") -> QA-29078 | L25: Created on 2026-04-03 for release 2026_Week_15 | M25: 4h | N25: 4h | O25: Maxxton-Tuhina | Q25: Automation test cases needs refactoring
A26: =HYPERLINK("https://maxxton.atlassian.net/browse/QA-12632","QA-12632") -> QA-12632 | B26: RT_Customer | C26: P3 | D26: MXTS-Reservation Manager | E26: QA-1797 | F26: Chetan Harkut | G26: 1h | H26: Y | I26: P3 | J26: Chetan Harkut | K26: =HYPERLINK("https://maxxton.atlassian.net/browse/QA-29079","QA-29079") -> QA-29079 | L26: Created on 2026-04-03 for release 2026_Week_15 | M26: 1h | N26: 1h | O26: Maxxton-Vicky | Q26: Started monitoring automation test cases
A27: =HYPERLINK("https://maxxton.atlassian.net/browse/QA-12633","QA-12633") -> QA-12633 | B27: RT_Reallocation | C27: P3 | D27: MXTS-Resrvation manager | E27: QA-1797 | F27: Parag Suryawanshi | G27: 2h | H27: Y | I27: P1 | J27: Parag Suryawanshi | K27: =HYPERLINK("https://maxxton.atlassian.net/browse/QA-29080","QA-29080") -> QA-29080 | L27: Created on 2026-04-03 for release 2026_Week_15 | M27: 2h | N27: 2h | O27: Frugal-Done
A28: =HYPERLINK("https://maxxton.atlassian.net/browse/QA-12943","QA-12943") -> QA-12943 | B28: RT_Cancellations | C28: P3 | D28: MXTS-Resrvation manager | E28: QA-1797 | F28: Chetan Harkut | G28: 3h | H28: Y | I28: P3 | J28: Chetan Harkut | K28: =HYPERLINK("https://maxxton.atlassian.net/browse/QA-29081","QA-29081") -> QA-29081 | L28: Created on 2026-04-03 for release 2026_Week_15 | M28: 4h | N28: 4h | O28: After Refactoring automation will start
A29: =HYPERLINK("https://maxxton.atlassian.net/browse/QA-13357","QA-13357") -> QA-13357 | B29: RT_Search reservation | C29: P3 | D29: MXTS-Resrvation manager | E29: QA-1797 | F29: Pooja Tudha | G29: 5h | H29: Y | I29: P3 | J29: Pooja Tudha | K29: =HYPERLINK("https://maxxton.atlassian.net/browse/QA-29082","QA-29082") -> QA-29082 | L29: Created on 2026-04-03 for release 2026_Week_15 | M29: 5h 30m | N29: 5h 30m | O29: Frugal-InProgress,will move in next Sprint
A30: =HYPERLINK("https://maxxton.atlassian.net/browse/QA-13906","QA-13906") -> QA-13906 | B30: RT_More Options | C30: P3 | D30: MXTS-Resrvation manager | E30: QA-1797 | F30: Tuhina Gupta | G30: 4h 20m | H30: Y | I30: P3 | J30: Tuhina Gupta | K30: =HYPERLINK("https://maxxton.atlassian.net/browse/QA-29083","QA-29083") -> QA-29083 | L30: Created on 2026-04-03 for release 2026_Week_15 | M30: 4h 20m | N30: 4h 20m | O30: Maxxton-Vicky40%
A31: =HYPERLINK("https://maxxton.atlassian.net/browse/QA-16435","QA-16435") -> QA-16435 | B31: RT_Reservation Manager- 2 | C31: P3 | D31: MXTS-Resrvation manager | E31: QA-1797 | F31: Parag Suryawanshi | G31: 3h | H31: Y | I31: P3 | J31: Parag Suryawanshi | K31: =HYPERLINK("https://maxxton.atlassian.net/browse/QA-29084","QA-29084") -> QA-29084 | L31: Created on 2026-04-03 for release 2026_Week_15 | M31: 3h | N31: 3h | O31: Sprint-6
A32: =HYPERLINK("https://maxxton.atlassian.net/browse/QA-18194","QA-18194") -> QA-18194 | B32: RT_Reservation Manager- Accommodation type | C32: P3 | D32: MXTS-Resrvation manager | E32: QA-1797 | F32: Chetan Harkut | G32: 1h | H32: Y | I32: P3 | J32: Chetan Harkut | K32: =HYPERLINK("https://maxxton.atlassian.net/browse/QA-29085","QA-29085") -> QA-29085 | L32: Created on 2026-04-03 for release 2026_Week_15 | M32: 2h | N32: 2h | O32: Sprint-6
A33: =HYPERLINK("https://maxxton.atlassian.net/browse/QA-18195","QA-18195") -> QA-18195 | B33: RT_Reservation Manager- Dashboard | C33: P3 | D33: MXTS-Resrvation manager | E33: QA-1797 | F33: Pooja Tudha | G33: 30m | H33: Y | I33: P3 | J33: Pooja Tudha | K33: =HYPERLINK("https://maxxton.atlassian.net/browse/QA-29086","QA-29086") -> QA-29086 | L33: Created on 2026-04-03 for release 2026_Week_15 | M33: 45m | N33: 30m | O33: Maxxton - Pooja
A34: =HYPERLINK("https://maxxton.atlassian.net/browse/QA-18196","QA-18196") -> QA-18196 | B34: RT_Reservation Manager- Overview | C34: P3 | D34: MXTS-Resrvation manager | E34: QA-1797 | F34: Pooja Tudha | G34: 3h | H34: Y | I34: P3 | J34: Pooja Tudha | K34: =HYPERLINK("https://maxxton.atlassian.net/browse/QA-29087","QA-29087") -> QA-29087 | L34: Created on 2026-04-03 for release 2026_Week_15 | M34: 3h | N34: 3h | O34: Maxxton - Pooja 60%
A35: =HYPERLINK("https://maxxton.atlassian.net/browse/QA-18197","QA-18197") -> QA-18197 | B35: RT_Reservation Manager- Finance | C35: P3 | D35: MXTS-Resrvation manager | E35: QA-1797 | F35: Pooja Tudha | G35: 5h | H35: Y | I35: P3 | J35: Pooja Tudha | K35: =HYPERLINK("https://maxxton.atlassian.net/browse/QA-29088","QA-29088") -> QA-29088 | L35: Created on 2026-04-03 for release 2026_Week_15 | M35: 5h | N35: 5h | O35: Frugal - 60% Complete
A36: =HYPERLINK("https://maxxton.atlassian.net/browse/QA-18198","QA-18198") -> QA-18198 | B36: RT_Reservation Manager- Customer Details | C36: P3 | D36: MXTS-Resrvation manager | E36: QA-1797 | F36: Pooja Tudha | G36: 1h 30m | H36: Y | I36: P3 | J36: Pooja Tudha | K36: =HYPERLINK("https://maxxton.atlassian.net/browse/QA-29089","QA-29089") -> QA-29089 | L36: Created on 2026-04-03 for release 2026_Week_15 | M36: 1h | N36: 1h | O36: After Refactoring automation will start
A37: =HYPERLINK("https://maxxton.atlassian.net/browse/QA-19223","QA-19223") -> QA-19223 | B37: RT_Reservation Manager- Loyalty | C37: P3 | D37: MXTS-Resrvation manager | E37: QA-1797 | F37: Chetan Harkut | G37: 4h 30m | H37: Y | I37: P3 | J37: Chetan Harkut | K37: =HYPERLINK("https://maxxton.atlassian.net/browse/QA-29090","QA-29090") -> QA-29090 | L37: Created on 2026-04-03 for release 2026_Week_15 | M37: 5h | N37: 5h | O37: Frugal- Done
A38: =HYPERLINK("https://maxxton.atlassian.net/browse/QA-21276","QA-21276") -> QA-21276 | B38: RT_FOM- Planning Chart- Move reservation to any unit. | C38: P3 | D38: FOM_Planning Chart | E38: QA-1796 | F38: Parag Suryawanshi | G38: 1h 30m | H38: Y | I38: P3 | J38: Parag Suryawanshi | K38: =HYPERLINK("https://maxxton.atlassian.net/browse/QA-29091","QA-29091") -> QA-29091 | L38: Created on 2026-04-03 for release 2026_Week_15 | M38: 2h 30m | N38: 2h 30m | O38: After Refactoring automation will start
A39: =HYPERLINK("https://maxxton.atlassian.net/browse/QA-21276","QA-22095") -> QA-22095 | B39: RT_Reservation Manager- CE-Portal | C39: P3 | D39: MXTS-Resrvation manager | E39: QA-1797 | F39: Chetan Harkut | G39: 3h | H39: Y | I39: P3 | J39: Chetan Harkut | K39: =HYPERLINK("https://maxxton.atlassian.net/browse/QA-29092","QA-29092") -> QA-29092 | L39: Created on 2026-04-03 for release 2026_Week_15 | M39: 4h | N39: 4h | O39: Sprint-6
A40: =HYPERLINK("https://maxxton.atlassian.net/browse/QA-12940","QA-12940") -> QA-12940 | B40: RT_Reservation Manager- Price Engine | C40: P3 | D40: MXTS-Resrvation manager | E40: QA-1797 | F40: Tuhina Gupta | G40: 9h | H40: Y | I40: P3 | J40: Tuhina Gupta | K40: =HYPERLINK("https://maxxton.atlassian.net/browse/QA-29093","QA-29093") -> QA-29093 | L40: Created on 2026-04-03 for release 2026_Week_15 | O40: Frugal-Done
B41: gap functionality | O41: Frugal - Done

Sheet Channel
O1: Components | P1: Epic
F2: Total Test Cases | G2: =countifs(A:A,"<>NEW",A:A,"<>")-1 -> 17 | O2: CMS-Castle BM | P2: QA-1 | Q2: Newyse Regression Test Cases
F3: Schedule? Y | G3: =countif(H:H,"=Y") -> 17 | O3: CMS-Castle MyEnv | P3: QA-24 | Q3: CMS Regression Test Cases
F4: New Test Cases | G4: =COUNTIF(A:A,"=NEW") -> 0 | O4: CMS-Contempo BM | P4: QA-25 | Q4: CMS Live Test Cases
E5: Token | F5: ATATT3xFfGF0N5MSvFDqXqFVMh2Uu502jAH5WMhV_ejuLvF | G5: 2026_Week_13 | O5: CMS-Contempo MyEnv | P5: QA-26 | Q5: CMS Sanity Test Cases
A6: Key | B6: Summary | C6: Priority | D6: Component | E6: Epic Link | F6: Test Case Assignee | G6: Estimate | H6: Schedule ? | I6: Execution Priority | J6: Execution By | K6: Test Result Ticket | L6: Comments | M6: Original Estimates | N6: Remaining Estimates | O6: CMS-Deepcreek BM | P6: QA-54 | Q6: Newyse Live Test Cases
A7: QA-6224 | B7: RT_ChnlMngr_Cancellation_General | C7: P3 | D7: ChnlMngr_Cancellation | E7: QA-6223 | F7: Kumar Saurabh | H7: Y | I7: P3 | J7: Chetan Gujar | K7: =HYPERLINK("https://maxxton.atlassian.net/browse/QA-28984","QA-28984") -> QA-28984 | L7: Created on 2026-03-23 for release 2026_Week_13 | M7: 100m | N7: 30m | O7: CMS-Deepcreek MyEnv | P7: QA-55 | Q7: Newyse Sanity Test Cases
A8: QA-6225 | B8: RT_ChnlMngr_Cancellation_Rates | C8: P3 | D8: ChnlMngr_Cancellation | E8: QA-6223 | F8: Chetan Gujar | H8: Y | I8: P3 | J8: Chetan Gujar | K8: =HYPERLINK("https://maxxton.atlassian.net/browse/QA-28985","QA-28985") -> QA-28985 | L8: Created on 2026-03-23 for release 2026_Week_13 | M8: 60m | N8: 15m | O8: CMS-Hogenboom BM | P8: QA-71 | Q8: MXTS Sanity Test Cases
A9: QA-6226 | B9: RT_ChnlMngr_Commission_General | C9: P3 | D9: ChnlMngr_Commission | E9: QA-6223 | F9: Chetan Gujar | H9: Y | I9: P3 | J9: Chetan Gujar | K9: =HYPERLINK("https://maxxton.atlassian.net/browse/QA-28986","QA-28986") -> QA-28986 | L9: Created on 2026-03-23 for release 2026_Week_13 | M9: 100m | N9: 30m | O9: CMS-Hogenboom MyEnv | P9: QA-72 | Q9: MXTS Regression Test Cases
A10: QA-6227 | B10: RT_ChnlMngr_Commission_Rates | C10: P3 | D10: ChnlMngr_Commission | E10: QA-6223 | F10: Chetan Gujar | H10: Y | I10: P3 | J10: Chetan Gujar | K10: =HYPERLINK("https://maxxton.atlassian.net/browse/QA-28987","QA-28987") -> QA-28987 | L10: Created on 2026-03-23 for release 2026_Week_13 | M10: 80m | N10: 30m | O10: CMS-Krim BM
A11: QA-6228 | B11: RT_ChnlMngr_DC | C11: P3 | D11: ChnlMngr_DC | E11: QA-6223 | F11: Kumar Saurabh | H11: Y | I11: P3 | J11: Chetan Gujar | K11: =HYPERLINK("https://maxxton.atlassian.net/browse/QA-28988","QA-28988") -> QA-28988 | L11: Created on 2026-03-23 for release 2026_Week_13 | M11: 100m | N11: 30m | O11: CMS-Krim MyEnv
A12: QA-6229 | B12: RT_ChnlMngr_RC | C12: P3 | D12: ChnlMngr_RC | E12: QA-6223 | F12: Kumar Saurabh | H12: Y | I12: P3 | J12: Chetan Gujar | K12: =HYPERLINK("https://maxxton.atlassian.net/browse/QA-28989","QA-28989") -> QA-28989 | L12: Created on 2026-03-23 for release 2026_Week_13 | M12: 150m | N12: 30m | O12: CMS-PerfectExp BM
A13: =HYPERLINK("https://maxxton.atlassian.net/browse/QA-15666","QA-15666") -> QA-15666 | B13: RT_ChnlMngr_Required_Field_Sets | C13: P3 | D13: ChnlMngr_Required_Field_Sets | E13: QA-6223 | F13: Chetan Gujar | H13: Y | I13: P3 | J13: Chetan Gujar | K13: =HYPERLINK("https://maxxton.atlassian.net/browse/QA-28990","QA-28990") -> QA-28990 | L13: Created on 2026-03-23 for release 2026_Week_13 | M13: 60m | N13: 15m | O13: MXTS-Implementation Manager
A14: QA-19285 | B14: RT_ChnlMngr_DC Allotment | C14: P3 | D14: ChnlMngr_DC | E14: QA-6223 | F14: Kumar Saurabh | H14: Y | I14: P3 | J14: Chetan Gujar | K14: =HYPERLINK("https://maxxton.atlassian.net/browse/QA-28991","QA-28991") -> QA-28991 | L14: Created on 2026-03-23 for release 2026_Week_13 | M14: 60m | N14: 15m | O14: MXTS-PaymentService
A15: QA-20397 | B15: RT_ChnlMngr_Linear_Type_Allotment | C15: P3 | D15: ChnlMngr_Linear | E15: QA-6223 | F15: Kumar Saurabh | H15: Y | I15: P3 | J15: Chetan Gujar | K15: =HYPERLINK("https://maxxton.atlassian.net/browse/QA-28992","QA-28992") -> QA-28992 | L15: Created on 2026-03-23 for release 2026_Week_13 | M15: 60m | N15: 15m | O15: CMS-RCN MyEnv
A16: QA-20397 | B16: RT_ChnlMngr_Linear_Unit_Allotment | C16: P3 | D16: ChnlMngr_Linear | E16: QA-6223 | F16: Kumar Saurabh | H16: Y | I16: P3 | J16: Chetan Gujar | K16: =HYPERLINK("https://maxxton.atlassian.net/browse/QA-28993","QA-28993") -> QA-28993 | L16: Created on 2026-03-23 for release 2026_Week_13 | M16: 60m | N16: 15m | O16: CMS-EuroparcsNL MyEnv
A17: QA-21823 | B17: RT_ChnlMngr_Create DC | C17: P3 | D17: ChnlMngr_DC | E17: QA-6223 | F17: Kumar Saurabh | H17: Y | I17: P3 | J17: Chetan Gujar | K17: =HYPERLINK("https://maxxton.atlassian.net/browse/QA-28994","QA-28994") -> QA-28994 | L17: Created on 2026-03-23 for release 2026_Week_13 | M17: 60m | N17: 15m
A18: QA-23401 | B18: Create Billing Rule For Payer type Agent | C18: P3 | D18: ChnlMngr_DC | E18: QA-6223 | F18: Chetan Gujar | H18: Y | I18: P3 | J18: Chetan Gujar | K18: =HYPERLINK("https://maxxton.atlassian.net/browse/QA-28995","QA-28995") -> QA-28995 | L18: Created on 2026-03-23 for release 2026_Week_13 | M18: 30m
A19: QA-23402 | B19: Create Billing Rule For Payer type Paying Customer | C19: P3 | D19: ChnlMngr_DC | E19: QA-6223 | F19: Chetan Gujar | H19: Y | I19: P3 | J19: Chetan Gujar | K19: =HYPERLINK("https://maxxton.atlassian.net/browse/QA-28996","QA-28996") -> QA-28996 | L19: Created on 2026-03-23 for release 2026_Week_13 | M19: 30m
A20: QA-23403 | B20: Create Billing Rule For Payer type Customer | C20: P3 | D20: ChnlMngr_DC | E20: QA-6223 | F20: Chetan Gujar | H20: Y | I20: P3 | J20: Chetan Gujar | K20: =HYPERLINK("https://maxxton.atlassian.net/browse/QA-28997","QA-28997") -> QA-28997 | L20: Created on 2026-03-23 for release 2026_Week_13 | M20: 30m
A21: QA-25195 | B21: RC- Free Resources | C21: P3 | D21: ChnlMngr_RC | E21: QA-6224 | F21: Kumar Saurabh | H21: Y | I21: P3 | J21: Kumar Saurabh | K21: =HYPERLINK("https://maxxton.atlassian.net/browse/QA-28998","QA-28998") -> QA-28998 | L21: Created on 2026-03-23 for release 2026_Week_13 | M21: 980m | N21: 240m
A22: QA-26180 | B22: Export :Cancellation and Commission | C22: P3 | D22: ChnlMngr_Cancellation | E22: QA-6223 | F22: Chetan Gujar | H22: Y | I22: P3 | J22: Kumar Saurabh | K22: =HYPERLINK("https://maxxton.atlassian.net/browse/QA-28999","QA-28999") -> QA-28999 | L22: Created on 2026-03-23 for release 2026_Week_13
A23: QA-28529 | B23: RT_ChnlMngr_DC Payment Term Sets | C23: P3 | D23: RT_ChnlMngr_DC Payment Term Sets | E23: QA-6223 | F23: Kumar Saurabh | H23: Y | I23: P3 | J23: Kumar Saurabh

Sheet BaseData
A1: Name | B1: ID
A2: Amruta Jadhav | B2: 625a78d65d1e700069b05360
A3: Anavika Mandhare | B3: 63fde7e515d668edd8ed36f8
A4: Anjali Bidkar | B4: 625a799f3bf0f0007018a261
A5: Ankit Vyawahare | B5: 615ff019048360006a721dd8
A6: Anup Sinha | B6: 712020:2a1fc492-5f7e-4ba4-9562-ff8f4baf1637
A7: Aparna Shinde | B7: 625a7a9213c2c8006a37f313
A8: Ashwini Kedare | B8: 712020:0cf88886-8385-45bb-b53b-ef36df94cc63
A9: Chandra Mohanty | B9: 625a7991ed2b3e0074fe9df3
A10: Chetan Gujar | B10: 625a7b26a87271006922df8a
A11: Dhiraj Bobade | B11: 625a79b0ed2b3e0074fe9e07
A12: Ekata Chavan | B12: 625a7c730630bd007077cc50
... A42: Kumar Saurabh | B42: 625a7c0413c2c8006a37f39c

Sheet Template
F2: Total Test Cases | G2: =countifs(A:A,"<>NEW",A:A,"<>")-1 -> 26
F3: Schedule? Y | G3: =countif(H:H,"=Y") -> 21
F4: New Test Cases | G4: =COUNTIF(A:A,"=NEW") -> 1
A6: Key | B6: Summary | C6: Priority | D6: Component | E6: Epic Link | F6: Test Case Assignee | G6: Estimate | H6: Schedule ? | I6: Execution Priority | J6: Execution By | K6: Test Result Ticket | L6: Comments | M6: Original Estimates | N6: Remaining Estimates
A7: =HYPERLINK("https://maxxton.atlassian.net/browse/QA-20678","QA-20678") -> QA-20678 | B7: RT_Legacy Template Functionalities | C7: P3 | D7: TempMngr_Templates | E7: QA-16540 | F7: Jyoti Koli | G7: 2h | H7: Y | I7: P3 | J7: Jyoti Koli | K7: =HYPERLINK("https://maxxton.atlassian.net/browse/QA-28885","QA-28885") -> QA-28885 | L7: Created on 2026-03-20 for release 2026_Week_13 | M7: 2h | N7: 2h
A8: =HYPERLINK("https://maxxton.atlassian.net/browse/QA-16542","QA-16542") -> QA-16542 | B8: RT_Templates_Template Overview | C8: P3 | D8: TempMngr_Templates | E8: QA-16540 | F8: Jyoti Koli | G8: 2h | H8: Y | I8: P3 | J8: Jyoti Koli | K8: =HYPERLINK("https://maxxton.atlassian.net/browse/QA-28886","QA-28886") -> QA-28886 | L8: Created on 2026-03-20 for release 2026_Week_13 | M8: 2h | N8: 1h
A9: =HYPERLINK("https://maxxton.atlassian.net/browse/QA-16543","QA-16543") -> QA-16543 | B9: RT_Context of Reservation template | C9: P3 | D9: TempMngr_Templates | E9: QA-16540 | F9: Jyoti Koli | G9: 3h | H9: Y | I9: P3 | J9: Swapnali Swami | K9: =HYPERLINK("https://maxxton.atlassian.net/browse/QA-28887","QA-28887") -> QA-28887 | L9: Created on 2026-03-20 for release 2026_Week_13 | M9: 3h | N9: 3h
A10: =HYPERLINK("https://maxxton.atlassian.net/browse/QA-16547","QA-16547") -> QA-16547 | B10: RT_Reservation Bill and Installments component | C10: P3 | D10: TempMngr_Layouts and Attributes | E10: QA-16540 | F10: Jyoti Koli | G10: 2h | H10: Y | I10: P3 | J10: Jyoti Koli | K10: =HYPERLINK("https://maxxton.atlassian.net/browse/QA-28888","QA-28888") -> QA-28888 | L10: Created on 2026-03-20 for release 2026_Week_13 | M10: 2h | N10: 2h
A11: =HYPERLINK("https://maxxton.atlassian.net/browse/QA-16550","QA-16550") -> QA-16550 | B11: RT_Reservation_Payment and Payment reminders | C11: P3 | D11: TempMngr_Layouts and Attributes | E11: QA-16540 | F11: Jyoti Koli | G11: 1h 30m | H11: Y | I11: P3 | J11: Swapnali Swami | K11: =HYPERLINK("https://maxxton.atlassian.net/browse/QA-28889","QA-28889") -> QA-28889 | L11: Created on 2026-03-20 for release 2026_Week_13 | M11: 1h 30m | N11: 1h 30m
A12: =HYPERLINK("https://maxxton.atlassian.net/browse/QA-16548","QA-16548") -> QA-16548 | B12: RT_Reservation_Accommodation type, add-ons and Recommended add-ons component | C12: P3 | D12: TempMngr_Layouts and Attributes | E12: QA-16540 | F12: Jyoti Koli | G12: 2h | H12: Y | I12: P3 | J12: Swapnali Swami | K12: =HYPERLINK("https://maxxton.atlassian.net/browse/QA-28890","QA-28890") -> QA-28890 | L12: Created on 2026-03-20 for release 2026_Week_13 | M12: 2h | N12: 2h
A13: =HYPERLINK("https://maxxton.atlassian.net/browse/QA-16551","QA-16551") -> QA-16551 | B13: RT_Reservation_Point of interest and Loyalty transactions | C13: P3 | D13: TempMngr_Layouts and Attributes | E13: QA-16540 | F13: Jyoti Koli | G13: 2h | H13: Y | I13: P3 | J13: Swapnali Swami | K13: =HYPERLINK("https://maxxton.atlassian.net/browse/QA-28891","QA-28891") -> QA-28891 | L13: Created on 2026-03-20 for release 2026_Week_13 | M13: 2h | N13: 2h
A14: =HYPERLINK("https://maxxton.atlassian.net/browse/QA-16544","QA-16544") -> QA-16544 | B14: RT_Context of Customer template | C14: P3 | D14: TempMngr_Templates | E14: QA-16540 | F14: Jyoti Koli | G14: 2h | H14: Y | I14: P3 | J14: Jyoti Koli | K14: =HYPERLINK("https://maxxton.atlassian.net/browse/QA-28892","QA-28892") -> QA-28892 | L14: Created on 2026-03-20 for release 2026_Week_13 | M14: 2h | N14: 2h
A15: =HYPERLINK("https://maxxton.atlassian.net/browse/QA-16545","QA-16545") -> QA-16545 | B15: RT_Context of Tax Invoice template | C15: P3 | D15: TempMngr_Templates | E15: QA-16540 | F15: Jyoti Koli | G15: 2h 30m | H15: Y | I15: P3 | J15: Swapnali Swami | K15: =HYPERLINK("https://maxxton.atlassian.net/browse/QA-28893","QA-28893") -> QA-28893 | L15: Created on 2026-03-20 for release 2026_Week_13 | M15: 2h 30m | N15: 2h 30m
A16: =HYPERLINK("https://maxxton.atlassian.net/browse/QA-19114","QA-19114") -> QA-19114 | B16: RT_Context of Payment template | C16: P3 | D16: TempMngr_Templates | E16: QA-16540 | F16: Jyoti Koli | G16: 2h | H16: Y | I16: P3 | J16: Jyoti Koli | K16: =HYPERLINK("https://maxxton.atlassian.net/browse/QA-28894","QA-28894") -> QA-28894 | L16: Created on 2026-03-20 for release 2026_Week_13 | M16: 2h | N16: 2h
A17: =HYPERLINK("https://maxxton.atlassian.net/browse/QA-19115","QA-19115") -> QA-19115 | B17: RT_Context of No dynamic data template | C17: P3 | D17: TempMngr_Templates | E17: QA-16540 | F17: Jyoti Koli | G17: 1h | H17: Y | I17: P3 | J17: Jyoti Koli | K17: =HYPERLINK("https://maxxton.atlassian.net/browse/QA-28895","QA-28895") -> QA-28895 | L17: Created on 2026-03-20 for release 2026_Week_13 | M17: 1h | N17: 1h
A18: =HYPERLINK("https://maxxton.atlassian.net/browse/QA-19116","QA-19116") -> QA-19116 | B18: RT_Context of Loyalty transaction template | C18: P3 | D18: TempMngr_Templates | E18: QA-16540 | F18: Jyoti Koli | G18: 1h 30m | H18: Y | I18: P3 | J18: Swapnali Swami | K18: =HYPERLINK("https://maxxton.atlassian.net/browse/QA-28896","QA-28896") -> QA-28896 | L18: Created on 2026-03-20 for release 2026_Week_13 | M18: 1h 30m | N18: 1h 30m
A19: =HYPERLINK("https://maxxton.atlassian.net/browse/QA-22641","QA-22641") -> QA-22641 | B19: RT_Attachment or Mail Template | C19: P3 | D19: TempMngr_Templates | E19: QA-16540 | F19: Jyoti Koli | G19: 1h | H19: Y | I19: P3 | J19: Swapnali Swami | K19: =HYPERLINK("https://maxxton.atlassian.net/browse/QA-28897","QA-28897") -> QA-28897 | L19: Created on 2026-03-20 for release 2026_Week_13 | M19: 1h | N19: 1h
A20: =HYPERLINK("https://maxxton.atlassian.net/browse/QA-16549","QA-16549") -> QA-16549 | B20: RT_Reservation_Activities and Activity e-ticket | C20: P3 | D20: TempMngr_Layouts and Attributes | E20: QA-16540 | F20: Jyoti Koli | G20: 2h 30m | H20: Y | I20: P3 | J20: Swapnali Swami | K20: =HYPERLINK("https://maxxton.atlassian.net/browse/QA-28898","QA-28898") -> QA-28898 | L20: Created on 2026-03-20 for release 2026_Week_13 | M20: 2h 30m | N20: 2h 30m
A21: =HYPERLINK("https://maxxton.atlassian.net/browse/QA-16546","QA-16546") -> QA-16546 | B21: RT_About and Build Mode | C21: P3 | D21: TempMngr_Templates | E21: QA-16540 | F21: Jyoti Koli | G21: 4h | H21: Y | I21: P3 | J21: Jyoti Koli | K21: =HYPERLINK("https://maxxton.atlassian.net/browse/QA-28899","QA-28899") -> QA-28899 | L21: Created on 2026-03-20 for release 2026_Week_13 | M21: 4h | N21: 4h
A22: =HYPERLINK("https://maxxton.atlassian.net/browse/QA-20872","QA-20872") -> QA-20872 | B22: RT_BuildMode_RowColumnConfiguration | C22: P3 | D22: TempMngr_Layouts and Attributes | E22: QA-16540 | F22: Jyoti Koli | G22: 3h | H22: Y | I22: P3 | J22: Swapnali Swami | K22: =HYPERLINK("https://maxxton.atlassian.net/browse/QA-28900","QA-28900") -> QA-28900 | L22: Created on 2026-03-20 for release 2026_Week_13 | M22: 3h | N22: 3h
A23: =HYPERLINK("https://maxxton.atlassian.net/browse/QA-16553","QA-16553") -> QA-16553 | B23: RT_Template_More options (Three dots) | C23: P3 | D23: TempMngr_Templates | E23: QA-16540 | F23: Jyoti Koli | G23: 1h | H23: Y | I23: P3 | J23: Jyoti Koli | K23: =HYPERLINK("https://maxxton.atlassian.net/browse/QA-28901","QA-28901") -> QA-28901 | L23: Created on 2026-03-20 for release 2026_Week_13 | M23: 1h | N23: 1h
A24: =HYPERLINK("https://maxxton.atlassian.net/browse/QA-16541","QA-16541") -> QA-16541 | B24: RT_Template Themes | C24: P3 | D24: TempMngr_Themes | E24: QA-16540 | F24: Jyoti Koli | G24: 2h | H24: Y | I24: P3 | J24: Jyoti Koli | K24: =HYPERLINK("https://maxxton.atlassian.net/browse/QA-28902","QA-28902") -> QA-28902 | L24: Created on 2026-03-20 for release 2026_Week_13 | M24: 2h | N24: 30m
A25: =HYPERLINK("https://maxxton.atlassian.net/browse/QA-17840","QA-17840") -> QA-17840 | B25: RT_Template blocks | C25: P3 | D25: TempMngr_Templates | E25: QA-16540 | F25: Jyoti Koli | G25: 2h | H25: Y | I25: P3 | J25: Swapnali Swami | K25: =HYPERLINK("https://maxxton.atlassian.net/browse/QA-28903","QA-28903") -> QA-28903 | L25: Created on 2026-03-20 for release 2026_Week_13 | M25: 2h | N25: 2h
A26: =HYPERLINK("https://maxxton.atlassian.net/browse/QA-22321","QA-22321") -> QA-22321 | B26: RT_Report Configuration | C26: P3 | D26: TempMngr_Templates | E26: QA-16540 | F26: Jyoti Koli | G26: 4h | H26: Y | I26: P3 | J26: Jyoti Koli | K26: =HYPERLINK("https://maxxton.atlassian.net/browse/QA-28904","QA-28904") -> QA-28904 | L26: Created on 2026-03-20 for release 2026_Week_13 | M26: 4h | N26: 4h
A27: =HYPERLINK("https://maxxton.atlassian.net/browse/QA-10187","QA-10187") -> QA-10187 | B27: RT_Notifications_Manager_ E2E | C27: P3 | D27: NM_Task | E27: QA-10184 | F27: Jyoti Koli | G27: 5h | H27: Y | I27: P3 | J27: Jyoti Koli | K27: =HYPERLINK("https://maxxton.atlassian.net/browse/QA-28905","QA-28905") -> QA-28905 | L27: Created on 2026-03-20 for release 2026_Week_13 | M27: 5h | N27: 5h | O27: Frugal-InProgress,will move in next Sprint
A28: NEW | B28: RT_Template Blocks_Visibility Settings | C28: P3 | D28: TempMngr_Templates | E28: QA-16540 | F28: Swapnali Swami | G28: 5h | H28: N | I28: P3 | J28: Swapnali Swami
A30: =HYPERLINK("https://maxxton.atlassian.net/browse/QA-16552","QA-16552") -> QA-16552 | B30: RT_Reservation_Loyalty Transactions | C30: P3 | D30: TempMngr_Layouts and Attributes | E30: QA-16540 | F30: Ashwini Kedare | G30: 30m | H30: N | I30: P3 | J30: Swapnali Swami | K30: =HYPERLINK("https://maxxton.atlassian.net/browse/QA-24024","QA-24024") -> QA-24024 | L30: Created on 2025-05-15 for release 2025_Week_21 | M30: 30m | N30: 30m
A32: =HYPERLINK("https://maxxton.atlassian.net/browse/QA-10188","QA-10188") -> QA-10188 | B32: RT_NM Landing Page | C32: P1 | D32: NM_LandingPage | E32: QA-10184 | F32: Jyoti Koli | G32: 4h | H32: N | I32: P3 | J32: Jyoti Koli | K32: =HYPERLINK("https://maxxton.atlassian.net/browse/QA-15375","QA-15375") -> QA-15375 | L32: Created on 2023-10-20 for release 2023_Week_43
A33: =HYPERLINK("https://maxxton.atlassian.net/browse/QA-10189","QA-10189") -> QA-10189 | B33: RT_NM General Test Cases | C33: P1 | D33: NM_LandingPage | E33: QA-10184 | F33: Jyoti Koli | G33: 4h | H33: N | I33: P3 | J33: Jyoti Koli | K33: =HYPERLINK("https://maxxton.atlassian.net/browse/QA-10281","QA-10281") -> QA-10281 | L33: Created on 2022-09-12 for release 2022_Week_37
A34: =HYPERLINK("https://maxxton.atlassian.net/browse/QA-10311","QA-10311") -> QA-10311 | B34: RT_NM Creating Manual task General | C34: P1 | D34: NM_Task | E34: QA-10184 | F34: Jyoti Koli | G34: 2h | H34: N | I34: P1 | J34: Jyoti Koli | L34: New Test Case Uploaded on 2022-09-16
A35: =HYPERLINK("https://maxxton.atlassian.net/browse/QA-10312","QA-10312") -> QA-10312 | B35: RT_NM Creating Periodic task Functional | C35: P1 | D35: NM_Task | E35: QA-10184 | F35: Jyoti Koli | G35: 3h | H35: N | I35: P1 | J35: Jyoti Koli | L35: New Test Case Uploaded on 2022-09-16

Sheet Content
F2: Total Test Cases | G2: =countifs(A:A,"<>NEW",A:A,"<>")-1 -> 25
F3: Schedule? Y | G3: =countif(H:H,"=Y") -> 24
F4: New Test Cases | G4: =COUNTIF(A:A,"=NEW") -> 0
A6: Key | B6: Summary | C6: Priority | D6: Component | E6: Epic Link | F6: Test Case Assignee | G6: Estimate | H6: Schedule ? | I6: Execution Priority | J6: Execution By | K6: Test Result Ticket | L6: Comments | M6: Original Estimates | N6: Remaining Estimates | O6: Comments
A7: QA-3120 | B7: RT_Locations | C7: P3 | D7: ContMgmt_Locations | E7: QA-3119 | F7: Vinay Baligar | G7: 60m | H7: Y | I7: P3 | J7: Vinay Baligar | K7: =HYPERLINK("https://maxxton.atlassian.net/browse/QA-28928","QA-28928") -> QA-28928 | L7: Created on 2026-03-20 for release 2026_Week_13 | M7: 1h 20m | N7: 25m
A8: QA-3121 | B8: RT_Accomodation Type | C8: P3 | D8: ContMgmt_AccoType | E8: QA-3119 | F8: Shubham Pasalkar | G8: 60m | H8: Y | I8: P3 | J8: Shubham Pasalkar | K8: =HYPERLINK("https://maxxton.atlassian.net/browse/QA-28929","QA-28929") -> QA-28929 | L8: Created on 2026-03-20 for release 2026_Week_13 | M8: 2h | N8: 40m
A9: QA-3122 | B9: RT_Units | C9: P3 | D9: ContMgmt_Units | E9: QA-3119 | F9: Shubham Pasalkar | G9: 60m | H9: Y | I9: P3 | J9: Shubham Pasalkar | K9: =HYPERLINK("https://maxxton.atlassian.net/browse/QA-28930","QA-28930") -> QA-28930 | L9: Created on 2026-03-20 for release 2026_Week_13 | M9: 1h | N9: 20m
A10: QA-3123 | B10: RT_Contacts | C10: P3 | D10: ContMgmt_Contacts | E10: QA-3119 | F10: Shubham Pasalkar | G10: 60m | H10: Y | I10: P3 | J10: Shubham Pasalkar | K10: =HYPERLINK("https://maxxton.atlassian.net/browse/QA-28931","QA-28931") -> QA-28931 | L10: Created on 2026-03-20 for release 2026_Week_13 | M10: 50m | N10: 15m
A11: QA-3124 | B11: RT_Amenities | C11: P3 | D11: ContMgmt_Amenities | E11: QA-3119 | F11: Vinay Baligar | G11: 60m | H11: Y | I11: P3 | J11: Vinay Baligar | K11: =HYPERLINK("https://maxxton.atlassian.net/browse/QA-28932","QA-28932") -> QA-28932 | L11: Created on 2026-03-20 for release 2026_Week_13 | M11: 1h | N11: 20m
A12: QA-3125 | B12: RT_InfoTexts | C12: P3 | D12: ContMgmt_InfoText | E12: QA-3119 | F12: Vinay Baligar | G12: 60m | H12: Y | I12: P3 | J12: Vinay Baligar | K12: =HYPERLINK("https://maxxton.atlassian.net/browse/QA-28933","QA-28933") -> QA-28933 | L12: Created on 2026-03-20 for release 2026_Week_13 | M12: 1h | N12: 30m
A13: QA-3126 | B13: RT_Media_Documentation | C13: P3 | D13: ContMgmt_Media | E13: QA-3119 | F13: Shubham Pasalkar | G13: 60m | H13: Y | I13: P3 | J13: Shubham Pasalkar | K13: =HYPERLINK("https://maxxton.atlassian.net/browse/QA-28934","QA-28934") -> QA-28934 | L13: Created on 2026-03-20 for release 2026_Week_13 | M13: 1h 10m | N13: 1h 10m | O13: Uploading media and documents is still out of scope
A14: QA-3127 | B14: RT_Memo | C14: P3 | D14: ContMgmt_Memo | E14: QA-3119 | F14: Vinay Baligar | G14: 60m | H14: Y | I14: P3 | J14: Vinay Baligar | K14: =HYPERLINK("https://maxxton.atlassian.net/browse/QA-28935","QA-28935") -> QA-28935 | L14: Created on 2026-03-20 for release 2026_Week_13 | M14: 50m | N14: 25m
A15: QA-3128 | B15: RT_Add-On | C15: P3 | D15: ContMgmt_AddOns | E15: QA-3119 | F15: Shubham Pasalkar | G15: 60m | H15: Y | I15: P3 | J15: Vinay Baligar | K15: =HYPERLINK("https://maxxton.atlassian.net/browse/QA-28936","QA-28936") -> QA-28936 | L15: Created on 2026-03-20 for release 2026_Week_13 | M15: 2h | N15: 45m
A16: QA-3129 | B16: RT_Fields | C16: P3 | D16: ContMgmt_Fields | E16: QA-3119 | F16: Shubham Pasalkar | G16: 60m | H16: Y | I16: P3 | J16: Vinay Baligar | K16: =HYPERLINK("https://maxxton.atlassian.net/browse/QA-28937","QA-28937") -> QA-28937 | L16: Created on 2026-03-20 for release 2026_Week_13 | M16: 1h | N16: 25m
A17: QA-3130 | B17: RT_Representation Set | C17: P3 | D17: ContMgmt_RepresentationSet | E17: QA-3119 | F17: Shubham Pasalkar | G17: 60m | H17: Y | I17: P3 | J17: Vinay Baligar | K17: =HYPERLINK("https://maxxton.atlassian.net/browse/QA-28938","QA-28938") -> QA-28938 | L17: Created on 2026-03-20 for release 2026_Week_13 | M17: 40m | N17: 20m
A18: QA-3131 | B18: RT_DC Groups | C18: P3 | D18: ContMgmt_DCGroups | E18: QA-3119 | F18: Shubham Pasalkar | G18: 60m | H18: Y | I18: P3 | J18: Shubham Pasalkar | K18: =HYPERLINK("https://maxxton.atlassian.net/browse/QA-28939","QA-28939") -> QA-28939 | L18: Created on 2026-03-20 for release 2026_Week_13 | M18: 1h | N18: 20m | O18: Linking and unlinking of DCs and DC group at various places
A19: QA-3132 | B19: RT_Import | C19: P3 | D19: ContMgmt_Imports | E19: QA-3119 | F19: Shubham Pasalkar | G19: 60m | H19: Y | I19: P3 | J19: Vinay Baligar | K19: =HYPERLINK("https://maxxton.atlassian.net/browse/QA-28940","QA-28940") -> QA-28940 | L19: Created on 2026-03-20 for release 2026_Week_13 | M19: 1h 15m | N19: 1h 15m | O19: Out of scope
A20: QA-3133 | B20: RT_Batch Update | C20: P3 | D20: ContMgmt_BatchUpdates | E20: QA-3119 | F20: Shubham Pasalkar | G20: 60m | H20: Y | I20: P3 | J20: Vinay Baligar | K20: =HYPERLINK("https://maxxton.atlassian.net/browse/QA-28941","QA-28941") -> QA-28941 | L20: Created on 2026-03-20 for release 2026_Week_13 | M20: 1h | N20: 1h | O20: Major part is not automated/out of scope
A21: QA-3134 | B21: RT_Other Config | C21: P3 | D21: ContMgmt_OtherConfig | E21: QA-3119 | F21: Vinay Baligar | G21: 60m | H21: Y | I21: P3 | J21: Vinay Baligar | K21: =HYPERLINK("https://maxxton.atlassian.net/browse/QA-28942","QA-28942") -> QA-28942 | L21: Created on 2026-03-20 for release 2026_Week_13 | M21: 1h 20m | N21: 40m
A22: QA-5072 | B22: RT_Dash Board | C22: P3 | D22: ContMgmt_Dashboard | E22: QA-3119 | F22: Shubham Pasalkar | G22: 60m | H22: Y | I22: P3 | J22: Shubham Pasalkar | K22: =HYPERLINK("https://maxxton.atlassian.net/browse/QA-28943","QA-28943") -> QA-28943 | L22: Created on 2026-03-20 for release 2026_Week_13 | M22: 1h | N22: 1h | O22: Validate export results and filters
A23: QA-5073 | B23: RT_Subject Categories | C23: P3 | D23: ContMgmt_Categories | E23: QA-3119 | F23: Shubham Pasalkar | G23: 60m | H23: Y | I23: P3 | J23: Shubham Pasalkar | K23: =HYPERLINK("https://maxxton.atlassian.net/browse/QA-28944","QA-28944") -> QA-28944 | L23: Created on 2026-03-20 for release 2026_Week_13 | M23: 1h | N23: 20m
A24: QA-5074 | B24: RT_Other Categories | C24: P3 | D24: ContMgmt_Categories | E24: QA-3119 | F24: Vinay Baligar | G24: 60m | H24: Y | I24: P3 | J24: Shubham Pasalkar | K24: =HYPERLINK("https://maxxton.atlassian.net/browse/QA-28945","QA-28945") -> QA-28945 | L24: Created on 2026-03-20 for release 2026_Week_13 | M24: 1h 20m | N24: 25m
A25: QA-5075 | B25: RT_API User | C25: P3 | D25: MXTS-BackOffice Manager | E25: QA-72 | F25: Shubham Pasalkar | G25: 60m | H25: N | I25: P3 | J25: Shubham Pasalkar | K25: QA-9294 | L25: Created on 2022-07-01 for release 2022_Week_27
A26: QA-5076 | B26: RT_Employee_Contact Person | C26: P3 | D26: MXTS-BackOffice Manager | E26: QA-72 | F26: Shubham Pasalkar | G26: 60m | H26: Y | I26: P3 | J26: Vinay Baligar | K26: =HYPERLINK("https://maxxton.atlassian.net/browse/QA-28946","QA-28946") -> QA-28946 | L26: Created on 2026-03-20 for release 2026_Week_13 | M26: 1h 30m | N26: 40m
A27: QA-5077 | B27: RT_Employee_Batch Update | C27: P3 | D27: MXTS-BackOffice Manager | E27: QA-72 | F27: Shubham Pasalkar | G27: 60m | H27: Y | I27: P3 | J27: Vinay Baligar | K27: =HYPERLINK("https://maxxton.atlassian.net/browse/QA-28947","QA-28947") -> QA-28947 | L27: Created on 2026-03-20 for release 2026_Week_13 | M27: 45m | N27: 45m | O27: Major part not automated/out of scope
A28: QA-7252 | B28: RT_Export | C28: P3 | D28: ContMgmt_Export | E28: QA-3119 | F28: Shubham Pasalkar | G28: 60m | H28: Y | I28: P3 | J28: Shubham Pasalkar | K28: =HYPERLINK("https://maxxton.atlassian.net/browse/QA-28948","QA-28948") -> QA-28948 | L28: Created on 2026-03-20 for release 2026_Week_13 | M28: 1h | N28: 1h | O28: Exporting Excel files and verifying it is out of automation scope
A29: =HYPERLINK("https://maxxton.atlassian.net/browse/QA-9482","QA-9482") -> QA-9482 | B29: RT_Activities | C29: P3 | D29: ContMgmt_Activities | E29: QA-3119 | F29: Vinay Baligar | G29: 60m | H29: Y | I29: P3 | J29: Vinay Baligar | K29: =HYPERLINK("https://maxxton.atlassian.net/browse/QA-28949","QA-28949") -> QA-28949 | L29: Created on 2026-03-20 for release 2026_Week_13 | M29: 1h | N29: 25m
A30: =HYPERLINK("https://maxxton.atlassian.net/browse/QA-9483","QA-9483") -> QA-9483 | B30: RT_Priority Management | C30: P3 | D30: ContMgmt_PriorityMgmt | E30: QA-3119 | F30: Vinay Baligar | G30: 60m | H30: Y | I30: P3 | J30: Shubham Pasalkar | K30: =HYPERLINK("https://maxxton.atlassian.net/browse/QA-28950","QA-28950") -> QA-28950 | L30: Created on 2026-03-20 for release 2026_Week_13 | M30: 2h | N30: 1h 20m | O30: As many test cases were failing due to revamp and new features in the module
A31: QA-17142 | B31: RT_Accommodation type groups | C31: P3 | D31: ContMgmt_OtherConfig | E31: QA-3119 | F31: Vinay Baligar | G31: 20m | H31: Y | I31: P3 | J31: Vinay Baligar | K31: =HYPERLINK("https://maxxton.atlassian.net/browse/QA-28951","QA-28951") -> QA-28951 | L31: Created on 2026-03-20 for release 2026_Week_13 | M31: 1h | N31: 25m
M34: 1680m | N34: 895m

Sheet CCM
O1: Components | P1: Epic
F2: Total Test Cases | G2: =countifs(A:A,"<>NEW",A:A,"<>")-1 -> 22 | O2: CMS-Castle BM | P2: QA-1 | Q2: Newyse Regression Test Cases
F3: Schedule? Y | G3: =countif(H:H,"=Y") -> 22 | O3: CMS-Castle MyEnv | P3: QA-24 | Q3: CMS Regression Test Cases
F4: New Test Cases | G4: =COUNTIF(A:A,"=NEW") -> 0 | O4: CMS-Contempo BM | P4: QA-25 | Q4: CMS Live Test Cases
O5: CMS-Contempo MyEnv | P5: QA-26 | Q5: CMS Sanity Test Cases
A6: Key | B6: Summary | C6: Priority | D6: Component | E6: Epic Link | F6: Test Case Assignee | G6: Estimate | H6: Schedule ? | I6: Execution Priority | J6: Execution By | K6: Test Result Ticket | L6: Comments | M6: Original Estimates | N6: Manual Estimate Work(this needs to fill in ticket) | O6: CMS-Deepcreek BM | P6: QA-54 | Q6: Newyse Live Test Cases
A7: QA-7533 | B7: RT_Customer_Merge | C7: P3 | D7: CRM_Customer | E7: QA-3535 | F7: Vicky Chauhan | G7: 1h 24m | H7: Y | I7: P3 | J7: Vicky Chauhan | K7: =HYPERLINK("https://maxxton.atlassian.net/browse/QA-28906","QA-28906") -> QA-28906 | L7: Created on 2026-03-20 for release 2026_Week_13 | M7: 2h | N7: 1h 24m | O7: CMS-Roompot BM
A8: QA-3536 | B8: RT_Customer_Overview_Page | C8: P3 | D8: CRM_Customer | E8: QA-3535 | F8: Vicky Chauhan | G8: 18m | H8: Y | I8: P3 | J8: Vicky Chauhan | K8: =HYPERLINK("https://maxxton.atlassian.net/browse/QA-28907","QA-28907") -> QA-28907 | L8: Created on 2026-03-20 for release 2026_Week_13 | M8: 2h | N8: 18m | O8: CMS-Deepcreek MyEnv | P8: QA-55 | Q8: Newyse Sanity Test Cases
A9: QA-3538 | B9: RT_Cases_Module | C9: P3 | D9: CRM_Case | E9: QA-3535 | F9: Vicky Chauhan | G9: 11m | H9: Y | I9: P3 | J9: Vicky Chauhan | K9: =HYPERLINK("https://maxxton.atlassian.net/browse/QA-28908","QA-28908") -> QA-28908 | L9: Created on 2026-03-20 for release 2026_Week_13 | M9: 1h | N9: 11m | O9: CMS-Hogenboom MyEnv | P9: QA-72 | Q9: MXTS Regression Test Cases
A10: QA-5113 | B10: RT_Customer_Care_Configuration | C10: P3 | D10: CRM_Configuration | E10: QA-3535 | F10: Vicky Chauhan | G10: 10m | H10: Y | I10: P3 | J10: Vicky Chauhan | K10: =HYPERLINK("https://maxxton.atlassian.net/browse/QA-28909","QA-28909") -> QA-28909 | L10: Created on 2026-03-20 for release 2026_Week_13 | M10: 1h | N10: 10m | O10: CMS-Krim MyEnv
A11: =HYPERLINK("https://maxxton.atlassian.net/browse/QA-10918","QA-10918") -> QA-10918 | B11: RT_Communication_Channel_Configuration | C11: P3 | D11: CRM_Configuration | E11: QA-3535 | F11: Vicky Chauhan | G11: 47m | H11: Y | I11: P3 | J11: Vicky Chauhan | K11: =HYPERLINK("https://maxxton.atlassian.net/browse/QA-28910","QA-28910") -> QA-28910 | L11: Created on 2026-03-20 for release 2026_Week_13 | M11: 2h | N11: 0h 47m | O11: CMS-Siblu MyEnv
A12: =HYPERLINK("https://maxxton.atlassian.net/browse/QA-11371","QA-11371") -> QA-11371 | B12: RT_Unified_Inbox | C12: P3 | D12: CRM_Emails | E12: QA-3535 | F12: Vicky Chauhan | G12: 1h 02m | H12: Y | I12: P3 | J12: Vicky Chauhan | K12: =HYPERLINK("https://maxxton.atlassian.net/browse/QA-28911","QA-28911") -> QA-28911 | L12: Created on 2026-03-20 for release 2026_Week_13 | M12: 3h | N12: 1h 02m | O12: MXTS-Content Manager
A13: QA-16898 | B13: RT_Loyalty_Program_Add_Points_Manually | C13: P3 | D13: CRM_Loyalty | E13: QA-3535 | F13: Vicky Chauhan | G13: 13m | H13: Y | I13: P3 | J13: Vicky Chauhan | K13: =HYPERLINK("https://maxxton.atlassian.net/browse/QA-28912","QA-28912") -> QA-28912 | L13: Created on 2026-03-20 for release 2026_Week_13 | M13: 1h 30m | N13: 13m | O13: CMS-RCN MyEnv
A14: QA-22287 | B14: RT_Whatsapp_End_to_End | C14: P3 | D14: CRM_Emails | E14: QA-3535 | F14: Vicky Chauhan | G14: 1h 30m | H14: Y | I14: P3 | J14: Vicky Chauhan | K14: =HYPERLINK("https://maxxton.atlassian.net/browse/QA-28913","QA-28913") -> QA-28913 | L14: Created on 2026-03-20 for release 2026_Week_13 | M14: 3h | N14: 1h | O14: MXTS-Reservation Manager
A15: QA-24463 | B15: RT_Loyalty_Dashboard | C15: P3 | D15: CRM_Loyalty | E15: QA-3535 | F15: Vicky Chauhan | G15: 1h 30m | H15: Y | I15: P3 | J15: Vicky Chauhan | K15: =HYPERLINK("https://maxxton.atlassian.net/browse/QA-28914","QA-28914") -> QA-28914 | L15: Created on 2026-03-20 for release 2026_Week_13 | M15: 1h 30m | N15: 1h 30m
A16: QA-5111 | B16: RT_Employee_Dashboard(V2) | C16: P3 | D16: CRM_EmployeeDashboard | E16: QA-3535 | F16: Vicky Chauhan | G16: 53m | H16: Y | I16: P3 | J16: Vicky Chauhan | K16: =HYPERLINK("https://maxxton.atlassian.net/browse/QA-28915","QA-28915") -> QA-28915 | L16: Created on 2026-03-20 for release 2026_Week_13 | M16: 1h 30m | N16: 53m | O16: MXTS-PaymentService
A17: QA-5112 | B17: RT_Supervisor_Dashboard(v2) | C17: P3 | D17: CRM_SupervisorDashboard | E17: QA-3535 | F17: Vicky Chauhan | G17: 3h | H17: Y | I17: P3 | J17: Vicky Chauhan | K17: =HYPERLINK("https://maxxton.atlassian.net/browse/QA-28916","QA-28916") -> QA-28916 | L17: Created on 2026-03-20 for release 2026_Week_13 | M17: 3h | N17: 3h
A18: QA-17158 | B18: RT_Customer_Title | C18: P3 | D18: CRM_Configuration | E18: QA-3535 | F18: Vicky Chauhan | G18: 0m | H18: Y | I18: P3 | J18: Vicky Chauhan | K18: =HYPERLINK("https://maxxton.atlassian.net/browse/QA-28917","QA-28917") -> QA-28917 | L18: Created on 2026-03-20 for release 2026_Week_13 | M18: 1h | N18: 0m | O18: CMS-Hogenboom BM | P18: QA-71 | Q18: MXTS Sanity Test Cases
A19: QA-8022 | B19: RT_Inbox_Configuration | C19: P3 | D19: CRM_Configuration | E19: QA-3535 | F19: Vicky Chauhan | G19: 0m | H19: Y | I19: P3 | J19: Vicky Chauhan | K19: =HYPERLINK("https://maxxton.atlassian.net/browse/QA-28918","QA-28918") -> QA-28918 | L19: Created on 2026-03-20 for release 2026_Week_13 | M19: 1h | N19: 0m | O19: MXTS-Owner Manager
A20: QA-3537 | B20: RT_Memos | C20: P3 | D20: CRM_Memo | E20: QA-3535 | F20: Vicky Chauhan | G20: 0m | H20: Y | I20: P3 | J20: Vicky Chauhan | K20: =HYPERLINK("https://maxxton.atlassian.net/browse/QA-28919","QA-28919") -> QA-28919 | L20: Created on 2026-03-20 for release 2026_Week_13 | M20: 1h | N20: 0m
A21: QA-12373 | B21: RT_All_Messages_Dashboard | C21: P3 | D21: CRM_Emails | E21: QA-3535 | F21: Vicky Chauhan | G21: 0m | H21: Y | I21: P3 | J21: Vicky Chauhan | K21: =HYPERLINK("https://maxxton.atlassian.net/browse/QA-28920","QA-28920") -> QA-28920 | L21: Created on 2026-03-20 for release 2026_Week_13 | M21: 1h | N21: 0m
A22: QA-24459 | B22: RT_Loyalty_Rewards | C22: P3 | D22: CRM_Loyalty | E22: QA-3535 | F22: Vicky Chauhan | G22: 2h | H22: Y | I22: P3 | J22: Vicky Chauhan | K22: =HYPERLINK("https://maxxton.atlassian.net/browse/QA-28921","QA-28921") -> QA-28921 | L22: Created on 2026-03-20 for release 2026_Week_13 | M22: 2h | N22: 0m | O22: CMS-PerfectExp BM
A23: QA-24462 | B23: RT_Cases_Workflow | C23: P3 | D23: CRM_Case | E23: QA-3535 | F23: Vicky Chauhan | G23: 2h | H23: Y | I23: P3 | J23: Vicky Chauhan | K23: =HYPERLINK("https://maxxton.atlassian.net/browse/QA-28922","QA-28922") -> QA-28922 | L23: Created on 2026-03-20 for release 2026_Week_13 | M23: 2h | N23: 0m
A24: QA-17268 | B24: RT_Redemption_Configuration | C24: P3 | D24: CRM_Configuration | E24: QA-3535 | F24: Vicky Chauhan | G24: 19m | H24: Y | I24: P3 | J24: Vicky Chauhan | K24: =HYPERLINK("https://maxxton.atlassian.net/browse/QA-28923","QA-28923") -> QA-28923 | L24: Created on 2026-03-20 for release 2026_Week_13 | M24: 1h 30m | N24: 0m | O24: MXTS-Rate Manager
A25: QA-8021 | B25: RT_Customer_Status_Configuration | C25: P3 | D25: CRM_Configuration | E25: QA-3535 | F25: Vicky Chauhan | G25: 1h 10m | H25: Y | I25: P3 | J25: Vicky Chauhan | K25: =HYPERLINK("https://maxxton.atlassian.net/browse/QA-28924","QA-28924") -> QA-28924 | L25: Created on 2026-03-20 for release 2026_Week_13 | M25: 2h | N25: 0m | O25: CMS-PerfectExp MyEnv
A26: QA-7534 | B26: RT_Customer_Search | C26: P3 | D26: CRM_Customer | E26: QA-3535 | F26: Vicky Chauhan | G26: 15m | H26: Y | I26: P3 | J26: Vicky Chauhan | K26: =HYPERLINK("https://maxxton.atlassian.net/browse/QA-28925","QA-28925") -> QA-28925 | L26: Created on 2026-03-20 for release 2026_Week_13 | M26: 1h | N26: 0m | O26: CMS-Roompot MyEnv
A27: QA-7535 | B27: RT_RM_Customer | C27: P3 | D27: CRM_Customer | E27: QA-3535 | F27: Vicky Chauhan | G27: 32m | H27: Y | I27: P3 | J27: Vicky Chauhan | K27: =HYPERLINK("https://maxxton.atlassian.net/browse/QA-28926","QA-28926") -> QA-28926 | L27: Created on 2026-03-20 for release 2026_Week_13 | M27: 2h | N27: 0m | O27: CMS-Siblu BM
A28: QA-16113 | B28: RT_Loyalty_Program_Reward_Configuration | C28: P3 | D28: CRM_Loyalty | E28: QA-3535 | F28: Vicky Chauhan | G28: 38m | H28: Y | I28: P3 | J28: Vicky Chauhan | K28: =HYPERLINK("https://maxxton.atlassian.net/browse/QA-28927","QA-28927") -> QA-28927 | L28: Created on 2026-03-20 for release 2026_Week_13 | M28: 3h | N28: 0m | O28: MXTS-Implementation Manager
M32: =IFERROR(__xludf.DUMMYFUNCTION("INT(SUMPRODUCT(IFERROR(VALUE(REGEXEXTRACT(M7:M26, ""(\d+)h"")), 0) + IFERROR(VALUE(REGEXEXTRACT(M7:M26, ""(\d+)m""))/60, 0))) & "" h "" & TEXT(MOD(SUMPRODUCT(IFERROR(VALUE(REGEXEXTRACT(M7:M26, ""(\d+)h"")), 0) + IFERROR(VALUE(REGEXEXTRACT(M7:M26, ""(\d+)m"&"""))/60, 0)), 1) * 60, ""00"") & "" m"" "),"34 h 00 m") -> 34 h 00 m | N32: =IFERROR(__xludf.DUMMYFUNCTION("INT(SUMPRODUCT(IFERROR(VALUE(REGEXEXTRACT(N7:N26, ""(\d+)h"")), 0) + IFERROR(VALUE(REGEXEXTRACT(N7:N26, ""(\d+)m""))/60, 0))) & "" h "" & TEXT(MOD(SUMPRODUCT(IFERROR(VALUE(REGEXEXTRACT(N7:N26, ""(\d+)h"")), 0) + IFERROR(VALUE(REGEXEXTRACT(N7:N26, ""(\d+)m"&"""))/60, 0)), 1) * 60, ""00"") & "" m"" "),"10 h 28 m") -> 10 h 28 m
